Workbook

Sheet Instructions
A1: MarketingResearch — Q1 Core Data Workbook
A2: Paste Workspace survey numbers into the yellow input cells. Thresholds: ≥110 important | <100 may hurt appeal.
A4: Sheet | B4: What to enter | C4: Analysis use
A5: Needs | B5: Importance scores by need × segment | C5: Sort ≥110; feature translation; peer miss risk
A6: Applications | B6: Use-pattern importance by segment | C6: Component/service fit; peer miss risk
A7: Price_WTP | B7: Max price willing to pay (ideal brand) | C7: Ceiling for Q2 pricing; margin vs elasticity
A8: Market_Potential | B8: 12-month unit potential by city × segment | C8: City attractiveness; crowding vs growth room
A9: Needs_Ranked | B9: Live links from Needs sheet | C9: Filter/sort IMPORTANT flags per segment
A10: Growth_Room | B10: Attractiveness / crowding / serveability (1–5) | C10: Competitor-focused opportunity pockets
A11: Competitor_CI | B11: Classmate tracker + research purchase log | C11: Room for growth vs peers (mainly Q2+)
A13: Primary research focus: maximize competitor (classmate) insight to find room for growth.
A14: Do not assume 25% of annual potential per quarter early — actual early demand is usually much lower.
A15: Hard Q1 finance check (elsewhere): Cash + CD ≥ $300,000 after setup decisions.
A17: Market potential formula: Potential = P(purchase) × units × # potential customers
A19: Need/application row labels are common Marketplace starters — rename to match your Workspace exactly.

Sheet Needs
A1: Customer Needs — Importance by Segment
A2: Rename labels to match Workspace. Yellow = inputs. Conditional formatting: green ≥110, red <100.
A4: Need / Benefit | B4: Recreation | C4: Mountain | D4: Speed | E4: Max | F4: Rec flag | G4: Mtn flag | H4: Spd flag | I4: Competitor miss risk (H/M/L) | J4: Notes
A5: Colorful | B5: 116 | C5: 120 | D5: 109 | E5: =IF(COUNT(B5:D5)=0,"",MAX(B5:D5)) -> 120 | F5: =IF(B5="","",IF(B5>=110,"IMPORTANT",IF(B5<100,"CAUTION",""))) -> IMPORTANT | G5: =IF(C5="","",IF(C5>=110,"IMPORTANT",IF(C5<100,"CAUTION",""))) -> IMPORTANT | H5: =IF(D5="","",IF(D5>=110,"IMPORTANT",IF(D5<100,"CAUTION","")))
A6: Fits rider's personality | B6: 116 | C6: 113 | D6: 116 | E6: =IF(COUNT(B6:D6)=0,"",MAX(B6:D6)) -> 116 | F6: =IF(B6="","",IF(B6>=110,"IMPORTANT",IF(B6<100,"CAUTION",""))) -> IMPORTANT | G6: =IF(C6="","",IF(C6>=110,"IMPORTANT",IF(C6<100,"CAUTION",""))) -> IMPORTANT | H6: =IF(D6="","",IF(D6>=110,"IMPORTANT",IF(D6<100,"CAUTION",""))) -> IMPORTANT
A7: Simple to use | B7: 121 | C7: 102 | D7: 69 | E7: =IF(COUNT(B7:D7)=0,"",MAX(B7:D7)) -> 121 | F7: =IF(B7="","",IF(B7>=110,"IMPORTANT",IF(B7<100,"CAUTION",""))) -> IMPORTANT | G7: =IF(C7="","",IF(C7>=110,"IMPORTANT",IF(C7<100,"CAUTION",""))) | H7: =IF(D7="","",IF(D7>=110,"IMPORTANT",IF(D7<100,"CAUTION",""))) -> CAUTION
A8: Safety | B8: 121 | C8: 112 | D8: 113 | E8: =IF(COUNT(B8:D8)=0,"",MAX(B8:D8)) -> 121 | F8: =IF(B8="","",IF(B8>=110,"IMPORTANT",IF(B8<100,"CAUTION",""))) -> IMPORTANT | G8: =IF(C8="","",IF(C8>=110,"IMPORTANT",IF(C8<100,"CAUTION",""))) -> IMPORTANT | H8: =IF(D8="","",IF(D8>=110,"IMPORTANT",IF(D8<100,"CAUTION",""))) -> IMPORTANT
A9: Low price point | B9: 117 | C9: 98 | D9: 70 | E9: =IF(COUNT(B9:D9)=0,"",MAX(B9:D9)) -> 117 | F9: =IF(B9="","",IF(B9>=110,"IMPORTANT",IF(B9<100,"CAUTION",""))) -> IMPORTANT | G9: =IF(C9="","",IF(C9>=110,"IMPORTANT",IF(C9<100,"CAUTION",""))) -> CAUTION | H9: =IF(D9="","",IF(D9>=110,"IMPORTANT",IF(D9<100,"CAUTION",""))) -> CAUTION
A10: Sleek | B10: 104 | C10: 83 | D10: 119 | E10: =IF(COUNT(B10:D10)=0,"",MAX(B10:D10)) -> 119 | F10: =IF(B10="","",IF(B10>=110,"IMPORTANT",IF(B10<100,"CAUTION",""))) | G10: =IF(C10="","",IF(C10>=110,"IMPORTANT",IF(C10<100,"CAUTION",""))) -> CAUTION | H10: =IF(D10="","",IF(D10>=110,"IMPORTANT",IF(D10<100,"CAUTION",""))) -> IMPORTANT
A11: Stylish | B11: 111 | C11: 118 | D11: 116 | E11: =IF(COUNT(B11:D11)=0,"",MAX(B11:D11)) -> 118 | F11: =IF(B11="","",IF(B11>=110,"IMPORTANT",IF(B11<100,"CAUTION",""))) -> IMPORTANT | G11: =IF(C11="","",IF(C11>=110,"IMPORTANT",IF(C11<100,"CAUTION",""))) -> IMPORTANT | H11: =IF(D11="","",IF(D11>=110,"IMPORTANT",IF(D11<100,"CAUTION",""))) -> IMPORTANT
A12: Easy to ride | B12: 124 | C12: 100 | D12: 102 | E12: =IF(COUNT(B12:D12)=0,"",MAX(B12:D12)) -> 124 | F12: =IF(B12="","",IF(B12>=110,"IMPORTANT",IF(B12<100,"CAUTION",""))) -> IMPORTANT | G12: =IF(C12="","",IF(C12>=110,"IMPORTANT",IF(C12<100,"CAUTION",""))) | H12: =IF(D12="","",IF(D12>=110,"IMPORTANT",IF(D12<100,"CAUTION","")))
A13: Comfortable | B13: 124 | C13: 95 | D13: 101 | E13: =IF(COUNT(B13:D13)=0,"",MAX(B13:D13)) -> 124 | F13: =IF(B13="","",IF(B13>=110,"IMPORTANT",IF(B13<100,"CAUTION",""))) -> IMPORTANT | G13: =IF(C13="","",IF(C13>=110,"IMPORTANT",IF(C13<100,"CAUTION",""))) -> CAUTION | H13: =IF(D13="","",IF(D13>=110,"IMPORTANT",IF(D13<100,"CAUTION","")))
A14: Soft ride | B14: 115 | C14: 89 | D14: 87 | E14: =IF(COUNT(B14:D14)=0,"",MAX(B14:D14)) -> 115 | F14: =IF(B14="","",IF(B14>=110,"IMPORTANT",IF(B14<100,"CAUTION",""))) -> IMPORTANT | G14: =IF(C14="","",IF(C14>=110,"IMPORTANT",IF(C14<100,"CAUTION",""))) -> CAUTION | H14: =IF(D14="","",IF(D14>=110,"IMPORTANT",IF(D14<100,"CAUTION",""))) -> CAUTION
A15: Repair, parts, support nearby | B15: 119 | C15: 121 | D15: 120 | E15: =IF(COUNT(B15:D15)=0,"",MAX(B15:D15)) -> 121 | F15: =IF(B15="","",IF(B15>=110,"IMPORTANT",IF(B15<100,"CAUTION",""))) -> IMPORTANT | G15: =IF(C15="","",IF(C15>=110,"IMPORTANT",IF(C15<100,"CAUTION",""))) -> IMPORTANT | H15: =IF(D15="","",IF(D15>=110,"IMPORTANT",IF(D15<100,"CAUTION",""))) -> IMPORTANT
A16: Can handle rough terrain | B16: 111 | C16: 128 | D16: 82 | E16: =IF(COUNT(B16:D16)=0,"",MAX(B16:D16)) -> 128 | F16: =IF(B16="","",IF(B16>=110,"IMPORTANT",IF(B16<100,"CAUTION",""))) -> IMPORTANT | G16: =IF(C16="","",IF(C16>=110,"IMPORTANT",IF(C16<100,"CAUTION",""))) -> IMPORTANT | H16: =IF(D16="","",IF(D16>=110,"IMPORTANT",IF(D16<100,"CAUTION",""))) -> CAUTION
... A34: Soften the impact of rough terrain | B34: 116 | C34: 124 | D34: 90 | E34: =IF(COUNT(B34:D34)=0,"",MAX(B34:D34)) -> 124 | F34: =IF(B34="","",IF(B34>=110,"IMPORTANT",IF(B34<100,"CAUTION",""))) -> IMPORTANT | G34: =IF(C34="","",IF(C34>=110,"IMPORTANT",IF(C34<100,"CAUTION",""))) -> IMPORTANT | H34: =IF(D34="","",IF(D34>=110,"IMPORTANT",IF(D34<100,"CAUTION",""))) -> CAUTION
A35: Easy to navigate on web site | B35: 128 | C35: 118 | D35: 123 | E35: =IF(COUNT(B35:D35)=0,"",MAX(B35:D35)) -> 128 | F35: =IF(B35="","",IF(B35>=110,"IMPORTANT",IF(B35<100,"CAUTION",""))) -> IMPORTANT | G35: =IF(C35="","",IF(C35>=110,"IMPORTANT",IF(C35<100,"CAUTION",""))) -> IMPORTANT | H35: =IF(D35="","",IF(D35>=110,"IMPORTANT",IF(D35<100,"CAUTION",""))) -> IMPORTANT | J35: Web focus
A36: Security of my credit card/identity | B36: 135 | C36: 123 | D36: 124 | E36: =IF(COUNT(B36:D36)=0,"",MAX(B36:D36)) -> 135 | F36: =IF(B36="","",IF(B36>=110,"IMPORTANT",IF(B36<100,"CAUTION",""))) -> IMPORTANT | G36: =IF(C36="","",IF(C36>=110,"IMPORTANT",IF(C36<100,"CAUTION",""))) -> IMPORTANT | H36: =IF(D36="","",IF(D36>=110,"IMPORTANT",IF(D36<100,"CAUTION",""))) -> IMPORTANT | J36: Web focus
A37: Likes to buy on the web | B37: 121 | C37: 122 | D37: 114 | E37: =IF(COUNT(B37:D37)=0,"",MAX(B37:D37)) -> 122 | F37: =IF(B37="","",IF(B37>=110,"IMPORTANT",IF(B37<100,"CAUTION",""))) -> IMPORTANT | G37: =IF(C37="","",IF(C37>=110,"IMPORTANT",IF(C37<100,"CAUTION",""))) -> IMPORTANT | H37: =IF(D37="","",IF(D37>=110,"IMPORTANT",IF(D37<100,"CAUTION",""))) -> IMPORTANT | J37: Web focus
A38: Wants human sales reps/support | B38: 133 | C38: 122 | D38: 118 | E38: =IF(COUNT(B38:D38)=0,"",MAX(B38:D38)) -> 133 | F38: =IF(B38="","",IF(B38>=110,"IMPORTANT",IF(B38<100,"CAUTION",""))) -> IMPORTANT | G38: =IF(C38="","",IF(C38>=110,"IMPORTANT",IF(C38<100,"CAUTION",""))) -> IMPORTANT | H38: =IF(D38="","",IF(D38>=110,"IMPORTANT",IF(D38<100,"CAUTION",""))) -> IMPORTANT | J38: Web focus
A39: Able to track my purchase | B39: 119 | C39: 124 | D39: 115 | E39: =IF(COUNT(B39:D39)=0,"",MAX(B39:D39)) -> 124 | F39: =IF(B39="","",IF(B39>=110,"IMPORTANT",IF(B39<100,"CAUTION",""))) -> IMPORTANT | G39: =IF(C39="","",IF(C39>=110,"IMPORTANT",IF(C39<100,"CAUTION",""))) -> IMPORTANT | H39: =IF(D39="","",IF(D39>=110,"IMPORTANT",IF(D39<100,"CAUTION",""))) -> IMPORTANT | J39: Web focus
A40: Easy to make purchase on web | B40: 127 | C40: 113 | D40: 119 | E40: =IF(COUNT(B40:D40)=0,"",MAX(B40:D40)) -> 127 | F40: =IF(B40="","",IF(B40>=110,"IMPORTANT",IF(B40<100,"CAUTION",""))) -> IMPORTANT | G40: =IF(C40="","",IF(C40>=110,"IMPORTANT",IF(C40<100,"CAUTION",""))) -> IMPORTANT | H40: =IF(D40="","",IF(D40>=110,"IMPORTANT",IF(D40<100,"CAUTION",""))) -> IMPORTANT | J40: Web focus
A43: Segment averages | B43: =_xlfn.FLOOR.MATH((IFERROR(AVERAGE(B5:B41),"")*1)) -> 115 | C43: =_xlfn.FLOOR.MATH((IFERROR(AVERAGE(C5:C41),"")*1)) -> 112 | D43: =_xlfn.FLOOR.MATH((IFERROR(AVERAGE(D5:D41),"")*1)) -> 109
A44: Segment averages, excluding web | B44: =_xlfn.FLOOR.MATH(IFERROR(AVERAGE(B5:B34),""),1) -> 112 | C44: =_xlfn.FLOOR.MATH(IFERROR(AVERAGE(C5:C34),""),1) -> 111 | D44: =_xlfn.FLOOR.MATH(IFERROR(AVERAGE(D5:D34),""),1) -> 107
A45: Segment averages, only web | B45: =_xlfn.FLOOR.MATH(IFERROR(AVERAGE(B35:B40),""),1) -> 127 | C45: =_xlfn.FLOOR.MATH(IFERROR(AVERAGE(C35:C40),""),1) -> 120 | D45: =_xlfn.FLOOR.MATH(IFERROR(AVERAGE(D35:D40),""),1) -> 118

Sheet Applications
A1: Applications / Use Patterns — Importance by Segment
A2: ≥110 = must design for | <100 = may hurt appeal if over-emphasized
A4: Application / Use | B4: Recreation | C4: Mountain | D4: Speed | E4: Max | F4: Rec flag | G4: Mtn flag | H4: Spd flag | I4: Component implications | J4: Peer miss risk
A5: Recreation | B5: 129 | C5: 115 | D5: 106 | E5: =IF(COUNT(B5:D5)=0,"",MAX(B5:D5)) -> 129 | F5: =IF(B5="","",IF(B5>=110,"IMPORTANT",IF(B5<100,"CAUTION",""))) -> IMPORTANT | G5: =IF(C5="","",IF(C5>=110,"IMPORTANT",IF(C5<100,"CAUTION",""))) -> IMPORTANT | H5: =IF(D5="","",IF(D5>=110,"IMPORTANT",IF(D5<100,"CAUTION","")))
A6: Exercise | B6: 115 | C6: 118 | D6: 121 | E6: =IF(COUNT(B6:D6)=0,"",MAX(B6:D6)) -> 121 | F6: =IF(B6="","",IF(B6>=110,"IMPORTANT",IF(B6<100,"CAUTION",""))) -> IMPORTANT | G6: =IF(C6="","",IF(C6>=110,"IMPORTANT",IF(C6<100,"CAUTION",""))) -> IMPORTANT | H6: =IF(D6="","",IF(D6>=110,"IMPORTANT",IF(D6<100,"CAUTION",""))) -> IMPORTANT
A7: Relaxation | B7: 122 | C7: 108 | D7: 102 | E7: =IF(COUNT(B7:D7)=0,"",MAX(B7:D7)) -> 122 | F7: =IF(B7="","",IF(B7>=110,"IMPORTANT",IF(B7<100,"CAUTION",""))) -> IMPORTANT | G7: =IF(C7="","",IF(C7>=110,"IMPORTANT",IF(C7<100,"CAUTION",""))) | H7: =IF(D7="","",IF(D7>=110,"IMPORTANT",IF(D7<100,"CAUTION","")))
A8: Fun | B8: 123 | C8: 115 | D8: 102 | E8: =IF(COUNT(B8:D8)=0,"",MAX(B8:D8)) -> 123 | F8: =IF(B8="","",IF(B8>=110,"IMPORTANT",IF(B8<100,"CAUTION",""))) -> IMPORTANT | G8: =IF(C8="","",IF(C8>=110,"IMPORTANT",IF(C8<100,"CAUTION",""))) -> IMPORTANT | H8: =IF(D8="","",IF(D8>=110,"IMPORTANT",IF(D8<100,"CAUTION","")))
A9: Adventure | B9: 112 | C9: 129 | D9: 117 | E9: =IF(COUNT(B9:D9)=0,"",MAX(B9:D9)) -> 129 | F9: =IF(B9="","",IF(B9>=110,"IMPORTANT",IF(B9<100,"CAUTION",""))) -> IMPORTANT | G9: =IF(C9="","",IF(C9>=110,"IMPORTANT",IF(C9<100,"CAUTION",""))) -> IMPORTANT | H9: =IF(D9="","",IF(D9>=110,"IMPORTANT",IF(D9<100,"CAUTION",""))) -> IMPORTANT
A10: Sport | B10: 81 | C10: 115 | D10: 129 | E10: =IF(COUNT(B10:D10)=0,"",MAX(B10:D10)) -> 129 | F10: =IF(B10="","",IF(B10>=110,"IMPORTANT",IF(B10<100,"CAUTION",""))) -> CAUTION | G10: =IF(C10="","",IF(C10>=110,"IMPORTANT",IF(C10<100,"CAUTION",""))) -> IMPORTANT | H10: =IF(D10="","",IF(D10>=110,"IMPORTANT",IF(D10<100,"CAUTION",""))) -> IMPORTANT
A12: Segment averages | B12: =_xlfn.FLOOR.MATH((IFERROR(AVERAGE(B5:B10),"")*1)) -> 113 | C12: =_xlfn.FLOOR.MATH((IFERROR(AVERAGE(C5:C10),"")*1)) -> 116 | D12: =_xlfn.FLOOR.MATH((IFERROR(AVERAGE(D5:D10),"")*1)) -> 112

Sheet Price_WTP
A1: Price Willing to Pay (Ideal Brand Ceiling)
A2: Treat as maximum for ideal brand. Above = fewer entrants. Elasticity unknown until test market.
A4: Segment | B4: WTP (max) | C4: vs Rec | D4: vs Mountain | E4: Price sensitivity note | F4: Peer price-war risk (H/M/L) | G4: Margin opportunity note
A5: Recreation | B5: 1100 | C5: =IF(OR($B$5="",B5=""),"",B5-$B$5) -> 0 | D5: =IF(OR($B$6="",B5=""),"",B5-$B$6) -> -265
A6: Mountain | B6: 1365 | C6: =IF(OR($B$5="",B6=""),"",B6-$B$5) -> 265 | D6: =IF(OR($B$6="",B6=""),"",B6-$B$6) -> 0
A7: Speed | B7: 1580 | C7: =IF(OR($B$5="",B7=""),"",B7-$B$5) -> 480 | D7: =IF(OR($B$6="",B7=""),"",B7-$B$6) -> 215
A9: Optional: paste graph / Workspace notes below

Sheet Market_Potential
A1: 12-Month Market Potential (Units)
A2: Potential = P(purchase) × units × # customers. Early quarterly demand usually << annual/4.
A4: City | B4: Recreation | C4: Mountain | D4: Speed | E4: City Total | F4: Naive Qtr (Total/4) | G4: Likely peer crowding (H/M/L) | H4: Growth-room note
A5: New York City | B5: 5114 | C5: 4757 | D5: 3826 | E5: =IF(COUNT(B5:D5)=0,"",SUM(B5:D5)) -> 13697 | F5: =IF(E5="","",E5/4) -> 3424.25
A6: Rio de Janeiro | B6: 4194 | C6: 3177 | D6: 1942 | E6: =IF(COUNT(B6:D6)=0,"",SUM(B6:D6)) -> 9313 | F6: =IF(E6="","",E6/4) -> 2328.25
A7: Amsterdam | B7: 5468 | C7: 3447 | D7: 3659 | E7: =IF(COUNT(B7:D7)=0,"",SUM(B7:D7)) -> 12574 | F7: =IF(E7="","",E7/4) -> 3143.5
A8: Bangalore | B8: 3491 | C8: 2439 | D8: 2447 | E8: =IF(COUNT(B8:D8)=0,"",SUM(B8:D8)) -> 8377 | F8: =IF(E8="","",E8/4) -> 2094.25
A9: Segment Total | B9: =IF(COUNT(B5:B8)=0,"",SUM(B5:B8)) -> 18267 | C9: =IF(COUNT(C5:C8)=0,"",SUM(C5:C8)) -> 13820 | D9: =IF(COUNT(D5:D8)=0,"",SUM(D5:D8)) -> 11874 | E9: =IF(COUNT(E5:E8)=0,"",SUM(E5:E8)) -> 43961 | F9: =IF(COUNT(F5:F8)=0,"",SUM(F5:F8)) -> 10990.25
A11: Segment share of total potential | B11: =IF(OR(B9="",E9="",E9=0),"",B9/E9) -> 0.4155274 | C11: =IF(OR(C9="",E9="",E9=0),"",C9/E9) -> 0.31436955 | D11: =IF(OR(D9="",E9="",E9=0),"",D9/E9) -> 0.27010305
A13: City rank by total potential (after fill):
A14: 1.
A15: 2.
A16: 3.
A17: 4.

Sheet Needs_Ranked
A1: Needs Snapshot — linked to Needs sheet
A2: After entering scores on Needs, filter each block where Flag = IMPORTANT, or sort Score descending (copy-paste values if needed).
A4: Recreation priorities | E4: Mountain priorities | I4: Speed priorities
A5: Need | B5: Score | C5: Flag | E5: Need | F5: Score | G5: Flag | I5: Need | J5: Score | K5: Flag
A6: =Needs!A5 -> Colorful | B6: =Needs!B5 -> 116 | C6: =Needs!F5 -> IMPORTANT | E6: =Needs!A5 -> Colorful | F6: =Needs!C5 -> 120 | G6: =Needs!G5 -> IMPORTANT | I6: =Needs!A5 -> Colorful | J6: =Needs!D5 -> 109 | K6: =Needs!H5
A7: =Needs!A6 -> Fits rider's personality | B7: =Needs!B6 -> 116 | C7: =Needs!F6 -> IMPORTANT | E7: =Needs!A6 -> Fits rider's personality | F7: =Needs!C6 -> 113 | G7: =Needs!G6 -> IMPORTANT | I7: =Needs!A6 -> Fits rider's personality | J7: =Needs!D6 -> 116 | K7: =Needs!H6 -> IMPORTANT
A8: =Needs!A7 -> Simple to use | B8: =Needs!B7 -> 121 | C8: =Needs!F7 -> IMPORTANT | E8: =Needs!A7 -> Simple to use | F8: =Needs!C7 -> 102 | G8: =Needs!G7 | I8: =Needs!A7 -> Simple to use | J8: =Needs!D7 -> 69 | K8: =Needs!H7 -> CAUTION
A9: =Needs!A8 -> Safety | B9: =Needs!B8 -> 121 | C9: =Needs!F8 -> IMPORTANT | E9: =Needs!A8 -> Safety | F9: =Needs!C8 -> 112 | G9: =Needs!G8 -> IMPORTANT | I9: =Needs!A8 -> Safety | J9: =Needs!D8 -> 113 | K9: =Needs!H8 -> IMPORTANT
A10: =Needs!A9 -> Low price point | B10: =Needs!B9 -> 117 | C10: =Needs!F9 -> IMPORTANT | E10: =Needs!A9 -> Low price point | F10: =Needs!C9 -> 98 | G10: =Needs!G9 -> CAUTION | I10: =Needs!A9 -> Low price point | J10: =Needs!D9 -> 70 | K10: =Needs!H9 -> CAUTION
A11: =Needs!A10 -> Sleek | B11: =Needs!B10 -> 104 | C11: =Needs!F10 | E11: =Needs!A10 -> Sleek | F11: =Needs!C10 -> 83 | G11: =Needs!G10 -> CAUTION | I11: =Needs!A10 -> Sleek | J11: =Needs!D10 -> 119 | K11: =Needs!H10 -> IMPORTANT
A12: =Needs!A11 -> Stylish | B12: =Needs!B11 -> 111 | C12: =Needs!F11 -> IMPORTANT | E12: =Needs!A11 -> Stylish | F12: =Needs!C11 -> 118 | G12: =Needs!G11 -> IMPORTANT | I12: =Needs!A11 -> Stylish | J12: =Needs!D11 -> 116 | K12: =Needs!H11 -> IMPORTANT
A13: =Needs!A12 -> Easy to ride | B13: =Needs!B12 -> 124 | C13: =Needs!F12 -> IMPORTANT | E13: =Needs!A12 -> Easy to ride | F13: =Needs!C12 -> 100 | G13: =Needs!G12 | I13: =Needs!A12 -> Easy to ride | J13: =Needs!D12 -> 102 | K13: =Needs!H12
A14: =Needs!A13 -> Comfortable | B14: =Needs!B13 -> 124 | C14: =Needs!F13 -> IMPORTANT | E14: =Needs!A13 -> Comfortable | F14: =Needs!C13 -> 95 | G14: =Needs!G13 -> CAUTION | I14: =Needs!A13 -> Comfortable | J14: =Needs!D13 -> 101 | K14: =Needs!H13
A15: =Needs!A14 -> Soft ride | B15: =Needs!B14 -> 115 | C15: =Needs!F14 -> IMPORTANT | E15: =Needs!A14 -> Soft ride | F15: =Needs!C14 -> 89 | G15: =Needs!G14 -> CAUTION | I15: =Needs!A14 -> Soft ride | J15: =Needs!D14 -> 87 | K15: =Needs!H14 -> CAUTION
A16: =Needs!A15 -> Repair, parts, support nearby | B16: =Needs!B15 -> 119 | C16: =Needs!F15 -> IMPORTANT | E16: =Needs!A15 -> Repair, parts, support nearby | F16: =Needs!C15 -> 121 | G16: =Needs!G15 -> IMPORTANT | I16: =Needs!A15 -> Repair, parts, support nearby | J16: =Needs!D15 -> 120 | K16: =Needs!H15 -> IMPORTANT
A17: =Needs!A16 -> Can handle rough terrain | B17: =Needs!B16 -> 111 | C17: =Needs!F16 -> IMPORTANT | E17: =Needs!A16 -> Can handle rough terrain | F17: =Needs!C16 -> 128 | G17: =Needs!G16 -> IMPORTANT | I17: =Needs!A16 -> Can handle rough terrain | J17: =Needs!D16 -> 82 | K17: =Needs!H16 -> CAUTION
... A25: =Needs!A24 -> Light weight | B25: =Needs!B24 -> 115 | C25: =Needs!F24 -> IMPORTANT | E25: =Needs!A24 -> Light weight | F25: =Needs!C24 -> 121 | G25: =Needs!G24 -> IMPORTANT | I25: =Needs!A24 -> Light weight | J25: =Needs!D24 -> 133 | K25: =Needs!H24 -> IMPORTANT

Sheet Growth_Room
A1: Growth Room vs Classmates (1–5 scores)
A2: Gap index = Attractiveness + Serveability − Crowding (higher = more room for growth). Yellow = inputs.
A4: Segment | B4: City / Channel | C4: Attractiveness (1–5) | D4: Expected crowding (1–5) | E4: Our serveability (1–5) | F4: Gap index | G4: Why peers may leave it | H4: Priority (H/M/L)
A5: Recreation | B5: New York | F5: =IF(COUNT(C5:E5)<3,"",C5+E5-D5)
A6: Recreation | B6: Amsterdam | F6: =IF(COUNT(C6:E6)<3,"",C6+E6-D6)
A7: Recreation | B7: Rio de Janeiro | F7: =IF(COUNT(C7:E7)<3,"",C7+E7-D7)
A8: Recreation | B8: Bangalore | F8: =IF(COUNT(C8:E8)<3,"",C8+E8-D8)
A9: Recreation | B9: Web | F9: =IF(COUNT(C9:E9)<3,"",C9+E9-D9)
A10: Mountain | B10: New York | F10: =IF(COUNT(C10:E10)<3,"",C10+E10-D10)
A11: Mountain | B11: Amsterdam | F11: =IF(COUNT(C11:E11)<3,"",C11+E11-D11)
A12: Mountain | B12: Rio de Janeiro | F12: =IF(COUNT(C12:E12)<3,"",C12+E12-D12)
A13: Mountain | B13: Bangalore | F13: =IF(COUNT(C13:E13)<3,"",C13+E13-D13)
A14: Mountain | B14: Web | F14: =IF(COUNT(C14:E14)<3,"",C14+E14-D14)
A15: Speed | B15: New York | F15: =IF(COUNT(C15:E15)<3,"",C15+E15-D15)
A16: Speed | B16: Amsterdam | F16: =IF(COUNT(C16:E16)<3,"",C16+E16-D16)
... A19: Speed | B19: Web | F19: =IF(COUNT(C19:E19)<3,"",C19+E19-D19)

Sheet Competitor_CI
A1: Competitor (Classmate) Tracker
A2: Q1: enter firm names when known. Metrics mainly from Q2+ results / purchased research.
A4: Firm | B4: Quarter | C4: Segments | D4: Cities / Web | E4: Brand Judgment notes | F4: Ad Judgment notes | G4: Price posture | H4: Share / demand served | I4: Weakness / gap for us | J4: Our response
A27: Research purchase log (competitor-first)
A28: Quarter | B28: Report bought | C28: Cost | D28: Key competitor insight | E28: Action
