Workbook

Sheet Instructions
A1: Q2Data — Unified Q2 team workbook (WeBike)
A2: Built from Q1Data. Paste new Workspace reports into yellow cells. Keep Q1 survey sheets as baseline until refreshed.
A4: Sheet | B4: Contents | C4: Decision use
A5: Needs | B5: Customer need scores by segment (from Q1; refresh if new survey) | C5: Brand Judgment / ads
A6: Applications | B6: Use-pattern importance (from Q1) | C6: Brand design / ads tone
A7: Price_WTP | B7: Ideal-brand price ceilings (from Q1) | C7: Pricing frame vs WTP
A8: Market_Potential | B8: 12-mo units by city × segment (from Q1) | C8: Demand / city #2 / capacity
A9: Sales_Channel | B9: Shop vs web posture — AMS + World web LIVE | C9: City #2 + staffing
A10: Stores_Costs | B10: Store/web setup + lease — update open status | C10: Cash / lease burn
A11: Manufacturing | B11: Fixed capacity live + OC / OT helpers | C11: Operating capacity ≤ 24/day
A12: Production_Sim | B12: Produce/demand/stockouts/utilization + printer add summary | C12: Production simulation & fixed capacity plan
A13: Cost_of_Production | B13: Unit cost by volume (Workspace Q2) | C13: Price vs COGS; volume scenarios
A14: Demand_Forecast | B14: Demand = units/SP × people; brand split; this Q + next Q | C14: OC schedule + printer planning + pricing volume
A15: Pricing | B15: Brand list price decision (Hike Bike) | C15: Price vs WTP and unit cost
... A23: Comp_Industry | B23: Industry pay + interactive packages / productivity | C23: Pay > avg; HR estimates

Sheet Q3_Advanced_BSC
A1: Advanced Balanced Scorecard — Q3 actual (all 7 firms)
A2: Exact in-sim numbers. Total Performance is the product of the nine indicators. Supersedes the chart-read BSC block in Q3_Industry_Graphs (Bike Bros 0.900 not ~2.5; Spoke'd Up 2.316 not ~1.0).
A4: Indicator | B4: Bike Bros | C4: LiteCycle | D4: WeBike | E4: BB LLC | F4: Spoke'd Up | G4: SpaceBikes | H4: MILC Bikes | I4: Min | J4: Max | K4: Average | L4: WeBike rank
A5: Total Performance | B5: 0.9 | C5: 2.765 | D5: 0.411 | E5: 21.531 | F5: 2.316 | G5: 10.753 | H5: 2.604 | I5: 0.411 | J5: 21.531 | K5: 5.8971429 | L5: 7
A6: Financial Performance | B6: 12.856 | C6: 14.84 | D6: 5.319 | E6: 37.687 | F6: 14.047 | G6: 33.398 | H6: 14.895 | I6: 5.319 | J6: 37.687 | K6: 19.006 | L6: 7
A7: Market Performance | B7: 0.085 | C7: 0.153 | D7: 0.098 | E7: 0.345 | F7: 0.172 | G7: 0.27 | H7: 0.17 | I7: 0.085 | J7: 0.345 | K7: 0.18471429 | L7: 6
A8: Marketing Effectiveness | B8: 0.765 | C8: 0.758 | D8: 0.738 | E8: 0.765 | F8: 0.66 | G8: 0.763 | H8: 0.755 | I8: 0.66 | J8: 0.765 | K8: 0.74342857 | L8: 6
A9: Investment in Future | B9: 7.401 | C9: 5.657 | D9: 6.795 | E9: 3.741 | F9: 5.601 | G9: 3.466 | H9: 5.038 | I9: 3.466 | J9: 7.401 | K9: 5.3855714 | L9: 2
A10: Wealth | B10: 0.797 | C10: 0.768 | D10: 0.668 | E10: 0.957 | F10: 0.803 | G10: 1.017 | H10: 0.806 | I10: 0.668 | J10: 1.017 | K10: 0.83085714 | L10: 7
A11: Human Resource Management | B11: 0.691 | C11: 0.732 | D11: 0.713 | E11: 0.767 | F11: 0.719 | G11: 0.735 | H11: 0.713 | I11: 0.691 | J11: 0.767 | K11: 0.72428571 | L11: 5
A12: Asset Management | B12: 0.366 | C12: 0.539 | D12: 0.353 | E12: 0.92 | F12: 0.479 | G12: 0.666 | H12: 0.473 | I12: 0.353 | J12: 0.92 | K12: 0.54228571 | L12: 7
A13: Manufacturing Productivity | B13: 0.722 | C13: 0.938 | D13: 0.938 | E13: 0.856 | F13: 0.938 | G13: 0.906 | H13: 0.995 | I13: 0.722 | J13: 0.995 | K13: 0.899 | L13: 2
A14: Financial Risk | B14: 1 | C14: 1 | D14: 1 | E14: 1 | F14: 1 | G14: 1 | H14: 1 | I14: 1 | J14: 1 | K14: 1 | L14: 1
A17: WeBike rank card | B17: Score | C17: Rank / 7 | D17: Best firm | E17: Best score | F17: Read
A18: Total Performance | B18: 0.411 | C18: 7 LAST | D18: BB LLC | E18: 21.531 | F18: 52x behind the leader; 6x behind mid-pack
A19: Financial Performance | B19: 5.319 | C19: 7 LAST | D19: BB LLC | E19: 37.687 | F19: Operating loss + 25,000 shares. Next-worst (Bike Bros) is 12.856 — we are half of last-but-one
A20: Market Performance | B20: 0.098 | C20: 6 | D20: BB LLC | E20: 0.345 | F20: Only Bike Bros (0.085) is worse. 33% stock-outs; share x fill-rate
A21: Marketing Effectiveness | B21: 0.738 | C21: 6 | D21: Bike Bros / BB LLC | E21: 0.765 | F21: 0.005 below average. Pack is 0.755–0.765; not a Q4 lever
A22: Investment in Future | B22: 6.795 | C22: 2 STRENGTH | D22: Bike Bros | E22: 7.401 | F22: Do not chase. Leaders score LOW because revenue is in the denominator
A23: Wealth | B23: 0.668 | C23: 7 LAST | D23: SpaceBikes | E23: 1.017 | F23: Cumulative losses. SpaceBikes is the only firm above 1.0
A24: Human Resource Management | B24: 0.713 | C24: 5= (tie MILC) | D24: BB LLC | E24: 0.767 | F24: Only Bike Bros (0.691) is worse. Pay is low-middle, not last
A25: Asset Management | B25: 0.353 | C25: 7 LAST | D25: BB LLC | E25: 0.92 | F25: $1.01M idle cash. Bike Bros 0.366 is almost as bad
A26: Manufacturing Productivity | B26: 0.938 | C26: 2= (tie LiteCycle, Spoke'd Up) | D26: MILC Bikes | E26: 0.995 | F26: FALSE strength: we used 100% of the 8/day we scheduled. Does not punish stock-outs
A27: Financial Risk | B27: 1 | C27: 1= (all firms) | D27: everyone | E27: 1 | F27: Nobody has debt. Zero differentiation
A30: Two-league industry (Total Performance) | B30: Score | C30: x WeBike | D30: League
A31: BB LLC | B31: 21.531 | C31: 52.4 | D31: League 1 — profitable, high share, high asset turnover
A32: SpaceBikes | B32: 10.753 | C32: 26.2 | D32: League 1
A33: LiteCycle | B33: 2.765 | C33: 6.7 | D33: League 2 — mid-pack, tightly bunched 2.3–2.8
A34: MILC Bikes | B34: 2.604 | C34: 6.3 | D34: League 2
A35: Spoke'd Up | B35: 2.316 | C35: 5.6 | D35: League 2 (chart-read had ~1.0 — WRONG)
A36: Bike Bros | B36: 0.9 | C36: 2.2 | D36: League 3 — basement (chart-read had ~2.5 — WRONG)
A37: WeBike | B37: 0.411 | C37: 1 | D37: League 3 — LAST
A40: Product identity (Total Performance = product of 9 indicators) | B40: Value
A41: Product of WeBike's 9 indicators | B41: 0.4122
A42: Reported Total Performance | B42: 0.411
A43: Match? | B43: YES
A46: If WeBike matched the industry average on ONE indicator (others held) | B46: New TP | C46: x actual | D46: Note
A47: Financial Performance | B47: 1.469 | C47: 3.57
A48: Market Performance | B48: 0.775 | C48: 1.88
A49: Marketing Effectiveness | B49: 0.414 | C49: 1.01
A50: Investment in Future | B50: 0.326 | C50: 0.79 | D50: matching average would HURT us — this is a strength
A51: Wealth | B51: 0.511 | C51: 1.24
A52: Human Resource Management | B52: 0.418 | C52: 1.02
A53: Asset Management | B53: 0.631 | C53: 1.54
A54: Manufacturing Productivity | B54: 0.394 | C54: 0.96 | D54: matching average would HURT us — this is a strength
A55: Financial Risk | B55: 0.411 | C55: 1
A56: All indicators at average (implied) | B56: 5.897 | C56: 14.3 | D56: industry mean TP is 5.897 — 14x us. Not a realistic Q4 target
A59: Path to mid-pack (~2.5, LiteCycle/MILC/Spoke'd Up) | B59: TP | C59: x actual | D59: What it takes
A60: Q3 actual | B60: 0.411 | C60: 1 | D60: baseline
A61: Serve 100% of demand (Market 0.098 → 0.150) | B61: 0.629 | C61: 1.53 | D61: schedule OC to the forecast; no printers required
A62: + Asset 0.353 → 0.55 | B62: 0.98 | C62: 2.38 | D62: deploy idle cash into revenue (people, web, ads, city #3)
A63: + Financial 5.319 → 14.8 (mid-pack) | B63: 2.727 | C63: 6.64 | D63: profitable quarter + stop issuing stock. This is the jump out of the basement
A64: Do NOT chase Investment in Future | D64: We are already 2nd. SpaceBikes is LAST on IIF (3.466) and 2nd overall. Bike Bros is BEST on IIF (7.401) and 6th overall
A65: Do NOT protect Manufacturing Productivity by under-scheduling | D65: 0.938 is what you get when you use 100% of a too-small plan. Market Performance is the indicator that saw the 204 lost units
A68: Chart-read BSC in Q3_Industry_Graphs — CORRECTIONS | B68: Graph-read TP | C68: Actual TP | D68: Error
A69: Bike Bros | B69: 2.5 | C69: 0.9 | D69: was placed in mid-pack; actually in the basement with us
A70: Spoke'd Up | B70: 1 | C70: 2.316 | D70: was placed in the basement; actually mid-pack with LiteCycle/MILC
A71: LiteCycle | B71: 2 | C71: 2.765 | D71: directionally fine, a bit low
A72: MILC Bikes | B72: 2.8 | C72: 2.604 | D72: directionally fine
A73: SpaceBikes | B73: 11 | C73: 10.753 | D73: fine
A74: BB LLC | B74: 22 | C74: 21.531 | D74: fine
A75: WeBike | B75: 0.411 | C75: 0.411 | D75: exact — we had the live scorecard for ourselves

Sheet Needs
A1: Customer Needs — Importance by Segment
A2: Rename labels to match Workspace. Yellow = inputs. Conditional formatting: green ≥110, red <100.
A4: Need / Benefit | B4: Recreation | C4: Mountain | D4: Speed | E4: Max | F4: Rec flag | G4: Mtn flag | H4: Spd flag | I4: Competitor miss risk (H/M/L) | J4: Notes
A5: Colorful | B5: 116 | C5: 120 | D5: 109 | E5: =IF(COUNT(B5:D5)=0,"",MAX(B5:D5)) | F5: =IF(B5="","",IF(B5>=110,"IMPORTANT",IF(B5<100,"CAUTION",""))) | G5: =IF(C5="","",IF(C5>=110,"IMPORTANT",IF(C5<100,"CAUTION",""))) | H5: =IF(D5="","",IF(D5>=110,"IMPORTANT",IF(D5<100,"CAUTION","")))
A6: Fits rider's personality | B6: 116 | C6: 113 | D6: 116 | E6: =IF(COUNT(B6:D6)=0,"",MAX(B6:D6)) | F6: =IF(B6="","",IF(B6>=110,"IMPORTANT",IF(B6<100,"CAUTION",""))) | G6: =IF(C6="","",IF(C6>=110,"IMPORTANT",IF(C6<100,"CAUTION",""))) | H6: =IF(D6="","",IF(D6>=110,"IMPORTANT",IF(D6<100,"CAUTION","")))
A7: Simple to use | B7: 121 | C7: 102 | D7: 69 | E7: =IF(COUNT(B7:D7)=0,"",MAX(B7:D7)) | F7: =IF(B7="","",IF(B7>=110,"IMPORTANT",IF(B7<100,"CAUTION",""))) | G7: =IF(C7="","",IF(C7>=110,"IMPORTANT",IF(C7<100,"CAUTION",""))) | H7: =IF(D7="","",IF(D7>=110,"IMPORTANT",IF(D7<100,"CAUTION","")))
A8: Safety | B8: 121 | C8: 112 | D8: 113 | E8: =IF(COUNT(B8:D8)=0,"",MAX(B8:D8)) | F8: =IF(B8="","",IF(B8>=110,"IMPORTANT",IF(B8<100,"CAUTION",""))) | G8: =IF(C8="","",IF(C8>=110,"IMPORTANT",IF(C8<100,"CAUTION",""))) | H8: =IF(D8="","",IF(D8>=110,"IMPORTANT",IF(D8<100,"CAUTION","")))
A9: Low price point | B9: 117 | C9: 98 | D9: 70 | E9: =IF(COUNT(B9:D9)=0,"",MAX(B9:D9)) | F9: =IF(B9="","",IF(B9>=110,"IMPORTANT",IF(B9<100,"CAUTION",""))) | G9: =IF(C9="","",IF(C9>=110,"IMPORTANT",IF(C9<100,"CAUTION",""))) | H9: =IF(D9="","",IF(D9>=110,"IMPORTANT",IF(D9<100,"CAUTION","")))
A10: Sleek | B10: 104 | C10: 83 | D10: 119 | E10: =IF(COUNT(B10:D10)=0,"",MAX(B10:D10)) | F10: =IF(B10="","",IF(B10>=110,"IMPORTANT",IF(B10<100,"CAUTION",""))) | G10: =IF(C10="","",IF(C10>=110,"IMPORTANT",IF(C10<100,"CAUTION",""))) | H10: =IF(D10="","",IF(D10>=110,"IMPORTANT",IF(D10<100,"CAUTION","")))
A11: Stylish | B11: 111 | C11: 118 | D11: 116 | E11: =IF(COUNT(B11:D11)=0,"",MAX(B11:D11)) | F11: =IF(B11="","",IF(B11>=110,"IMPORTANT",IF(B11<100,"CAUTION",""))) | G11: =IF(C11="","",IF(C11>=110,"IMPORTANT",IF(C11<100,"CAUTION",""))) | H11: =IF(D11="","",IF(D11>=110,"IMPORTANT",IF(D11<100,"CAUTION","")))
A12: Easy to ride | B12: 124 | C12: 100 | D12: 102 | E12: =IF(COUNT(B12:D12)=0,"",MAX(B12:D12)) | F12: =IF(B12="","",IF(B12>=110,"IMPORTANT",IF(B12<100,"CAUTION",""))) | G12: =IF(C12="","",IF(C12>=110,"IMPORTANT",IF(C12<100,"CAUTION",""))) | H12: =IF(D12="","",IF(D12>=110,"IMPORTANT",IF(D12<100,"CAUTION","")))
A13: Comfortable | B13: 124 | C13: 95 | D13: 101 | E13: =IF(COUNT(B13:D13)=0,"",MAX(B13:D13)) | F13: =IF(B13="","",IF(B13>=110,"IMPORTANT",IF(B13<100,"CAUTION",""))) | G13: =IF(C13="","",IF(C13>=110,"IMPORTANT",IF(C13<100,"CAUTION",""))) | H13: =IF(D13="","",IF(D13>=110,"IMPORTANT",IF(D13<100,"CAUTION","")))
A14: Soft ride | B14: 115 | C14: 89 | D14: 87 | E14: =IF(COUNT(B14:D14)=0,"",MAX(B14:D14)) | F14: =IF(B14="","",IF(B14>=110,"IMPORTANT",IF(B14<100,"CAUTION",""))) | G14: =IF(C14="","",IF(C14>=110,"IMPORTANT",IF(C14<100,"CAUTION",""))) | H14: =IF(D14="","",IF(D14>=110,"IMPORTANT",IF(D14<100,"CAUTION","")))
A15: Repair, parts, support nearby | B15: 119 | C15: 121 | D15: 120 | E15: =IF(COUNT(B15:D15)=0,"",MAX(B15:D15)) | F15: =IF(B15="","",IF(B15>=110,"IMPORTANT",IF(B15<100,"CAUTION",""))) | G15: =IF(C15="","",IF(C15>=110,"IMPORTANT",IF(C15<100,"CAUTION",""))) | H15: =IF(D15="","",IF(D15>=110,"IMPORTANT",IF(D15<100,"CAUTION","")))
A16: Can handle rough terrain | B16: 111 | C16: 128 | D16: 82 | E16: =IF(COUNT(B16:D16)=0,"",MAX(B16:D16)) | F16: =IF(B16="","",IF(B16>=110,"IMPORTANT",IF(B16<100,"CAUTION",""))) | G16: =IF(C16="","",IF(C16>=110,"IMPORTANT",IF(C16<100,"CAUTION",""))) | H16: =IF(D16="","",IF(D16>=110,"IMPORTANT",IF(D16<100,"CAUTION","")))
... A34: Soften the impact of rough terrain | B34: 116 | C34: 124 | D34: 90 | E34: =IF(COUNT(B34:D34)=0,"",MAX(B34:D34)) | F34: =IF(B34="","",IF(B34>=110,"IMPORTANT",IF(B34<100,"CAUTION",""))) | G34: =IF(C34="","",IF(C34>=110,"IMPORTANT",IF(C34<100,"CAUTION",""))) | H34: =IF(D34="","",IF(D34>=110,"IMPORTANT",IF(D34<100,"CAUTION","")))
A35: Easy to navigate on web site | B35: 128 | C35: 118 | D35: 123 | E35: =IF(COUNT(B35:D35)=0,"",MAX(B35:D35)) | F35: =IF(B35="","",IF(B35>=110,"IMPORTANT",IF(B35<100,"CAUTION",""))) | G35: =IF(C35="","",IF(C35>=110,"IMPORTANT",IF(C35<100,"CAUTION",""))) | H35: =IF(D35="","",IF(D35>=110,"IMPORTANT",IF(D35<100,"CAUTION",""))) | J35: Web focus
A36: Security of my credit card/identity | B36: 135 | C36: 123 | D36: 124 | E36: =IF(COUNT(B36:D36)=0,"",MAX(B36:D36)) | F36: =IF(B36="","",IF(B36>=110,"IMPORTANT",IF(B36<100,"CAUTION",""))) | G36: =IF(C36="","",IF(C36>=110,"IMPORTANT",IF(C36<100,"CAUTION",""))) | H36: =IF(D36="","",IF(D36>=110,"IMPORTANT",IF(D36<100,"CAUTION",""))) | J36: Web focus
A37: Likes to buy on the web | B37: 121 | C37: 122 | D37: 114 | E37: =IF(COUNT(B37:D37)=0,"",MAX(B37:D37)) | F37: =IF(B37="","",IF(B37>=110,"IMPORTANT",IF(B37<100,"CAUTION",""))) | G37: =IF(C37="","",IF(C37>=110,"IMPORTANT",IF(C37<100,"CAUTION",""))) | H37: =IF(D37="","",IF(D37>=110,"IMPORTANT",IF(D37<100,"CAUTION",""))) | J37: Web focus
A38: Wants human sales reps/support | B38: 133 | C38: 122 | D38: 118 | E38: =IF(COUNT(B38:D38)=0,"",MAX(B38:D38)) | F38: =IF(B38="","",IF(B38>=110,"IMPORTANT",IF(B38<100,"CAUTION",""))) | G38: =IF(C38="","",IF(C38>=110,"IMPORTANT",IF(C38<100,"CAUTION",""))) | H38: =IF(D38="","",IF(D38>=110,"IMPORTANT",IF(D38<100,"CAUTION",""))) | J38: Web focus
A39: Able to track my purchase | B39: 119 | C39: 124 | D39: 115 | E39: =IF(COUNT(B39:D39)=0,"",MAX(B39:D39)) | F39: =IF(B39="","",IF(B39>=110,"IMPORTANT",IF(B39<100,"CAUTION",""))) | G39: =IF(C39="","",IF(C39>=110,"IMPORTANT",IF(C39<100,"CAUTION",""))) | H39: =IF(D39="","",IF(D39>=110,"IMPORTANT",IF(D39<100,"CAUTION",""))) | J39: Web focus
A40: Easy to make purchase on web | B40: 127 | C40: 113 | D40: 119 | E40: =IF(COUNT(B40:D40)=0,"",MAX(B40:D40)) | F40: =IF(B40="","",IF(B40>=110,"IMPORTANT",IF(B40<100,"CAUTION",""))) | G40: =IF(C40="","",IF(C40>=110,"IMPORTANT",IF(C40<100,"CAUTION",""))) | H40: =IF(D40="","",IF(D40>=110,"IMPORTANT",IF(D40<100,"CAUTION",""))) | J40: Web focus
A43: Segment averages | B43: =_xlfn.FLOOR.MATH((IFERROR(AVERAGE(B5:B41),"")*1)) | C43: =_xlfn.FLOOR.MATH((IFERROR(AVERAGE(C5:C41),"")*1)) | D43: =_xlfn.FLOOR.MATH((IFERROR(AVERAGE(D5:D41),"")*1))
A44: Segment averages, excluding web | B44: =_xlfn.FLOOR.MATH(IFERROR(AVERAGE(B5:B34),""),1) | C44: =_xlfn.FLOOR.MATH(IFERROR(AVERAGE(C5:C34),""),1) | D44: =_xlfn.FLOOR.MATH(IFERROR(AVERAGE(D5:D34),""),1)
A45: Segment averages, only web | B45: =_xlfn.FLOOR.MATH(IFERROR(AVERAGE(B35:B40),""),1) | C45: =_xlfn.FLOOR.MATH(IFERROR(AVERAGE(C35:C40),""),1) | D45: =_xlfn.FLOOR.MATH(IFERROR(AVERAGE(D35:D40),""),1)

Sheet Applications
A1: Applications / Use Patterns — Importance by Segment
A2: ≥110 = must design for | <100 = may hurt appeal if over-emphasized
A4: Application / Use | B4: Recreation | C4: Mountain | D4: Speed | E4: Max | F4: Rec flag | G4: Mtn flag | H4: Spd flag | I4: Component implications | J4: Peer miss risk
A5: Recreation | B5: 129 | C5: 115 | D5: 106 | E5: =IF(COUNT(B5:D5)=0,"",MAX(B5:D5)) | F5: =IF(B5="","",IF(B5>=110,"IMPORTANT",IF(B5<100,"CAUTION",""))) | G5: =IF(C5="","",IF(C5>=110,"IMPORTANT",IF(C5<100,"CAUTION",""))) | H5: =IF(D5="","",IF(D5>=110,"IMPORTANT",IF(D5<100,"CAUTION","")))
A6: Exercise | B6: 115 | C6: 118 | D6: 121 | E6: =IF(COUNT(B6:D6)=0,"",MAX(B6:D6)) | F6: =IF(B6="","",IF(B6>=110,"IMPORTANT",IF(B6<100,"CAUTION",""))) | G6: =IF(C6="","",IF(C6>=110,"IMPORTANT",IF(C6<100,"CAUTION",""))) | H6: =IF(D6="","",IF(D6>=110,"IMPORTANT",IF(D6<100,"CAUTION","")))
A7: Relaxation | B7: 122 | C7: 108 | D7: 102 | E7: =IF(COUNT(B7:D7)=0,"",MAX(B7:D7)) | F7: =IF(B7="","",IF(B7>=110,"IMPORTANT",IF(B7<100,"CAUTION",""))) | G7: =IF(C7="","",IF(C7>=110,"IMPORTANT",IF(C7<100,"CAUTION",""))) | H7: =IF(D7="","",IF(D7>=110,"IMPORTANT",IF(D7<100,"CAUTION","")))
A8: Fun | B8: 123 | C8: 115 | D8: 102 | E8: =IF(COUNT(B8:D8)=0,"",MAX(B8:D8)) | F8: =IF(B8="","",IF(B8>=110,"IMPORTANT",IF(B8<100,"CAUTION",""))) | G8: =IF(C8="","",IF(C8>=110,"IMPORTANT",IF(C8<100,"CAUTION",""))) | H8: =IF(D8="","",IF(D8>=110,"IMPORTANT",IF(D8<100,"CAUTION","")))
A9: Adventure | B9: 112 | C9: 129 | D9: 117 | E9: =IF(COUNT(B9:D9)=0,"",MAX(B9:D9)) | F9: =IF(B9="","",IF(B9>=110,"IMPORTANT",IF(B9<100,"CAUTION",""))) | G9: =IF(C9="","",IF(C9>=110,"IMPORTANT",IF(C9<100,"CAUTION",""))) | H9: =IF(D9="","",IF(D9>=110,"IMPORTANT",IF(D9<100,"CAUTION","")))
A10: Sport | B10: 81 | C10: 115 | D10: 129 | E10: =IF(COUNT(B10:D10)=0,"",MAX(B10:D10)) | F10: =IF(B10="","",IF(B10>=110,"IMPORTANT",IF(B10<100,"CAUTION",""))) | G10: =IF(C10="","",IF(C10>=110,"IMPORTANT",IF(C10<100,"CAUTION",""))) | H10: =IF(D10="","",IF(D10>=110,"IMPORTANT",IF(D10<100,"CAUTION","")))
A12: Segment averages | B12: =_xlfn.FLOOR.MATH((IFERROR(AVERAGE(B5:B10),"")*1)) | C12: =_xlfn.FLOOR.MATH((IFERROR(AVERAGE(C5:C10),"")*1)) | D12: =_xlfn.FLOOR.MATH((IFERROR(AVERAGE(D5:D10),"")*1))

Sheet Price_WTP
A1: Price Willing to Pay (Ideal Brand Ceiling)
A2: Treat as maximum for ideal brand. Above = fewer entrants. Elasticity unknown until test market.
A4: Segment | B4: WTP (max) | C4: vs Rec | D4: vs Mountain | E4: Price sensitivity note | F4: Peer price-war risk (H/M/L) | G4: Margin opportunity note
A5: Recreation | B5: 1100 | C5: =IF(OR($B$5="",B5=""),"",B5-$B$5) | D5: =IF(OR($B$6="",B5=""),"",B5-$B$6) | E5: Q1, we expect all target here | F5: H
A6: Mountain | B6: 1365 | C6: =IF(OR($B$5="",B6=""),"",B6-$B$5) | D6: =IF(OR($B$6="",B6=""),"",B6-$B$6) | E6: Someone might monopolize Q1 | F6: M
A7: Speed | B7: 1580 | C7: =IF(OR($B$5="",B7=""),"",B7-$B$5) | D7: =IF(OR($B$6="",B7=""),"",B7-$B$6) | E7: Q1, we expect no target here | F7: L
A9: Optional: paste graph / Workspace notes below

Sheet Market_Potential
A1: 12-Month Market Potential (Units)
A2: Potential = P(purchase) × units × # customers. Early quarterly demand usually << annual/4.
A3: See Sales_Channel sheet for shop vs web strategy (linked to these city sizes). First store LOCKED: Amsterdam.
A4: City | B4: Recreation | C4: Mountain | D4: Speed | E4: City Total | F4: Naive Qtr (Total/4) | G4: Likely peer crowding (H/M/L) | H4: Growth-room note
A5: New York City | B5: 5114 | C5: 4757 | D5: 3826 | E5: =IF(COUNT(B5:D5)=0,"",SUM(B5:D5)) | F5: =IF(E5="","",E5/4)
A6: Rio de Janeiro | B6: 4194 | C6: 3177 | D6: 1942 | E6: =IF(COUNT(B6:D6)=0,"",SUM(B6:D6)) | F6: =IF(E6="","",E6/4)
A7: Amsterdam | B7: 5468 | C7: 3447 | D7: 3659 | E7: =IF(COUNT(B7:D7)=0,"",SUM(B7:D7)) | F7: =IF(E7="","",E7/4)
A8: Bangalore | B8: 3491 | C8: 2439 | D8: 2447 | E8: =IF(COUNT(B8:D8)=0,"",SUM(B8:D8)) | F8: =IF(E8="","",E8/4)
A9: Segment Total | B9: =IF(COUNT(B5:B8)=0,"",SUM(B5:B8)) | C9: =IF(COUNT(C5:C8)=0,"",SUM(C5:C8)) | D9: =IF(COUNT(D5:D8)=0,"",SUM(D5:D8)) | E9: =IF(COUNT(E5:E8)=0,"",SUM(E5:E8)) | F9: =IF(COUNT(F5:F8)=0,"",SUM(F5:F8))
A11: Segment share of total potential | B11: =IF(OR(B9="",E9="",E9=0),"",B9/E9) | C11: =IF(OR(C9="",E9="",E9=0),"",C9/E9) | D11: =IF(OR(D9="",E9="",E9=0),"",D9/E9)
A13: City rank by total potential (after fill):
A14: 1.
A15: 2.
A16: 3.
A17: 4.

Sheet Sales_Channel
A1: Sales Channel Strategy — connects to Market_Potential
A2: Company-operated shops + web. LIVE for test market: Amsterdam + World web. Schedule city #2 this quarter.
A4: Market size for channel choice (linked to Market_Potential)
A5: City | B5: Recreation | C5: Mountain | D5: Speed | E5: City Total | F5: Locked first store? | G5: Channel note
A6: New York City | B6: =Market_Potential!B5 | C6: =Market_Potential!C5 | D6: =Market_Potential!D5 | E6: =SUM(B6:D6) | F6: No | G6: Largest overall; likely peer crowding
A7: Rio de Janeiro | B7: =Market_Potential!B6 | C7: =Market_Potential!C6 | D7: =Market_Potential!D6 | E7: =SUM(B7:D7) | F7: No | G7: Smaller Speed pool
A8: Amsterdam | B8: =Market_Potential!B7 | C8: =Market_Potential!C7 | D8: =Market_Potential!D7 | E8: =SUM(B8:D8) | F8: YES — Q1 LOCKED | G8: Largest Recreation pool; team lock
A9: Bangalore | B9: =Market_Potential!B8 | C9: =Market_Potential!C8 | D9: =Market_Potential!D8 | E9: =SUM(B9:D9) | F9: No | G9: Smallest overall; cost may be lower
A11: Brick-and-mortar vs Web
A12: Channel | B12: Advantages | C12: Disadvantages | D12: Our Q1 posture
A13: Brick-and-mortar bike shop | B13: Touch/feel/test ride; segment-specialist sales; custom fit; full control of brand/price/ads/sales; no independent-retailer surprises | C13: Expensive to open/run; many details; productivity drop if >~15 display bikes or >~15 salespeople | D13: LOCKED — Amsterdam Q1
A14: Web sales center | B14: One site serves all geos; broader metro reach; multilingual staff; demand beyond one store footprint | C14: No touch/feel; harder phone vs in-person; must wait for customer to find you (ads/SEM); staff wait for calls | D14: LIVE — World Market
A16: Sim decision tips
A17: 1. Both channels are expensive to start together — may open one first, then expand.
A18: 2. Web and stores cannibalize each other → lower productivity per channel; dual channels may still raise TOTAL demand.
A19: 3. Segment preferences differ for web vs store — Rec especially wants humans + web (see Needs).
A20: 4. Must schedule first channel in Q1 (takes a full quarter) to test in Q2.
A21: 5. Recommended: one store for test marketing; add more after learning.
A22: 6. Store ~3,200 sq ft / 300 m²: display ~50%, fitting ~20%, service ~15%, counter/office/storage ~15%. Middle-class area near major road.
A23: 7. POP displays + several bikes; fitting area for custom measurements.
A24: 8. Productivity risk if more than ~15 bikes OR ~15 salespeople in one store.
A26: Web order fulfillment
A27: 1. Daily web orders (dimensions + preferences) → single fabrication facility.
A28: 2. 3D modeling software generates customized frame specs.
... A33: Strategy worksheet (yellow = team inputs)
A34: Question | B34: Team answer | C34: Data link
A35: Primary channel for Q2 test? | B35: Amsterdam brick-and-mortar (LIVE) | C35: Market_Potential
A36: Open web sales center in Q1? | B36: YES — LIVE (World Market) | C36: Needs web scores; cost + cannibalization tips
A37: First-store segment specialist focus? | B37: Mountain primary (Hike Bike) | C37: decisions.md / Q2Data Pricing
A38: Q2–Q4 city order? | C38: NYC, Rio, Bangalore remaining
A39: Dual-channel cannibalization plan? | C39: Sim: total demand may still rise
A40: Store productivity caps (# bikes / # sales)? | C40: Sim guideline: avoid >15 / >15

Sheet Stores_Costs
A1: Sales outlets and web — setup and lease costs
A2: Full quarter to open. LIVE: Amsterdam store + World web. City #2 undecided (NYC candidate). | B2: Full quarter to open. LIVE: Amsterdam + World web. City #2 LOCKED: Rio (schedule Q2 → live Q3).
A4: Brick-and-mortar stores
A5: City | B5: Status | C5: Setup/Close Cost | D5: Quarterly Lease | E5: 12-mo Rec potential | F5: Notes
A6: New York City | B6: closed | C6: 200000 | D6: 62000 | E6: 5114 | F6: Highest setup+lease
A7: Rio de Janeiro | B7: SCHEDULED (Q2) → OPEN next Q | C7: 90000 | D7: 17000 | E7: 4194 | F7: LOCKED Q2 city #2 — setup $90k this Q; lease when live
A8: Amsterdam | B8: OPEN (Q2 live) | C8: 136000 | D8: 44000 | E8: 5468
A9: Bangalore | B9: closed | C9: 84000 | D9: 13000 | E9: 3491 | F9: Lowest store costs; also fab city
A11: Web sales center
A12: Region | B12: City | C12: Status | D12: Setup/Close Cost | E12: Quarterly Lease | F12: Notes
A13: World Market | B13: OPEN (Q2 live) | C13: closed | D13: 150000 | E13: 60000 | F13: World Market web live; serves all geos
A15: Q1 cash sketch (major outlays only)
A16: Scenario | B16: Printers | C16: Printer $ | D16: AMS setup | E16: Web setup | F16: Total major outlay | G16: Cash left from $1.5M | H16: >= $300k floor?
A17: AMS only + 2 printers | B17: 2 | C17: 480000 | D17: 136000 | E17: 0 | F17: 616000 | G17: 884000 | H17: YES
A18: AMS only + 3 printers | B18: 3 | C18: 720000 | D18: 136000 | E18: 0 | F18: 856000 | G18: 644000 | H18: YES
A19: AMS + web + 2 printers | B19: 2 | C19: 480000 | D19: 136000 | E19: 150000 | F19: 766000 | G19: 734000 | H19: YES
A20: AMS + web + 3 printers | B20: 3 | C20: 720000 | D20: 136000 | E20: 150000 | F20: 1006000 | G20: 494000 | H20: YES
A21: AMS only + 5 printers | B21: 5 | C21: 1200000 | D21: 136000 | E21: 0 | F21: 1336000 | G21: 164000 | H21: NO
A22: AMS + web + 1 printer | B22: 1 | C22: 240000 | D22: 136000 | E22: 150000 | F22: 526000 | G22: 974000 | H22: YES
A25: Ongoing leases once open: AMS $44k/qtr, web $60k/qtr, NYC $62k, Rio $17k, Bangalore store $13k. Confirm in-sim whether lease hits opening quarter or first operating quarter.

Sheet Manufacturing
A1: Manufacturing — Bangalore production facility
A2: Location fixed for all firms: Bangalore (gov incentives). Cannot relocate or add facilities later; can add printers. Airfreight; no inventory; same-quarter fulfillment; shipping cost to firm.
A4: Production math
A5: 1 frame/hour x 8 hrs/day x 5 days/week x 13 weeks/quarter = 520 units/printer/quarter (normal hours)
A6: Operating capacity <= fixed capacity. Turn printers on/off to set operating capacity and staffing.
A8: Fixed capacity options
A9: 3D Printers | B9: Units/Day | C9: Units/Quarter | D9: Capital Investment | E9: Cash after printers* | F9: + Amsterdam $136k | G9: Notes
A10: 0 | B10: 0 | C10: 0 | D10: 0 | E10: 1500000 | F10: 1364000
A11: 1 | B11: 8 | C11: 520 | D11: 240000 | E11: 1260000 | F11: 1124000
A12: 2 | B12: 16 | C12: 1040 | D12: 480000 | E12: 1020000 | F12: 884000 | G12: Common early-test range | H12: This gives us a conservative approach without additional inventory
A13: 3 | B13: 24 | C13: 1560 | D13: 720000 | E13: 780000 | F13: 644000 | G13: Common early-test range | H13: This covers our goals for having extra capacity
A14: 4 | B14: 32 | C14: 2080 | D14: 960000 | E14: 540000 | F14: 404000 | G14: Tight vs $300k floor
A15: 5 | B15: 40 | C15: 2600 | D15: 1200000 | E15: 300000 | F15: 164000 | G15: BREACHES $300k floor with AMS only
A16: 7 | B16: 56 | C16: 3640 | D16: 1680000 | E16: -180000 | F16: -316000 | G16: BREACHES $300k floor with AMS only
A17: 10 | B17: 80 | C17: 5200 | D17: 2400000 | E17: -900000 | F17: -1036000 | G17: BREACHES $300k floor with AMS only
A20: *Assumes Q1 start cash $1,500,000; ignores other Q1 costs. Required floor: Cash+CD >= $300,000.
A21: MARGIN NOTE: We do NOT have sim COGS/contribution margins yet. Earlier 'high margin segment' language used Price Willing to Pay ceilings (Rec $1100 / Mtn $1365 / Speed $1580) as a price-ladder proxy only — NOT proven unit profit.
A22: Process: daily orders with custom specs -> fab -> box/ship airfreight -> store pickup or break-bulk. No inventory at plant; transit <= 2 days.
A24: Operating Capacity (Workspace — Q2)
A25: Fixed capacity available THIS quarter | B25: 24 | C25: units/day
A26: Quarterly fixed capacity (×65) | B26: =B25*65 | C26: 1,560 at full fixed
A28: Demand & productivity inputs
A29: Total forecasted demand (all brands) | B29: =IF(Demand_Forecast!B12="","",Demand_Forecast!B12) | C29: from Demand_Forecast
A30: Worker productivity (HR) | B30: 0.85 | C30: LOCKED Q2 — production productivity 85%
A31: (alias) demand | B31: =B29
A32: (alias) productivity | B32: =B30
A33: Productivity loss pad | B33: =IF(B30="","",1+(1-B30)) | C33: e.g. 70% → ×1.30
A34: Operating Capacity — Workspace table
A35: Metric | B35: Units per Day | C35: Units per Quarter | D35: Notes
A36: Fixed capacity (previous quarter) | B36: 0 | C36: 0 | D36: Q1: printers not yet online
A37: Operating capacity (previous quarter) | B37: 0 | C37: 0 | D37: Q1: no production
A38: Fixed capacity | B38: =B25 | C38: =B25*65 | D38: 24 / day · 1,560 / quarter
A39: Operating capacity ← CHANGEABLE | B39: 20 | C39: =IF(B39="","",B39*65) | D39: LOCKED Q2 — 20/day · 1,300/qtr scheduled; effective ~17/day · ~1,105/qtr @ 85%
A40: Effective OC after adjustment for worker productivity | B40: =IF(OR(B39="",B30=""),"",B39*B30) | C40: =IF(B40="","",B40*65) | D40: Scheduled OC × productivity % (e.g. 10×0.70=7)
A41: Effective OC needed for demand projection | B41: =IF(OR(B29="",B30=""),"",(B29/65)*(1+(1-B30))) | C41: =IF(OR(B29="",B30=""),"",B29*(1+(1-B30))) | D41: Demand/65 × (1 + productivity loss)
A42: Projected worker productivity [%] | B42: =B30 | D42: Same as B30
A43: New direct labor cost/unit of operating capacity | B43: 110 | D43: Approx from Workspace cost curve
A44: New overhead cost/unit of operating capacity | B44: 48 | D44: Falls then flats ~$45–50
A45: Expense to change operating capacity (add to overhead) | B45: 0 | D45: Paste from Workspace if non-zero
A46: Labor + overhead $/unit at scheduled OC | B46: =IF(OR(B43="",B44=""),"",B43+B44)
A47: Scheduled vs needed | B47: =IF(OR(B39="",B41=""),"",IF(B39+0.001>=B41,"OC ≥ needed","SHORT — raise OC or use OT"))
A48: Near fixed max (labor rising)? | B48: =IF(B39="","",IF(B39>=23,"YES — labor U-curve rising; consider ~18–22","OK"))
A50: Helpers
A51: Min daily OC (padded) alias | B51: =B41
A52: Scheduled daily OC alias | B52: =B39
A53: Max overtime hours/day authorized | B53: 0 | C53: LOCKED Q2 — no overtime
A55: Operating Capacity Costs per Unit (approx Workspace chart)
A56: OC units/day | B56: Labor $/unit | C56: Overhead $/unit | D56: Labor+OH
A57: 1 | B57: 1200 | C57: 1400 | D57: =B57+C57
A58: 2 | B58: 380 | C58: 350 | D58: =B58+C58
A59: 4 | B59: 220 | C59: 180 | D59: =B59+C59
A60: 6 | B60: 190 | C60: 130 | D60: =B60+C60
A61: 8 | B61: 170 | C61: 95 | D61: =B61+C61
A62: 10 | B62: 155 | C62: 80 | D62: =B62+C62
A63: 12 | B63: 145 | C63: 70 | D63: =B63+C63
A64: 14 | B64: 135 | C64: 60 | D64: =B64+C64
A65: 16 | B65: 125 | C65: 55 | D65: =B65+C65
A66: 18 | B66: 115 | C66: 50 | D66: =B66+C66
A67: 20 | B67: 110 | C67: 48 | D67: =B67+C67
A68: 22 | B68: 120 | C68: 45 | D68: =B68+C68
... A71: 26 | B71: 400 | C71: 45 | D71: =B71+C71
A74: Planning takeaway | B74: Sweet spot ~18–22 units/day (labor trough ~$110–120). At fixed max 24, labor rises (~$190). Overhead already low by ~16+. Trade revenue vs unit cost; OT can cover spikes without always running at 24.
A75: Next-quarter fixed capacity add (printers) — prefer Production_Sim!B62 | B75: =Production_Sim!B62 | C75: arrives NEXT quarter
A76: Printers online | B76: 3
A78: Source | B78: Workspace Operating Capacity + cost curve chart (Q2)
A80: Compat aliases (do not edit)
A81: Min daily OC (legacy B34) | B81: =B41
A82: Scheduled OC (legacy B35) | B82: =B39
A84: Maximum Overtime per Day (Workspace)
A85: Overtime | B85: Units per Quarter (add'l capacity) | C85: Productivity | D85: Average Labor Cost/Unit
A86: No overtime | B86: =IF(OR($B$25="",$B$39=""),0,$B$25*(0/8)*65) | C86: 0.7 | D86: =IF($B$39="","",IF($B$43="",0,$B$43))
A87: 1 hour | B87: =IF(OR($B$25="",$B$39=""),0,$B$25*(1/8)*65) | C87: 0.693 | D87: =IF($B$39="","",IF($B$43="","", $B$43*(1+(1/8))))
A88: 2 hours | B88: =IF(OR($B$25="",$B$39=""),0,$B$25*(2/8)*65) | C88: 0.68 | D88: =IF($B$39="","",IF($B$43="","", $B$43*(1+(2/8))))
A89: 3 hours | B89: =IF(OR($B$25="",$B$39=""),0,$B$25*(3/8)*65) | C89: 0.664 | D89: =IF($B$39="","",IF($B$43="","", $B$43*(1+(3/8))))
A90: 4 hours | B90: =IF(OR($B$25="",$B$39=""),0,$B$25*(4/8)*65) | C90: 0.644 | D90: =IF($B$39="","",IF($B$43="","", $B$43*(1+(4/8))))
A92: Effect of Using Maximum Overtime
A93: Maximum hours of overtime per day ← CHANGEABLE | B93: =B53 | C93: Edit B53 (0–4); this mirrors it
A94: Effective operating capacity addition (units/quarter) | B94: =IF(OR(B53="",B25=""),0,B25*(B53/8)*65)
A95: Loss of productivity | B95: =IF(B53="","",IF(B53=0,0,IF(B53=1,0.7-0.693,IF(B53=2,0.7-0.68,IF(B53=3,0.7-0.664,IF(B53=4,0.7-0.644,0))))))
A96: Increase in average labor cost/unit (approx) | B96: =IF(OR(B53="",B43=""),"",IF(B53=0,0,B43*(B53/8))) | C96: Rough OT premium model — replace with Workspace figure when shown
A97: Productivity with selected max OT | B97: =IF(B53="","",IF(B53=0,0.7,IF(B53=1,0.693,IF(B53=2,0.68,IF(B53=3,0.664,IF(B53=4,0.644,0.7))))))
A99: Projected Change in Worker Productivity (OT curve)
A100: Overtime Hours | B100: Productivity %
A101: 0 | B101: 0.7
A102: 1 | B102: 0.693
A103: 2 | B103: 0.68
A104: 3 | B104: 0.664
A105: 4 | B105: 0.644
A107: Source | B107: Workspace Maximum Overtime + productivity chart (Q2)

Sheet Production_Sim
A1: Production Simulation (Workspace — Q2)
A2: Reflects linked decisions: Demand_Forecast, Manufacturing OC/OT, Pricing, Cost_of_Production. Yellow = overrides. Re-paste Workspace when live numbers differ. Detail: manufacturing-background.md
A3: Percent of forecasted demand (scenario) | B3: 1 | C3: 100% = use Demand_Forecast; try 50% / 150% scenarios
A5: Brand — Produce / Demand / Price
A6: Brand | B6: Produce (Y/N) | C6: Previous Demand | D6: Projected Demand | E6: Average Cost | F6: Selling Price | G6: Unit Contribution
A7: Hike Bike | B7: Y | C7: 0 | D7: =IF(OR(UPPER(B7)="N",UPPER(B7)="NO"),0,IF(Demand_Forecast!D17="","",Demand_Forecast!D17*$B$3)) | E7: =IF(Cost_of_Production!B15="","",Cost_of_Production!B15) | F7: =IF(Pricing!F5="","",Pricing!F5) | G7: =IF(OR(F7="",E7=""),"",F7-E7)
A9: Capacity (linked to Manufacturing)
A10: Metric | B10: Units/Day | C10: Units/Quarter
A11: Fixed capacity | B11: =Manufacturing!B25 | C11: =Manufacturing!B25*65
A12: Operating capacity | B12: =Manufacturing!B39 | C12: =IF(Manufacturing!B39="","",Manufacturing!B39*65)
A13: Effective OC after productivity (no OT) | B13: =Manufacturing!B40 | C13: =Manufacturing!C40
A14: Effective OC needed for demand projection | B14: =Manufacturing!B41 | C14: =Manufacturing!C41
A15: Maximum hours of overtime per day | B15: =Manufacturing!B53
A16: Projected worker productivity [%] (base / with OT) | B16: =Manufacturing!B30 | C16: =Manufacturing!B97
A18: Number of Units
A19: Brand | B19: Units Produced | C19: Net Demand | D19: Lost Sales Due to Stock-Outs
A20: Hike Bike | B20: =IF(OR(D7="",Manufacturing!B39=""),0,MIN(D7,Manufacturing!B39*IF(Manufacturing!B53=0,Manufacturing!B30,Manufacturing!B97)*65+Manufacturing!B25*(IF(Manufacturing!B53="",0,Manufacturing!B53)/8)*65)) | C20: =D7 | D20: =IF(OR(C20="",B20=""),0,MAX(0,C20-B20))
A21: Total | B21: =B20 | C21: =C20 | D21: =D20
A22: Unmet demand % | B22: =IF(OR(C21="",C21=0),"",D21/C21)
A23: Next-Q ill-will penalty % (½ unmet) | B23: =IF(B22="","",B22/2)
A25: Production Costs per Unit
A26: Brand | B26: Units Produced | C26: Direct Materials | D26: + Direct Labor | E26: + Total Overhead | F26: ="= Production Average"
A27: Hike Bike | B27: =B20 | C27: 337 | D27: =IF(Manufacturing!B43="","",Manufacturing!B43+IF(Manufacturing!B96="",0,Manufacturing!B96)) | E27: =IF(Manufacturing!B44="","",Manufacturing!B44+IF(Manufacturing!B45="",0,Manufacturing!B45)) | F27: =IF(COUNT(C27:E27)<1,"",SUM(C27:E27)) | G27: Materials default ~$337 parts (brand-mountain); replace with Workspace
A28: vs Cost_of_Production table | B28: =IF(Cost_of_Production!B15="","",Cost_of_Production!B15) | C28: Reconcile F27 vs Workspace volume cost table
A30: Operating Capacity Utilization
A31: Overtime
A32: Overtime hours used | B32: =IF(OR(C20="",Manufacturing!B39=""),0,IF(C20<=Manufacturing!B39*Manufacturing!B30*65,0,MIN(IF(Manufacturing!B53="",0,Manufacturing!B53),(C20-Manufacturing!B39*Manufacturing!B30*65)/(Manufacturing!B25*65/8)))) | C32: Approx hours needed; capped by max authorized
A33: Overtime capacity (units/quarter add'l) | B33: =Manufacturing!B94
A34: Production worker productivity without overtime | B34: =Manufacturing!B30
A35: Production worker productivity with overtime | B35: =IF(OR(Manufacturing!B53="",Manufacturing!B53=0),"N/A",Manufacturing!B97)
A36: Increase in average direct labor cost/unit due to overtime | B36: =Manufacturing!B96
A38: Operating Capacity
A39: Planned operating capacity (units/quarter) | B39: =IF(Manufacturing!B39="","",Manufacturing!B39*65)
A40: Planned operating capacity including overtime | B40: =IF(B39="","",B39+IF(B33="",0,B33))
A41: Production worker productivity (effective) | B41: =IF(OR(Manufacturing!B53="",Manufacturing!B53=0),Manufacturing!B30,Manufacturing!B97)
A42: Effective operating capacity (units/quarter) | B42: =IF(Manufacturing!B39="","",Manufacturing!B39*IF(Manufacturing!B53=0,Manufacturing!B30,Manufacturing!B97)*65+Manufacturing!B25*(IF(Manufacturing!B53="",0,Manufacturing!B53)/8)*65*IF(Manufacturing!B53=0,1,Manufacturing!B97))
A43: Effective operating capacity utilized | B43: =B20
A44: Effective operating capacity utilization | B44: =IF(OR(B42="",B42=0),"",B43/B42)
A46: Excess Capacity
A47: Unused operating capacity | B47: =IF(OR(B42="",B43=""),0,MAX(0,B42-B43))
A48: Excess operating capacity % | B48: =IF(OR(B42="",B42=0),"",B47/B42)
A49: Overhead+labor charged to excess OC (approx) | B49: =IF(OR(B47="",Manufacturing!B46=""),0,B47*Manufacturing!B46) | C49: Rough: unused units × (labor+OH)/unit — refine in Workspace
A51: Fixed Capacity Increase (order this Q → available next Q)
A52: 3D Printers | B52: Units/Day | C52: Units/Quarter | D52: Capital Investment | E52: Select?
A53: 0 | B53: 0 | C53: 0 | D53: 0
A54: 1 | B54: 8 | C54: 520 | D54: 240000
A55: 2 | B55: 16 | C55: 1040 | D55: 480000
A56: 3 | B56: 24 | C56: 1560 | D56: 720000
A57: 4 | B57: 32 | C57: 2080 | D57: 960000
A58: 5 | B58: 40 | C58: 2600 | D58: 1200000
A59: 7 | B59: 56 | C59: 3640 | D59: 1680000
A60: 10 | B60: 80 | C60: 5200 | D60: 2400000
A62: Printers to add (count) | B62: 0 | C62: Or mark Select? column; B62 drives summary (0–10)
A63: Capital for selected add | B63: =IF(B62=0,0,IF(B62=1,240000,IF(B62=2,480000,IF(B62=3,720000,IF(B62=4,960000,IF(B62=5,1200000,IF(B62=7,1680000,IF(B62=10,2400000,"check"))))))))
A64: Sync Manufacturing!B75 | B64: =B62 | C64: Keep Manufacturing next-Q add in sync
A66: Summary
A67: Metric | B67: Units/Day | C67: Units/Quarter
A68: Fixed capacity available in current quarter | B68: 24 | C68: 1560
A69: Planned increase in fixed capacity | B69: =IF(B62=0,0,IF(B62=1,8,IF(B62=2,16,IF(B62=3,24,IF(B62=4,32,IF(B62=5,40,IF(B62=7,56,IF(B62=10,80,0)))))))) | C69: =B69*65
A70: Fixed capacity available in next quarter | B70: =B68+B69 | C70: =C68+C69
A72: Next Q demand vs next Q fixed (check) | B72: =IF(Demand_Forecast!I34="","",Demand_Forecast!I34) | C72: =IF(OR(B72="",C70=""),"",IF(C70>=B72*(1+(1-Manufacturing!B30)),"Capacity OK for padded demand","May need more printers or OT"))
A74: Optimization reminders
A75: 1. Set Demand_Forecast + Sales_Ops headcount first
A76: 2. Set Manufacturing B39 OC near needed (labor sweet spot ~18–22 if demand allows)
A77: 3. Use B53 OT as safety net — productivity falls 70%→64.4% at 4h; labor cost rises
A78: 4. Avoid stock-outs (ill-will = ½ unmet % next Q) and excess capacity (idle labor+OH)
A79: 5. Order printers (B62) only if next-Q demand needs > current 24/day after OT

Sheet Cost_of_Production
A1: Cost of Production Estimate
A2: Report reflects company decisions in Quarter 2 (Workspace). Look under the column for total units you expect to sell across ALL brands.
A3: Ask Sales for the demand forecast. Unit cost falls with volume until crowding near fixed capacity.
A5: Brand | B5: 100 units | C5: 250 units | D5: 500 units | E5: 1,000 units | F5: 5,000 units | G5: 10,000 units
A6: Hike Bike | B6: 924 | C6: 675 | D6: 550 | E6: 495 | F6: 405 | G6: 363
A8: Volume columns (units across all brands) | B8: 100 | C8: 250 | D8: 500 | E8: 1000 | F8: 5000 | G8: 10000
A9: Source | B9: Workspace — Cost of Production Estimate (Q2)
A10: As-of | B10: Q2 current decisions
A12: Lookup helper (yellow = expected total units)
A13: Expected total units (all brands) | B13: =IF(Demand_Forecast!B12="","",Demand_Forecast!B12) | C13: linked to Demand_Forecast total (override yellow if needed)
A14: Nearest column volume | B14: =IF(B13="","",IF(B13<=175,100,IF(B13<=375,250,IF(B13<=750,500,IF(B13<=3000,1000,IF(B13<=7500,5000,10000))))))
A15: Est. unit production cost (Hike Bike) | B15: =IF(B13="","",IF(B14=100,B6,IF(B14=250,C6,IF(B14=500,D6,IF(B14=1000,E6,IF(B14=5000,F6,G6))))))
A16: Note | B16: Interpolation not applied — uses nearest published column. Re-paste table if Workspace updates.
A18: Room for additional brands (paste when priced)
A19: Brand | B19: 100 | C19: 250 | D19: 500 | E19: 1000 | F19: 5000 | G19: 10000

Sheet Demand_Forecast
A1: Demand Projection — Current & Next Quarter
A2: Formula: Demand = units per salesperson × # sales people. Feeds Manufacturing OC / Pricing / Cost_of_Production. Detail: demand-projection-background.md · Yellow = changeable.
A3: Q2 tip: conservative — ~30–70 units/SP; safe ~40. Q3 tip: ~40–80 units/SP; start ~60. Stock-out ill-will: next Q demand cut by half of unmet %.
A5: This Quarter (Projected) vs Last Quarter (Actual)
A6: Channel | B6: Last Q — Sales People | C6: Last Q — Demand/SP | D6: Last Q — Total Demand | E6: This Q — Sales People | F6: This Q — Demand/SP | G6: This Q — Total Demand
A7: Stores | B7: 0 | C7: 0 | D7: 0 | E7: =IF(Sales_Ops!C19="","",Sales_Ops!C19) | F7: 40 | G7: =IF(OR(E7="",F7=""),"",E7*F7)
A8: Web Sales Center | B8: 0 | C8: 0 | D8: 0 | E8: =IF(Sales_Ops!E55="","",Sales_Ops!E55) | F8: 40 | G8: =IF(OR(E8="",F8=""),"",E8*F8)
A9: Total | B9: =B7+B8 | D9: =D7+D8 | E9: =IF(COUNT(E7:E8)=0,"",SUM(E7:E8)) | G9: =IF(COUNT(G7:G8)=0,"",SUM(G7:G8))
A10: Scenario multiplier (lean stress-test) | B10: 1 | C10: 1.0 = base; 0.5 = half; 1.5 = +50%
A11: Total forecasted demand (adjusted) — Manufacturing link
A12: Total forecasted demand (adjusted) | B12: =IF(G9="","",G9*B10) | C12: ← Manufacturing!B31 and Cost_of_Production lookup use this cell
A13: Changeable this Q: E7/E8 people (linked; override OK) · F7/F8 demand per SP · brand demands below · B10 multiplier
A15: Brand Demand Projections
A16: Brand | B16: Last Q Demand | C16: Last Q % | D16: This Q Demand | E16: This Q % | F16: Capacity Required (units) | G16: Segment | H16: Notes
A17: Hike Bike | B17: n/a | C17: LOCKED hiring → ~400 total @ 40/SP (AMS 5 + web 5); 100% Hike Bike | D17: =IF($B$12="","",$B$12) | E17: =IF(OR($B$12="",D17="",$B$12=0),"",D17/$B$12) | F17: =D17 | G17: Mountain | H17: Primary; replace D17 formula with fixed units if splitting brands
E18: =IF(OR($B$12="",D18="",$B$12=0),"",D18/$B$12) | F18: =D18 | H18: Optional brand 2
E19: =IF(OR($B$12="",D19="",$B$12=0),"",D19/$B$12) | F19: =D19 | H19: Optional brand 3
A20: Total | D20: =IF(COUNT(D17:D19)=0,"",SUM(D17:D19)) | E20: =IF(OR($B$12="",D20=""),"",D20/$B$12) | F20: =D20 | H20: Should equal 100% of B12
A21: Brand sum matches total? | B21: =IF(OR(B12="",D20=""),"",IF(ABS(D20-B12)<0.5,"YES","NO — adjust brand demands"))
A23: Operating capacity required to satisfy projected demand
B24: Units / Quarter | C24: Units / Day
A25: Operating capacity required (raw demand) | B25: =IF(B12="","",B12) | C25: =IF(B12="","",B12/65) | D25: Workspace-style: demand ÷ 65 workdays
A26: Min daily OC with productivity pad | B26: =IF(OR(B12="",Manufacturing!B32=""),"",B12) | C26: =IF(OR(B12="",Manufacturing!B32=""),"",B12/65*(1+(1-Manufacturing!B32))) | D26: Use this when scheduling OC (Manufacturing lecture)
A27: Fixed capacity / day available | C27: =Manufacturing!B25
A28: Headroom (fixed − padded daily OC) | C28: =IF(OR(C26="",C27=""),"",C27-C26)
A30: Demand Projection — Next Quarter (for fixed capacity / printers)
A31: Channel | B31: This Q — Outlets | C31: This Q — People | D31: This Q — Demand/SP | E31: This Q — Total | F31: Next Q — Outlets | G31: Next Q — People | H31: Next Q — Demand/SP | I31: Next Q — Total
A32: Stores | B32: 1 | C32: =E7 | D32: =F7 | E32: =G7 | F32: 1 | H32: 60 | I32: =IF(OR(G32="",H32=""),"",G32*H32)
A33: Web Sales Center | B33: 1 | C33: =E8 | D33: =F8 | E33: =G8 | F33: 1 | H33: 60 | I33: =IF(OR(G33="",H33=""),"",G33*H33)
A34: Total | B34: =B32+B33 | C34: =IF(COUNT(C32:C33)=0,"",SUM(C32:C33)) | E34: =IF(COUNT(E32:E33)=0,"",SUM(E32:E33)) | F34: =F32+F33 | G34: =IF(COUNT(G32:G33)=0,"",SUM(G32:G33)) | I34: =IF(COUNT(I32:I33)=0,"",SUM(I32:I33))
A36: Next Q total demand (for printer planning) | B36: =I34 | C36: Link hint: also paste into Sales_Ops Q3 demand / Manufacturing capacity add
A37: Next Q min daily OC (w/ productivity pad) | B37: =IF(OR(I34="",Manufacturing!B32=""),"",I34/65*(1+(1-Manufacturing!B32))) | C37: If > fixed 24/day, order printers this Q
A38: Changeable next Q: F32/F33 outlets · G32/G33 people · H32/H33 demand per SP
A40: Ill-will reminder | B40: Unmet demand % this Q → next Q demand reduced by half that %. Prefer slight OC buffer / overtime safety net over chronic stock-outs.
A41: Source | B41: Workspace — Demand Projection (current + next quarter)

Sheet Pricing
A1: Brand Pricing — Q2
A2: Decide list price for each brand on sale. Compare to WTP ceiling and estimated unit production cost at expected volume.
A4: Brand | B4: Segment | C4: Priority | D4: WTP ceiling | E4: Est. unit prod. cost | F4: List price (decision) | G4: vs WTP | H4: Gross vs prod. cost | I4: Gross margin % | J4: Status
A5: Hike Bike | B5: Mountain | C5: 1 | D5: =Price_WTP!B6 | E5: =Cost_of_Production!B15 | G5: =IF(OR(F5="",D5=""),"",F5-D5) | H5: =IF(OR(F5="",E5=""),"",F5-E5) | I5: =IF(OR(F5="",E5="",F5=0),"",H5/F5) | J5: OPEN — set list price
A7: Pricing notes
A8: Mountain WTP ceiling (ideal brand) | B8: =Price_WTP!B6
A9: Alumni ballpark (advisory only) | B9: ~$1,260–$1,500
A10: At 100 units, COGS ≈ $924 → price must clear this + other opex
A11: At 250 units, COGS ≈ $675; at 500 ≈ $550 — volume drops unit cost sharply
A12: Decision tip: price near WTP if Brand/Ad Judgment lead; slightly under if fighting for share
A13: Team decision (yellow F5). Do not lock until majority vote.
A15: Scenario scratch (optional)
A16: Trial price
A17: Assumed volume
A18: Nearest cost column | B18: =IF(B17="","",IF(B17<=175,100,IF(B17<=375,250,IF(B17<=750,500,IF(B17<=3000,1000,IF(B17<=7500,5000,10000))))))
A19: Unit cost at trial volume | B19: =IF(B17="","",IF(B18=100,Cost_of_Production!B6,IF(B18=250,Cost_of_Production!C6,IF(B18=500,Cost_of_Production!D6,IF(B18=1000,Cost_of_Production!E6,IF(B18=5000,Cost_of_Production!F6,Cost_of_Production!G6))))))
A20: Unit contribution (price − cost) | B20: =IF(OR(B16="",B19=""),"",B16-B19)

Sheet Media_Preference
A1: Media Preference
A2: One-time report prepared for your company (Workspace). Higher score = stronger preference for that medium in the segment.
A3: Use to prioritize major media placement for Mountain (primary), then Speed / Rec. Yellow = placement decisions (not locked).
A5: Medium | B5: Recreation | C5: Mountain | D5: Speed | E5: Max | F5: Mtn rank | G5: Notes
A6: Leisure & Entertainment | B6: 143 | C6: 60 | D6: 51 | E6: =IF(COUNT(B6:D6)=0,"",MAX(B6:D6)) | F6: =IF(C6="","",RANK(C6,$C$6:$C$12,0))
A7: Health & Fitness Magazines | B7: 127 | C7: 104 | D7: 100 | E7: =IF(COUNT(B7:D7)=0,"",MAX(B7:D7)) | F7: =IF(C7="","",RANK(C7,$C$6:$C$12,0))
A8: Biking Magazines | B8: 51 | C8: 134 | D8: 133 | E8: =IF(COUNT(B8:D8)=0,"",MAX(B8:D8)) | F8: =IF(C8="","",RANK(C8,$C$6:$C$12,0))
A9: Sport Magazines | B9: 84 | C9: 123 | D9: 117 | E9: =IF(COUNT(B9:D9)=0,"",MAX(B9:D9)) | F9: =IF(C9="","",RANK(C9,$C$6:$C$12,0))
A10: Business Magazines | B10: 90 | C10: 93 | D10: 125 | E10: =IF(COUNT(B10:D10)=0,"",MAX(B10:D10)) | F10: =IF(C10="","",RANK(C10,$C$6:$C$12,0))
A11: New Venture Magazines | B11: 81 | C11: 94 | D11: 114 | E11: =IF(COUNT(B11:D11)=0,"",MAX(B11:D11)) | F11: =IF(C11="","",RANK(C11,$C$6:$C$12,0))
A12: General News Magazines | B12: 111 | C12: 122 | D12: 113 | E12: =IF(COUNT(B12:D12)=0,"",MAX(B12:D12)) | F12: =IF(C12="","",RANK(C12,$C$6:$C$12,0))
A14: Mountain priority (by score)
A15: 1st | B15: Biking Magazines (134)
A16: 2nd | B16: Sport Magazines (123)
A17: 3rd | B17: General News Magazines (122)
A18: Avoid / low for Mountain | B18: Leisure & Entertainment (60) — Rec-skewed
A20: Speed priority (by score)
A21: 1st | B21: Biking Magazines (133)
A22: 2nd | B22: Business Magazines (125)
A23: 3rd | B23: Sport Magazines (117)
A25: Recreation priority (by score)
A26: 1st | B26: Leisure & Entertainment (143)
A27: 2nd | B27: Health & Fitness Magazines (127)
A28: 3rd | B28: General News Magazines (111)
A30: Major media placement (OPEN — team decision)
A31: Ad name / focus | B31: Primary medium | C31: Inserts / spend | D31: Secondary medium | E31: Inserts / spend | F31: Geo / notes | G31: Status
A32: HikeBike1 — Mountain primary | B32: Web + World Market magazines | C32: 1000 | D32: Biking | E32: 12 | F32: LOCKED: web $1,000/qtr; inserts Health1 Biking12 Sport2 News1 = $89,000 (Leisure/Business/NV=0); ranks brand→trail→gears→tires→adventure→tough→mtns→price | G32: LOCKED 2026-08-27
A33: Secondary segment ad (TBD) | G33: OPEN
A34: Company / corporate ad (optional) | G34: OPEN
A36: Budget / constraints
A37: Total traditional media budget (this Q) | B37: 89000 | C37: World Market traditional inserts LOCKED
A38: Web media / SEM budget (this Q) | B38: 1000 | C38: HikeBike1 web LOCKED
A39: Source | B39: Workspace — Media Preference (one-time report)
A40: HikeBike1 insert detail (LOCKED) | B40: Primary spend should follow Mountain prefs (Biking → Sport → General News). Leisure is Rec-primary — use only if Rec ad launched.
A41: Medium | B41: Inserts | C41: Cost/insert | D41: Spend
A42: Leisure & Entertainment | B42: 0 | C42: 10000 | D42: 0
A43: Health & Fitness Magazines | B43: 1 | C43: 7000 | D43: 7000
A44: Biking Magazines | B44: 12 | C44: 4500 | D44: 54000
A45: Sport Magazines | B45: 2 | C45: 10000 | D45: 20000
A46: Business Magazines | B46: 0 | C46: 9500 | D46: 0
A47: New Venture Magazines | B47: 0 | C47: 5500 | D47: 0
A48: General News Magazines | B48: 1 | C48: 8000 | D48: 8000
A49: TOTAL traditional | D49: 89000 | E49: $1,594 of ~$90,594 envelope unspent

Sheet Web_SEO
A1: Internet Marketing / Organic SEM — Web Pages
A2: Q2: build marketing site from ads; assign segment (keywords follow); check to run. Organic first — slow ramp. Yellow = decisions (not locked). Detail: seo-internet-marketing-background.md
A3: SERP tip: only first 3 ad benefits show in search results — rank carefully. No deceptive claims (match Hike Bike specs).
A5: Background summary
A6: Focus | B6: Organic SEM this quarter; paid SEM later
A7: Content source | B7: Convert media ads → web layout (same message)
A8: Keywords | B8: Agency set per segment — chosen when you pick segment (≠ ad benefits)
A9: Expectation | B9: Modest early traffic; support with traditional ads that list brand + URL
A10: Localize | B10: Pages translated / country-tagged for markets with outlets
A11: Fee | C11: yellow = paste modest web-page design fee from Workspace
A13: Web Page Content tracker (from ads)
A14: Ad name | B14: Brand emphasized | C14: Segment + keywords | D14: Status (Inactive/Run) | E14: SERP top-3 benefits OK? | F14: Deceptive flag? | G14: Design fee | H14: Notes
A15: TBD — Mountain primary ad | B15: Hike Bike | C15: Mountain (agency keywords) | D15: Inactive | H15: Primary; steep-trail / adventure pool
A16: TBD — Secondary segment ad | D16: Inactive | H16: Speed or Rec if launched
A17: TBD — Company ad (optional) | B17: WeBike (company) | D17: Inactive | H17: No brand emphasize
A19: Segment keyword reminder
A20: Segment | B20: Keywords (paste from Workspace when assigned) | C20: Primary use
A21: Mountain | C21: Hike Bike / primary Q2
A22: Speed | C22: If Speed ad/page launched
A23: Recreation | C23: If Rec ad/page launched
A25: Organic support checklist
A26: Traditional ads list brand + web URL | C26: Yes/No — helps discovery
A27: Deceptive review cleared
A28: Cash+CD still ≥ $300k after page fees
A29: Source | B29: Workspace — Internet marketing / Web Page Content / organic SEM
A31: Do not expect
A32: Large Q2 demand from organic alone. Pair with media placement + strong top-3 benefits.

Sheet Sales_Ops
A1: Sales Channel Ops — Staffing Planner + Regional Summary
A2: Plan per-location headcount and specialty training (Service / Recreation / Mountain / Speed). Yellow = inputs. Paste Workspace unit costs into rate table. Test tip: ≤7 people per city; ≥1 service. Detail: sales-channel-background.md
A3: Training counts need not equal total headcount — unassigned sell to all segments equally. Prior Q = 0 (no sales staff in Q1 setup).
A5: Unit cost rates (paste from Workspace — yellow)
A6: Cost item | B6: Unit / basis | C6: $ this quarter | D6: Notes
A7: Hiring expense | B7: per person hired | D7: One-time when headcount rises
A8: Layoff expense | B8: per person laid off | D8: One-time when headcount falls
A9: Salary + training — Service | B9: per person assigned | C9: 300 | D9: LOCKED Q2 — training only; salary via $24,425 annual package
A10: Salary + training — Recreation | B10: per person assigned | C10: 250
A11: Salary + training — Mountain | B11: per person assigned | C11: 400 | D11: LOCKED Q2 primary segment
A12: Salary + training — Speed | B12: per person assigned | C12: 400
A13: Salary + training — Unassigned / general | B13: per unassigned person | C13: 0 | D13: No specialty; optional rate
A15: Rate keys (for formulas): Hire=C7 Layoff=C8 Svc=C9 Rec=C10 Mtn=C11 Spd=C12 Unass=C13
A17: Per-location staffing & specialized training
A18: Location | B18: Status | C18: Total sales+service | D18: Service | E18: Recreation | F18: Mountain | G18: Speed | H18: Unassigned (calc) | I18: Specialty sum | J18: ≤7 tip / notes
A19: Amsterdam | B19: OPEN (Q2 live) | C19: 5 | D19: 1 | E19: 0 | F19: 4 | G19: 0 | H19: =IF(C19="","",C19-SUM(D19:G19)) | I19: =IF(COUNT(D19:G19)=0,"",SUM(D19:G19)) | J19: Physical store — Hike Bike primary
A20: World Web | B20: OPEN (Q2 live) | C20: =IF(E55="","",E55) | D20: 2 | E20: 0 | F20: 3 | G20: 0 | H20: =IF(C20="","",C20-SUM(D20:G20)) | I20: =IF(COUNT(D20:G20)=0,"",SUM(D20:G20)) | J20: Total linked to Web Personnel E55 (C55+D55)
A21: Rio de Janeiro (opens next Q) | B21: LOCKED — schedule Q2 / live Q3 | H21: =IF(C21="","",C21-SUM(D21:G21)) | I21: =IF(COUNT(D21:G21)=0,"",SUM(D21:G21)) | J21: Opens next quarter if scheduled
A22: Other / TBD | B22: — | H22: =IF(C22="","",C22-SUM(D22:G22)) | I22: =IF(COUNT(D22:G22)=0,"",SUM(D22:G22)) | J22: Optional
A23: Checks
A24: AMS total ≤7? | B24: =IF(C19="","",IF(C19<=7,"YES","OVER tip"))
A25: AMS service ≥1? | B25: =IF(D19="","",IF(D19>=1,"YES","NEED ≥1 service"))
A26: Specialty ≤ total (all rows)? | B26: =IF(OR(H19<0,H20<0,IF(C21="",FALSE,H21<0),IF(C22="",FALSE,H22<0)),"ERROR — specialties exceed total","OK")
A28: Estimated salary & training cost by location (uses rates above)
A29: Location | B29: Service $ | C29: Rec $ | D29: Mountain $ | E29: Speed $ | F29: Unassigned $ + Total
A30: =A19 | B30: =IF(OR(D19="",$C$9=""),"",D19*$C$9) | C30: =IF(OR(E19="",$C$10=""),"",E19*$C$10) | D30: =IF(OR(F19="",$C$11=""),"",F19*$C$11) | E30: =IF(OR(G19="",$C$12=""),"",G19*$C$12) | F30: =IF(C19="","",IFERROR(B30,0)+IFERROR(C30,0)+IFERROR(D30,0)+IFERROR(E30,0)+IF(OR(H19="",$C$13=""),0,H19*$C$13))
A31: =A20 | B31: =IF(OR(D20="",$C$9=""),"",D20*$C$9) | C31: =IF(OR(E20="",$C$10=""),"",E20*$C$10) | D31: =IF(OR(F20="",$C$11=""),"",F20*$C$11) | E31: =IF(OR(G20="",$C$12=""),"",G20*$C$12) | F31: =IF(C20="","",IFERROR(B31,0)+IFERROR(C31,0)+IFERROR(D31,0)+IFERROR(E31,0)+IF(OR(H20="",$C$13=""),0,H20*$C$13))
A32: =A21 | B32: =IF(OR(D21="",$C$9=""),"",D21*$C$9) | C32: =IF(OR(E21="",$C$10=""),"",E21*$C$10) | D32: =IF(OR(F21="",$C$11=""),"",F21*$C$11) | E32: =IF(OR(G21="",$C$12=""),"",G21*$C$12) | F32: =IF(C21="","",IFERROR(B32,0)+IFERROR(C32,0)+IFERROR(D32,0)+IFERROR(E32,0)+IF(OR(H21="",$C$13=""),0,H21*$C$13))
A33: =A22 | B33: =IF(OR(D22="",$C$9=""),"",D22*$C$9) | C33: =IF(OR(E22="",$C$10=""),"",E22*$C$10) | D33: =IF(OR(F22="",$C$11=""),"",F22*$C$11) | E33: =IF(OR(G22="",$C$12=""),"",G22*$C$12) | F33: =IF(C22="","",IFERROR(B33,0)+IFERROR(C33,0)+IFERROR(D33,0)+IFERROR(E33,0)+IF(OR(H22="",$C$13=""),0,H22*$C$13))
A34: Total salary & training (all locations) | B34: =IF(COUNT(F30:F33)=0,"",SUM(F30:F33))
A36: Regional Summary (Workspace mirror — strategic planning)
A37: Total Number of Sales and Service People
A38: Prior Quarter | B38: 0 | C38: Q1 had no sales staff
A39: Current Quarter | B39: =IF(COUNT(C19:C22)=0,"",SUM(C19:C22)) | C39: Sum of location totals
A40: Net Change | B40: =IF(B39="","",B39-B38)
A42: Costs This Quarter
A43: Hiring expenses | B43: =IF(OR(B40="",$C$7=""),"",IF(B40>0,B40*$C$7,0)) | C43: Net hires × hiring rate (simple; refine if mix hire/layoff)
A44: Lay off expenses | B44: =IF(OR(B40="",$C$8=""),"",IF(B40<0,ABS(B40)*$C$8,0)) | C44: Net layoffs × layoff rate
A45: Salary and Training Costs | B45: =B34 | C45: From specialty assignments × rates
A46: TOTAL people costs (hire + layoff + salary/training) | B46: =IF(COUNT(B43:B45)=0,"",SUM(B43:B45))
A48: Specialty mix — current quarter (all locations)
A49: Service | B49: Recreation | C49: Mountain | D49: Speed | E49: Unassigned
A50: =SUM(D19:D22) | B50: =SUM(E19:E22) | C50: =SUM(F19:F22) | D50: =SUM(G19:G22) | E50: =SUM(H19:H22)
A52: Web Personnel (Workspace — World Market)
A53: Changeable: Web Sales headcount · Web Support headcount. Annual compensation shown is industry-sales package baseline ($19,310) until our Comp_Industry package is locked — then update.
A54: Location | B54: Annual Compensation | C54: Web Sales | D54: Web Support | E54: Total Sales People
A55: Bangalore, World Market | B55: 24425 | C55: 3 | D55: 2 | E55: =IF(COUNT(C55:D55)=0,"",SUM(C55:D55))
A56: Compensation source | B56: LOCKED Q2 sales package $24,425 (Comp_Industry) | C56: Prefer Comp_Industry total when set; B55 is the $ used for employ-cost calc
A57: Use Comp_Industry sales total for B55? | B57: Paste or set B55 = Comp_Industry!C42 when package decided
A58: Sync tip | B58: Set row 20 (World Web) Total ≈ E55. Specialty columns on row 20 are optional for web; Web Sales vs Web Support is the Workspace split.
A59: World Web row20 Total vs Web Personnel Total | B59: =IF(OR(C20="",E55=""),"",C20-E55) | C59: 0 = synced
A61: Web Personnel Summary
A62: Total number of web personnel in the prior quarter | B62: 0 | C62: Q1: web center opening, no staff yet
A63: Total number of web personnel in the current quarter | B63: =E55
A64: Net change in number of web personnel | B64: =IF(B63="","",B63-B62)
A66: Cost to hire new web personnel | B66: =IF(OR(B64="",$C$7=""),"",IF(B64>0,B64*$C$7,0)) | C66: Uses Hiring expense rate C7 (paste from Workspace)
A67: Cost to lay off web personnel | B67: =IF(OR(B64="",$C$8=""),"",IF(B64<0,ABS(B64)*$C$8,0)) | C67: Uses Layoff expense rate C8
A68: Cost to employ web personnel for the quarter | B68: =IF(OR(E55="",B55=""),"",E55*B55/4) | C68: Assumes annual package ÷ 4 × headcount (adjust if Workspace uses different timing)
A69: TOTAL web people costs (hire + layoff + employ) | B69: =IF(COUNT(B66:B68)=0,"",SUM(B66:B68))
A71: Elements that can be changed | B71: Web Sales (C55) · Web Support (D55) · Annual compensation (B55) · Hire/layoff rates (C7/C8)
A73: Web productivity tactics — see sheet Web_Productivity
A74: Active cash this Q (linked) | B74: =IF(Web_Productivity!B10="","",Web_Productivity!B10) | C74: Edit Start/Budget on Web_Productivity sheet | D74: Quarters to full effect | E74: Notes
A75: Toll-free default | B75: Setup $3,000 · Quarterly $3,000
A76: Page upgrades default | B76: Setup $6,000 · Quarterly $6,000
A77: Curve insight | B77: Toll-free >> page upgrades on % improvement; diminishing returns after ~$10k
A80: Total web tactics budget (linked) | B80: =B74
A82: New sales outlet for NEXT quarter (city #2)
A83: Open a new store? | B83: Yes | C83: LOCKED Q2 — full quarter to open; live next quarter
A84: City candidate | B84: Rio | C84: Setup $90,000 · lease $17,000/qtr when live (Stores_Costs)
A85: Setup cost (hint) | B85: =IF(B84="","",IF(OR(LOWER(B84)="new york city",LOWER(B84)="nyc"),Stores_Costs!C6,IF(OR(LOWER(B84)="rio de janeiro",LOWER(B84)="rio"),Stores_Costs!C7,IF(LOWER(B84)="bangalore",Stores_Costs!C9,""))))
A86: Quarterly lease (hint) | B86: =IF(B84="","",IF(OR(LOWER(B84)="new york city",LOWER(B84)="nyc"),Stores_Costs!D6,IF(OR(LOWER(B84)="rio de janeiro",LOWER(B84)="rio"),Stores_Costs!D7,IF(LOWER(B84)="bangalore",Stores_Costs!D9,""))))
A88: Demand forecast bridge
A89: Q2 total demand | B89: =IF(Demand_Forecast!B12="","",Demand_Forecast!B12)
A90: Q3 demand projection | B90: =IF(Demand_Forecast!I34="","",Demand_Forecast!I34)
A91: Naive AMS Mountain /4 (context only) | B91: =Market_Potential!C7/4
A93: Cash reminder | B93: Ending Cash+CD ≥ $300,000 after store + web people costs, tactics, leases, optional store setup.

Sheet Web_Productivity
A1: Web Productivity — Purchase Probability Tactics
A2: LOCKED Q2: Start BOTH — Toll-free budget $3,000 · Page upgrades budget $6,000. First-Q cash ≈ setup $3k+$6k + budgets $3k+$6k = $18,000. Workspace: Options to Improve the Probability of Purchase. Start this quarter; full effect over a few quarters; diminishing returns on budget. Detail: web-productivity-background.md · Yellow = decisions (not locked).
A3: You can Stop a service anytime. Chart points are approximate read-offs from Workspace graph.
A5: Options to Improve the Probability of Purchase
A6: Activity | B6: Start (Y/N) | C6: Stop (Y/N) | D6: Status | E6: Setup Cost | F6: Quarterly Budget | G6: Est. Potential Improvement % | H6: Setup due this Q? | I6: Cash hit this Q
A7: Toll-free phone number for advising customers in the decision making process and for handling service calls | B7: Y | D7: =IF(OR(UPPER(B7)="Y",UPPER(B7)="YES"),"Active",IF(OR(UPPER(C7)="Y",UPPER(C7)="YES"),"Stopped","—")) | E7: 3000 | F7: 3000 | G7: =IF(OR(D7<>"Active",F7=""),"",IF(F7<=1500,0.22,IF(F7<=4000,0.31,IF(F7<=7500,0.35,IF(F7<=12500,0.415,IF(F7<=17500,0.44,IF(F7<=25000,0.45,0.465))))))) | I7: =IF(D7<>"Active","",IF(OR(UPPER(H7)="Y",UPPER(H7)="YES"),E7+F7,F7))
A8: Continuous upgrading of the product description, pricing, and order entry pages to improve content, visual appeal and navigation | B8: Y | D8: =IF(OR(UPPER(B8)="Y",UPPER(B8)="YES"),"Active",IF(OR(UPPER(C8)="Y",UPPER(C8)="YES"),"Stopped","—")) | E8: 6000 | F8: 6000 | G8: =IF(OR(D8<>"Active",F8=""),"",IF(F8<=1500,0.12,IF(F8<=4000,0.16,IF(F8<=7500,0.185,IF(F8<=12500,0.235,IF(F8<=17500,0.26,IF(F8<=25000,0.275,0.295))))))) | I8: =IF(D8<>"Active","",IF(OR(UPPER(H8)="Y",UPPER(H8)="YES"),E8+F8,F8))
A10: TOTAL web productivity cash this quarter | B10: =IF(COUNT(I7:I8)=0,"",SUM(I7:I8)) | C10: Sum of active tactics (setup if flagged + quarterly budget)
A12: Planning notes
A13: Default Workspace budgets sit on the steep part of both curves (efficient).
A14: Toll-free dominates page upgrades on improvement % at every budget on the chart.
A15: Most incremental gain is earned by ~$10k; $10k→$30k adds only ~5 points.
A16: Effects take a few quarters to fully mature — don’t expect full % in Q2 alone.
A17: Elements that can be changed: Start/Stop · Quarterly Budget · Setup-due flag
A19: Potential Improvement [%] vs Quarterly Budget (approx chart read-off)
A20: Quarterly Budget | B20: Toll-free phone % | C20: Page upgrades %
A21: 0 | B21: 0 | C21: 0
A22: 3000 | B22: 0.31 | C22: 0.16
A23: 5000 | B23: 0.35 | C23: 0.185
A24: 10000 | B24: 0.415 | C24: 0.235
A25: 15000 | B25: 0.44 | C25: 0.26
A26: 20000 | B26: 0.45 | C26: 0.275
A27: 30000 | B27: 0.465 | C27: 0.295
A29: Source | B29: Workspace Web Sales Center + Potential Improvement chart (Q2)
A30: Cash rule | B30: Keep ending Cash+CD ≥ $300,000 after web productivity + personnel + other Q2 spends.

Sheet Needs_Ranked
A1: Needs Snapshot — linked to Needs sheet
A2: After entering scores on Needs, filter each block where Flag = IMPORTANT, or sort Score descending (copy-paste values if needed).
A4: Recreation priorities | E4: Mountain priorities | I4: Speed priorities
A5: Need | B5: Score | C5: Flag | E5: Need | F5: Score | G5: Flag | I5: Need | J5: Score | K5: Flag
A6: =Needs!A5 | B6: =Needs!B5 | C6: =Needs!F5 | E6: =Needs!A5 | F6: =Needs!C5 | G6: =Needs!G5 | I6: =Needs!A5 | J6: =Needs!D5 | K6: =Needs!H5
A7: =Needs!A6 | B7: =Needs!B6 | C7: =Needs!F6 | E7: =Needs!A6 | F7: =Needs!C6 | G7: =Needs!G6 | I7: =Needs!A6 | J7: =Needs!D6 | K7: =Needs!H6
A8: =Needs!A7 | B8: =Needs!B7 | C8: =Needs!F7 | E8: =Needs!A7 | F8: =Needs!C7 | G8: =Needs!G7 | I8: =Needs!A7 | J8: =Needs!D7 | K8: =Needs!H7
A9: =Needs!A8 | B9: =Needs!B8 | C9: =Needs!F8 | E9: =Needs!A8 | F9: =Needs!C8 | G9: =Needs!G8 | I9: =Needs!A8 | J9: =Needs!D8 | K9: =Needs!H8
A10: =Needs!A9 | B10: =Needs!B9 | C10: =Needs!F9 | E10: =Needs!A9 | F10: =Needs!C9 | G10: =Needs!G9 | I10: =Needs!A9 | J10: =Needs!D9 | K10: =Needs!H9
A11: =Needs!A10 | B11: =Needs!B10 | C11: =Needs!F10 | E11: =Needs!A10 | F11: =Needs!C10 | G11: =Needs!G10 | I11: =Needs!A10 | J11: =Needs!D10 | K11: =Needs!H10
A12: =Needs!A11 | B12: =Needs!B11 | C12: =Needs!F11 | E12: =Needs!A11 | F12: =Needs!C11 | G12: =Needs!G11 | I12: =Needs!A11 | J12: =Needs!D11 | K12: =Needs!H11
A13: =Needs!A12 | B13: =Needs!B12 | C13: =Needs!F12 | E13: =Needs!A12 | F13: =Needs!C12 | G13: =Needs!G12 | I13: =Needs!A12 | J13: =Needs!D12 | K13: =Needs!H12
A14: =Needs!A13 | B14: =Needs!B13 | C14: =Needs!F13 | E14: =Needs!A13 | F14: =Needs!C13 | G14: =Needs!G13 | I14: =Needs!A13 | J14: =Needs!D13 | K14: =Needs!H13
A15: =Needs!A14 | B15: =Needs!B14 | C15: =Needs!F14 | E15: =Needs!A14 | F15: =Needs!C14 | G15: =Needs!G14 | I15: =Needs!A14 | J15: =Needs!D14 | K15: =Needs!H14
A16: =Needs!A15 | B16: =Needs!B15 | C16: =Needs!F15 | E16: =Needs!A15 | F16: =Needs!C15 | G16: =Needs!G15 | I16: =Needs!A15 | J16: =Needs!D15 | K16: =Needs!H15
A17: =Needs!A16 | B17: =Needs!B16 | C17: =Needs!F16 | E17: =Needs!A16 | F17: =Needs!C16 | G17: =Needs!G16 | I17: =Needs!A16 | J17: =Needs!D16 | K17: =Needs!H16
... A41: =Needs!A40 | B41: =Needs!B40 | C41: =Needs!F40 | E41: =Needs!A40 | F41: =Needs!C40 | G41: =Needs!G40 | I41: =Needs!A40 | J41: =Needs!D40 | K41: =Needs!H40

Sheet Growth_Room
A1: Growth Room vs Classmates (1–5 scores)
A2: Gap index = Attractiveness + Serveability − Crowding (higher = more room for growth). Yellow = inputs.
A4: Segment | B4: City / Channel | C4: Attractiveness (1–5) | D4: Expected crowding (1–5) | E4: Our serveability (1–5) | F4: Gap index | G4: Why peers may leave it | H4: Priority (H/M/L)
A5: Recreation | B5: New York | F5: =IF(COUNT(C5:E5)<3,"",C5+E5-D5)
A6: Recreation | B6: Amsterdam | F6: =IF(COUNT(C6:E6)<3,"",C6+E6-D6)
A7: Recreation | B7: Rio de Janeiro | F7: =IF(COUNT(C7:E7)<3,"",C7+E7-D7)
A8: Recreation | B8: Bangalore | F8: =IF(COUNT(C8:E8)<3,"",C8+E8-D8)
A9: Recreation | B9: Web | F9: =IF(COUNT(C9:E9)<3,"",C9+E9-D9)
A10: Mountain | B10: New York | F10: =IF(COUNT(C10:E10)<3,"",C10+E10-D10)
A11: Mountain | B11: Amsterdam | C11: 5 | F11: =IF(COUNT(C11:E11)<3,"",C11+E11-D11)
A12: Mountain | B12: Rio de Janeiro | F12: =IF(COUNT(C12:E12)<3,"",C12+E12-D12)
A13: Mountain | B13: Bangalore | F13: =IF(COUNT(C13:E13)<3,"",C13+E13-D13)
A14: Mountain | B14: Web | C14: 5 | F14: =IF(COUNT(C14:E14)<3,"",C14+E14-D14)
A15: Speed | B15: New York | F15: =IF(COUNT(C15:E15)<3,"",C15+E15-D15)
A16: Speed | B16: Amsterdam | F16: =IF(COUNT(C16:E16)<3,"",C16+E16-D16)
A17: Speed | B17: Rio de Janeiro | F17: =IF(COUNT(C17:E17)<3,"",C17+E17-D17)
A18: Speed | B18: Bangalore | F18: =IF(COUNT(C18:E18)<3,"",C18+E18-D18)
A19: Speed | B19: Web | F19: =IF(COUNT(C19:E19)<3,"",C19+E19-D19)

Sheet Competitor_CI
A1: Competitor (Classmate) Tracker
A2: Q2+: enter firm names and metrics from results / purchased research. Competitor-first buy priority.
A4: Firm | B4: Quarter | C4: Segments | D4: Cities / Web | E4: Brand Judgment notes | F4: Ad Judgment notes | G4: Price posture | H4: Share / demand served | I4: Weakness / gap for us | J4: Our response
A27: Research purchase log (competitor-first)
A28: Quarter | B28: Report bought | C28: Cost | D28: Key competitor insight | E28: Action

Sheet Comp_Industry
A1: Compensation & Productivity Planner (Q2)
A2: Team goal: pay ABOVE average. Set OUR planning weights (F68:F71); Score mode B73 = Our|Industry. History + charts track changes over quarters. Detail: compensation-background.md
A3: Projected productivity starts ~70%. Last-quarter industry averages appear from Q3. Yellow = our decisions (not locked).
A4: Sales people
A5: Component | B5: Industry setting | C5: Cost | D5: Importance of further improvement
A6: Salary | B6: 17000 | C6: 17000 | D6: 87
A7: Health benefits | B7: Minimum | C7: 1700 | D7: 84
A8: Vacation | B8: 1 week | C8: 440 | D8: 72
A9: Pension | B9: 1% | C9: 170 | D9: 70
A10: TOTAL yearly cost | C10: 19310
A13: Production workers
A14: Component | B14: Industry setting | C14: Cost | D14: Importance of further improvement
A15: Salary | B15: 14000 | C15: 14000 | D15: 87
A16: Health benefits | B16: Minimum | C16: 1400 | D16: 84
A17: Vacation | B17: 1 week | C17: 363 | D17: 72
A18: Pension | B18: 2% | C18: 280 | D18: 70
A19: TOTAL yearly cost | C19: 16043
A22: Benefit cost menus — Sales (Workspace)
A23: Health tier | B23: Cost | C23: Vacation weeks | D23: Cost | E23: Pension | F23: Total cost | G23: vs Industry
A24: No health benefits | B24: 0 | C24: 0 | D24: 0
A25: Minimum | B25: 1700 | C25: 1 | D25: 440
A26: Expanded | B26: 2550 | C26: 2 | D26: 944
A27: Full coverage | B27: 3740 | C27: 3 | D27: 1475
A28: Comprehensive | B28: 5610 | C28: 4 | D28: 2024
C29: 5 | D29: 2587
C30: 6 | D30: 3161
C31: 7 | D31: 3745
A33: Note: Production health/vacation $ may differ — confirm in Workspace (Q1 ind. Min health $1,400 / 1 wk $363).
A34: Pension cost = Salary × (Pension % / 100). Salary $ = cost $.
A36: OUR SALES PACKAGE (interactive — yellow)
A37: Metric | B37: Our choice | C37: Cost $ | D37: Industry | E37: vs Industry $ | F37: Importance
A38: Annual salary | B38: 19000 | C38: =IF(B38="","",B38) | D38: 17000 | E38: =IF(C38="","",C38-D38) | F38: 87
A39: Health (type tier name or paste cost) | B39: Full coverage | C39: 4180 | D39: 1700 | E39: =IF(C39="","",C39-D39) | F39: 84
A40: Vacation weeks | B40: 2 | C40: 1055 | D40: 440 | E40: =IF(C40="","",C40-D40) | F40: 72
A41: Pension % | B41: 1 | C41: =IF(OR(B38="",B41=""),"",B38*B41/100) | D41: 170 | E41: =IF(C41="","",C41-D41) | F41: 70
A42: TOTAL yearly cost / person | C42: =IF(COUNT(C38:C41)<1,"",SUM(C38:C41)) | D42: 19310 | E42: =IF(C42="","",C42-D42)
A43: Estimated sales productivity % | B43: 0.85 | C43: LOCKED Q2 — World Market / sales force; productivity 85%
A44: Above industry total? | B44: =IF(C42="","",IF(C42>D42,"YES — goal direction","NO — below/at industry"))
A46: OUR PRODUCTION PACKAGE (interactive — yellow)
A47: Metric | B47: Our choice | C47: Cost $ | D47: Industry | E47: vs Industry $ | F47: Importance
A48: Annual salary | B48: 16800 | C48: =IF(B48="","",B48) | D48: 14000 | E48: =IF(C48="","",C48-D48) | F48: 87
A49: Health cost (paste from Workspace) | B49: Expanded coverage | C49: 2520 | D49: 1400 | E49: =IF(C49="","",C49-D49) | F49: 84
A50: Vacation weeks / cost | B50: 2 | C50: 933 | D50: 363 | E50: =IF(C50="","",C50-D50) | F50: 72
A51: Pension % | B51: 3 | C51: =IF(OR(B48="",B51=""),"",B48*B51/100) | D51: 280 | E51: =IF(C51="","",C51-D51) | F51: 70
A52: TOTAL yearly cost / person | C52: =IF(COUNT(C48:C51)<1,"",SUM(C48:C51)) | D52: 16043 | E52: =IF(C52="","",C52-D52)
A53: Estimated production productivity % | B53: 0.85 | C53: LOCKED Q2 — World Market / production; productivity 85% → Manufacturing!B30
A54: Above industry total? | B54: =IF(C52="","",IF(C52>D52,"YES — goal direction","NO — below/at industry"))
A55: Link tip | B55: When production productivity is set, copy to Manufacturing worker productivity (OC pad).
A57: Scenario scratch (optional what-ifs)
A58: Scenario name | B58: Role | C58: Total $/person | D58: Est. productivity % | E58: $ per productivity point | F58: Notes
E59: =IF(OR(C59="",D59="",D59=0),"",C59/(D59*100))
E60: =IF(OR(C60="",D60="",D60=0),"",C60/(D60*100))
E61: =IF(OR(C61="",D61="",D61=0),"",C61/(D61*100))
E62: =IF(OR(C62="",D62="",D62=0),"",C62/(D62*100))
E63: =IF(OR(C63="",D63="",D63=0),"",C63/(D63*100))
A65: Importance Weights — Industry (Workspace) vs Our Planning Weights
A66: Industry column = survey (locked reference). OUR PLANNING WEIGHTS (yellow) drive Value Index, budget split, and charts — edit anytime. Reset: copy Industry → Our. Score mode below chooses which set scores use.
A67: Component | B67: Industry Importance | C67: Industry % | D67: Rank | E67: Implication | F67: OUR Planning Weight | G67: Our % | H67: Our − Industry
A68: Salary | B68: 87 | C68: =B68/$B$72 | D68: 1 | E68: First dollars above industry — highest leverage | F68: 87 | G68: =IF($F$72=0,"",F68/$F$72) | H68: =F68-B68
A69: Health Benefits | B69: 84 | C69: =B69/$B$72 | D69: 2 | E69: Second — almost as strong as salary | F69: 84 | G69: =IF($F$72=0,"",F69/$F$72) | H69: =F69-B69
A70: Vacation | B70: 72 | C70: =B70/$B$72 | D70: 3 | E70: Third — meaningful but weaker $/point | F70: 72 | G70: =IF($F$72=0,"",F70/$F$72) | H70: =F70-B70
A71: Pension | B71: 70 | C71: =B71/$B$72 | D71: 4 | E71: Fourth — still positive; finish after others | F71: 70 | G71: =IF($F$72=0,"",F71/$F$72) | H71: =F71-B71
A72: Total Industry importance | B72: =SUM(B68:B71) | C72: 313 expected | E72: Total OUR planning weight | F72: =SUM(F68:F71) | G72: Must be > 0
A73: Score / allocate using | B73: Our | C73: Type "Our" or "Industry" — Value Index & budget split follow this choice
A74: Active weight total (for formulas) | B74: =IF(UPPER(LEFT(B73,1))="I",$B$72,$F$72) | C74: Salary active weight | D74: =IF(UPPER(LEFT(B73,1))="I",$B$68,$F$68) | E74: Health | F74: =IF(UPPER(LEFT(B73,1))="I",$B$69,$F$69) | G74: Vacation | H74: =IF(UPPER(LEFT(B73,1))="I",$B$70,$F$70) | I74: Pension | J74: =IF(UPPER(LEFT(B73,1))="I",$B$71,$F$71)
A75: Value model
A76: Component Value Points = max(0, uplift % vs industry) × Active Importance. Package Value Index = Σ points / Active total × 100. Change OUR weights (F68:F71) to stress-test alternate priorities (e.g. overweight Health).
A77: Reset tip: set F68:F71 equal to B68:B71 to match Workspace. Log each quarter’s weights & indices in the History table so charts show change over time.
A78: Productivity hint: 70% + min(12 pts, Value Index × 0.15) — heuristic only.
A79: SALES — Importance-Weighted Value Scorecard (links to package above)
A80: Component | B80: Our $ | C80: Industry $ | D80: Extra $ | E80: Uplift % | F80: Importance | G80: Value Points | H80: Value / Extra $1k
A81: Salary | B81: =IF(C38="","",C38) | C81: 17000 | D81: =IF(OR(B81="",C81=""),"",B81-C81) | E81: =IF(OR(C81="",C81=0,D81=""),"",D81/C81) | F81: =$D$74 | G81: =IF(OR(E81="",F81=""),"",MAX(0,E81)*F81) | H81: =IF(OR(D81="",D81<=0),"",F81/(D81/1000))
A82: Health Benefits | B82: =IF(C39="","",C39) | C82: 1700 | D82: =IF(OR(B82="",C82=""),"",B82-C82) | E82: =IF(OR(C82="",C82=0,D82=""),"",D82/C82) | F82: =$F$74 | G82: =IF(OR(E82="",F82=""),"",MAX(0,E82)*F82) | H82: =IF(OR(D82="",D82<=0),"",F82/(D82/1000))
A83: Vacation | B83: =IF(C40="","",C40) | C83: 440 | D83: =IF(OR(B83="",C83=""),"",B83-C83) | E83: =IF(OR(C83="",C83=0,D83=""),"",D83/C83) | F83: =$H$74 | G83: =IF(OR(E83="",F83=""),"",MAX(0,E83)*F83) | H83: =IF(OR(D83="",D83<=0),"",F83/(D83/1000))
A84: Pension | B84: =IF(C41="","",C41) | C84: 170 | D84: =IF(OR(B84="",C84=""),"",B84-C84) | E84: =IF(OR(C84="",C84=0,D84=""),"",D84/C84) | F84: =$J$74 | G84: =IF(OR(E84="",F84=""),"",MAX(0,E84)*F84) | H84: =IF(OR(D84="",D84<=0),"",F84/(D84/1000))
A85: SALES TOTALS | B85: =IF(C42="","",C42) | C85: 19310 | D85: =IF(OR(B85="",C85=""),"",B85-C85) | G85: =IF(COUNT(G81:G84)=0,"",SUM(G81:G84))
A86: Sales Package Value Index (0–100+ scale) | B86: =IF(OR(G85="",$B$74="",$B$74=0),"",G85/$B$74*100) | C86: 100 ≈ average +100% uplift on every lever (unlikely); compare scenarios relatively
A87: Suggested sales productivity % (heuristic) | B87: =IF(B86="","",MIN(0.85,0.7+MIN(0.12,B86*0.0015))) | C87: Copy to B43 after judgment — or override B43 yellow directly
A88: Apply suggested productivity to B43? | B88: N | C88: Set Y then paste B87→B43 manually (kept separate so you stay in control)
A90: PRODUCTION — Importance-Weighted Value Scorecard
A91: Component | B91: Our $ | C91: Industry $ | D91: Extra $ | E91: Uplift % | F91: Importance | G91: Value Points | H91: Value / Extra $1k
A92: Salary | B92: =IF(C48="","",C48) | C92: 14000 | D92: =IF(OR(B92="",C92=""),"",B92-C92) | E92: =IF(OR(C92="",C92=0,D92=""),"",D92/C92) | F92: =$D$74 | G92: =IF(OR(E92="",F92=""),"",MAX(0,E92)*F92) | H92: =IF(OR(D92="",D92<=0),"",F92/(D92/1000))
A93: Health Benefits | B93: =IF(C49="","",C49) | C93: 1400 | D93: =IF(OR(B93="",C93=""),"",B93-C93) | E93: =IF(OR(C93="",C93=0,D93=""),"",D93/C93) | F93: =$F$74 | G93: =IF(OR(E93="",F93=""),"",MAX(0,E93)*F93) | H93: =IF(OR(D93="",D93<=0),"",F93/(D93/1000))
A94: Vacation | B94: =IF(C50="","",C50) | C94: 363 | D94: =IF(OR(B94="",C94=""),"",B94-C94) | E94: =IF(OR(C94="",C94=0,D94=""),"",D94/C94) | F94: =$H$74 | G94: =IF(OR(E94="",F94=""),"",MAX(0,E94)*F94) | H94: =IF(OR(D94="",D94<=0),"",F94/(D94/1000))
A95: Pension | B95: =IF(C51="","",C51) | C95: 280 | D95: =IF(OR(B95="",C95=""),"",B95-C95) | E95: =IF(OR(C95="",C95=0,D95=""),"",D95/C95) | F95: =$J$74 | G95: =IF(OR(E95="",F95=""),"",MAX(0,E95)*F95) | H95: =IF(OR(D95="",D95<=0),"",F95/(D95/1000))
A96: PRODUCTION TOTALS | B96: =IF(C52="","",C52) | C96: 16043 | D96: =IF(OR(B96="",C96=""),"",B96-C96) | G96: =IF(COUNT(G92:G95)=0,"",SUM(G92:G95))
A97: Production Package Value Index | B97: =IF(OR(G96="",$B$74="",$B$74=0),"",G96/$B$74*100)
A98: Suggested production productivity % (heuristic) | B98: =IF(B97="","",MIN(0.85,0.7+MIN(0.12,B97*0.0015))) | C98: Copy to B53 and Manufacturing!B30 when locked
A100: Interactive: allocate extra $/person above industry by importance weights
A101: Role | B101: Sales | C101: Sales or Production
A102: Extra budget $/person above industry total | B102: 2000 | C102: Yellow — try 1000 / 2000 / 4000
A103: Industry total for role | B103: =IF(UPPER(LEFT(B101,1))="P",16043,19310)
A104: Component | B104: Importance share | C104: Suggested extra $ | D104: Implied total $ | E104: Notes
A105: Salary | B105: =$D$74/$B$74 | C105: =$B$102*B105 | D105: =IF(UPPER(LEFT($B$101,1))="P",14000,17000)+C105 | E105: Highest weight — put most of the raise here
A106: Health Benefits | B106: =$F$74/$B$74 | C106: =$B$102*B106 | D106: =IF(UPPER(LEFT($B$101,1))="P",1400,1700)+C106 | E106: Round to nearest health tier cost (menu rows 24–28)
A107: Vacation | B107: =$H$74/$B$74 | C107: =$B$102*B107 | D107: =IF(UPPER(LEFT($B$101,1))="P",363,440)+C107 | E107: Round to vacation week cost
A108: Pension | B108: =$J$74/$B$74 | C108: =$B$102*B108 | D108: =IF(UPPER(LEFT($B$101,1))="P",280,170)+C108 | E108: Convert $ to pension % of salary after salary set
A109: Suggested package total | B109: =$B$103+$B$102
A110: Check: suggested extras sum | B110: =SUM(C105:C108)
A112: How to use
...

Sheet Q3_BSC
A1: Balanced Scorecard — Q3 actual (WeBike vs industry)
A2: Total Performance = product of all indicators. WeBike = LAST place (0.411 = industry minimum).
A3: Indicator | B3: Min | C3: Max | D3: Average | E3: WeBike | F3: vs Avg | G3: Read | H3: WeBike rank
A4: Total Performance | B4: 0.411 | C4: 21.531 | D4: 5.897 | E4: 0.411 | F4: =E4-D4 | G4: LAST — dragged by Market Perf + Asset Mgmt | H4: 7
A5: Financial Performance | B5: 5.319 | C5: 37.687 | D5: 19.006 | E5: 5.319 | F5: =E5-D5 | G5: LAST — operating loss | H5: 7
A6: Market Performance | B6: 0.085 | C6: 0.345 | D6: 0.185 | E6: 0.098 | F6: =E6-D6 | G6: Near last — 33% stock-outs | H6: 6
A7: Marketing Effectiveness | B7: 0.66 | C7: 0.765 | D7: 0.743 | E7: 0.738 | F7: =E7-D7 | G7: At par — ads working | H7: 6
A8: Investment in Future | B8: 3.466 | C8: 7.401 | D8: 5.386 | E8: 6.795 | F8: =E8-D8 | G8: STRENGTH — 2nd best | H8: 2
A9: Wealth | B9: 0.668 | C9: 1.017 | D9: 0.831 | E9: 0.668 | F9: =E9-D9 | G9: LAST — cumulative losses | H9: 7
A10: Human Resource Mgmt | B10: 0.691 | C10: 0.767 | D10: 0.724 | E10: 0.713 | F10: =E10-D10 | G10: Below avg — pay fell behind | H10: 5
A11: Asset Management | B11: 0.353 | C11: 0.92 | D11: 0.542 | E11: 0.353 | F11: =E11-D11 | G11: LAST — $1.01M idle cash | H11: 7
A12: Manufacturing Productivity | B12: 0.722 | C12: 0.995 | D12: 0.899 | E12: 0.938 | F12: =E12-D12 | G12: STRENGTH — but only by under-scheduling | H12: 2
A13: Financial Risk | B13: 1 | C13: 1 | D13: 1 | E13: 1 | F13: =E13-D13 | G13: No debt | H13: 1
A15: Cumulative BSC (Q2+Q3)
A16: Indicator | B16: Min | C16: Max | D16: Average | E16: WeBike
A17: Cumulative Total Performance | B17: 0.033 | C17: 6.54 | D17: 2.466 | E17: 0.033
A18: Cumulative Financial Performance | B18: 1.203 | C18: 24.032 | D18: 12.327 | E18: 1.203
A19: Cumulative Market Performance | B19: 0.091 | C19: 0.264 | D19: 0.168 | E19: 0.091
A20: Cumulative Marketing Effectiveness | B20: 0.576 | C20: 0.754 | D20: 0.701 | E20: 0.576
A21: Cumulative Investment in Future | B21: 3.466 | C21: 7.401 | D21: 5.386 | E21: 6.795
A22: Cumulative Wealth | B22: 0.668 | C22: 1.017 | D22: 0.831 | E22: 0.668
A23: Cumulative HR Management | B23: 0.666 | C23: 0.75 | D23: 0.709 | E23: 0.733
A24: Cumulative Asset Management | B24: 0.28 | C24: 0.71 | D24: 0.444 | E24: 0.28
A25: Cumulative Manufacturing Productivity | B25: 0.566 | C25: 0.969 | D25: 0.852 | E25: 0.566
A26: Cumulative Financial Risk | B26: 1 | C26: 1 | D26: 1 | E26: 1
A29: Sensitivity — what moves Total Performance
A30: Scenario | B30: Total Performance | C30: Note
A31: Q3 actual | B31: 0.411 | C31: baseline
A32: Serve 100% of demand (MP 0.098 -> 0.150) | B32: =0.411/0.098*0.15 | C32: no stock-outs, same share
A33: + Asset turnover 0.353 -> 0.55 | B33: =B32/0.353*0.55 | C33: deploy idle cash into revenue
A34: + HR 0.713 -> 0.80 | B34: =B33/0.713*0.80 | C34: raise pay above new industry avg

Sheet Q3_Market
A1: Q3 Market Demand & Share (all competitors)
A2: Mountain is our strong segment (#2 of 7). Speed is crowded and we are weak there.
A3: Company | B3: Recreation | C3: Mountain | D3: Speed | E3: Total Demand | F3: Rec % | G3: Mtn % | H3: Speed % | I3: Total %
A4: Bike Bros | B4: 138 | C4: 172 | D4: 180 | E4: 490 | F4: 0.067 | G4: 0.1061 | H4: 0.0625 | I4: 0.0747
A5: LiteCycle | B5: 96 | C5: 340 | D5: 548 | E5: 984 | F5: 0.0466 | G5: 0.2097 | H5: 0.1904 | I5: 0.15
A6: WeBike | B6: 54 | C6: 358 | D6: 215 | E6: 627 | F6: 0.0262 | G6: 0.2209 | H6: 0.0747 | I6: 0.0956
A7: BB LLC | B7: 99 | C7: 751 | D7: 657 | E7: 1507 | F7: 0.0481 | G7: 0.4633 | H7: 0.2283 | I7: 0.2298
A8: Spoke'd Up | B8: 492 | C8: 0 | D8: 362 | E8: 854 | F8: 0.2388 | G8: 0 | H8: 0.1258 | I8: 0.1302
A9: SpaceBikes | B9: 710 | C9: 0 | D9: 588 | E9: 1298 | F9: 0.3447 | G9: 0 | H9: 0.2043 | I9: 0.1979
A10: MILC Bikes | B10: 471 | C10: 0 | D10: 328 | E10: 799 | F10: 0.2286 | G10: 0 | H10: 0.114 | I10: 0.1218
A11: TOTAL | B11: 2060 | C11: 1621 | D11: 2878 | E11: 6559
A14: Segment read | B14: Detail
A15: Mountain | B15: Only 4 of 7 firms compete. We are #2 at 22.1% behind BB LLC 46.3%. Smallest segment (1,621) but least crowded.
A16: Speed | B16: Largest segment (2,878) and all 7 firms compete. We are 6th at 7.5%. Swift Bike is not winning.
A17: Recreation | B17: Not targeted. 3 firms own ~81% of it.
A18: BB LLC | B18: Industry leader: 23% total share, dominates Mountain AND #1 Speed. Main rival in our primary.
A21: Demand after ill will & stock-outs (WeBike)
A22: Brand | B22: Generated Demand | C22: Net Demand | D22: Lost to Stock-out | E22: Units Sold
A23: Hike Bike | B23: 412 | C23: 412 | D23: 134 | E23: 278
A24: Swift Bike | B24: 215 | C24: 215 | D24: 70 | E24: 145
A25: Total | B25: 627 | C25: 627 | D25: 204 | E25: 423
A26: Percent of demand served | B26: =E25/C25 | E26: 67%
A27: Q4 ill-will penalty (half of lost %) | B27: =D25/C25/2 | C27: Q4 generated demand cut by this

Sheet Q3_Financials
A1: Income Statement / Cash Flow / Balance Sheet — Q1-Q3 actual
A3: Income Statement | B3: Q1 | C3: Q2 | D3: Q3
A4: Revenues | B4: 0 | C4: 266175 | D4: 589720
A5: - Cost of Goods Sold | B5: 0 | C5: 100928 | D5: 272340
A6: =Gross Profit | B6: 0 | C6: 165247 | D6: 317380
A7: Research and Development | B7: 30000 | C7: 0 | D7: 30000
A8: + Advertising | B8: 0 | C8: 81780 | D8: 119165
A9: + Internet Marketing | B9: 0 | C9: 1000 | D9: 2000
A10: + Sales Force Expense | B10: 0 | C10: 70010 | D10: 93815
A11: + Store and Web Center Expense | B11: 286000 | C11: 194000 | D11: 121000
A12: + Web Sales Productivity | B12: 0 | C12: 18000 | D12: 6000
A13: + Marketing Research | B13: 0 | C13: 20000 | D13: 20000
A14: + Shipping | B14: 0 | C14: 3537 | D14: 6830
A15: + Excess Capacity Cost | B15: 0 | C15: 148652 | D15: 0
A16: + Depreciation | B16: 0 | C16: 30000 | D16: 30000
A17: =Total Expenses | B17: 316000 | C17: 566978 | D17: 428810
A18: Operating Profit | B18: -316000 | C18: -401731 | D18: -111431
A19: =Net Income | B19: -316000 | C19: -401731 | D19: -111431
A20: Earnings per Share | B20: -21 | C20: -20 | D20: -4
A24: Cash Flow | B24: Q1 | C24: Q2 | D24: Q3
A25: Beginning Cash | B25: 0 | C25: 464000 | D25: 592269
A26: Net Operating Cash Flow | B26: -316000 | C26: -371731 | D26: -81431
A27: Investing (fixed capacity) | B27: 720000 | C27: 0 | D27: 0
A28: Financing (stock issued) | B28: 1500000 | C28: 500000 | D28: 500000
A29: Ending Cash | B29: 464000 | C29: 592269 | D29: 1010838
A32: Balance Sheet | B32: Q1 | C32: Q2 | D32: Q3
A33: Cash | B33: 464000 | C33: 592269 | D33: 1010838
A34: 3-Month CD | B34: 0 | C34: 0 | D34: 0
A35: Net Fixed Assets | B35: 720000 | C35: 690000 | D35: 660000
A36: =Total Assets | B36: 1184000 | C36: 1282269 | D36: 1670838
A37: Common Stock | B37: 1500000 | C37: 2000000 | D37: 2500000
A38: Retained Earnings | B38: -316000 | C38: -717731 | D38: -829162
A39: Shares issued | B39: 15000 | C39: 20000 | D39: 25000
A42: Industry ratios (Q3) | B42: Lowest | C42: Highest | D42: Average | E42: WeBike
A43: Fixed Assets Turnover | B43: 0.63 | C43: 2.14 | D43: 1.22 | E43: 0.89
A44: Total Assets Turnover | B44: 0.35 | C44: 0.92 | D44: 0.54 | E44: 0.35
A45: Gross Profit Margin | B45: 0.5382 | C45: 0.6547 | D45: 0.5824 | E45: 0.5382
A46: Net Profit Margin | B46: -0.41 | C46: 0.2823 | D46: 0.009 | E46: -0.189
A47: Return on Assets | B47: -0.1493 | C47: 0.2132 | D47: 0.0368 | E47: -0.0667
A48: Revenues | B48: 589720 | C48: 2198310 | D48: 1170036 | E48: 589720
A49: Gross Profit | B49: 317380 | C49: 1204529 | D49: 683601 | E49: 317380
A50: Net Income | B50: -297348 | C50: 510317 | D50: 103771 | E50: -111431

Sheet Q3_Unit_Economics
A1: Q3 realized unit economics + cost of the stock-out
A2: Actual prices/costs from the Sales report. Contribution per unit is strong; we simply did not build enough.
A3: Brand | B3: Units Sold | C3: Revenue | D3: COGS | E3: Price/unit | F3: Cost/unit | G3: Contribution/unit | H3: Lost units | I3: Lost contribution
A4: Hike Bike | B4: 278 | C4: 379470 | D4: 171741 | E4: =C4/B4 | F4: =D4/B4 | G4: =E4-F4 | H4: 134 | I4: =G4*H4
A5: Swift Bike | B5: 145 | C5: 210250 | D5: 100599 | E5: =C5/B5 | F5: =D5/B5 | G5: =E5-F5 | H5: 70 | I5: =G5*H5
A6: Total | B6: =SUM(B4:B5) | C6: =SUM(C4:C5) | D6: =SUM(D4:D5) | H6: =SUM(H4:H5) | I6: =SUM(I4:I5)
A9: Counterfactual — if every unit of demand had been built
A10: Q3 operating profit (actual) | B10: -111431
A11: + Gross margin lost to stock-outs | B11: =I6
A12: =Operating profit if fully served | B12: =B10+B11
A13: Note | B13: Ignores extra shipping/labor; higher volume would also LOWER unit cost (cost curve).
A16: Capacity back-solve — what actually happened
A17: Units produced | B17: 423
A18: Overtime as % of operating capacity used | B18: 0.13
A19: Implied normal-hours units | B19: =B17/(1+B18)
A20: Implied units/day (65 days) | B20: =B19/65
A21: Production worker productivity (actual) | B21: 0.72
A22: Implied SCHEDULED operating capacity | B22: =B20/B21
A23: Fixed capacity available | B23: 24
A24: Unused fixed capacity per day | B24: =B23-B22
A25: Read | B25: We owned 24/day and only scheduled ~8/day. The stock-out was a scheduling error, not a printer shortage.

Sheet Q4_Planner
A1: Q4 planning — operating capacity sizing (yellow = decision)
A2: Rule: required OC/day = forecast units / (productivity x 65 days). Never schedule below the forecast again. Q3 proof: OC 8/day vs 24 owned -> 204 stock-outs AND labour cost/unit up $130 -> $205.
A3: Input | B3: Value | C3: Note
A4: Q3 generated demand | B4: 627 | C4: actual
A5: Ill-will penalty % (half of 32.5% lost) | B5: 0.163 | C5: applies to Q4 generated demand
A6: Assumed demand growth before ill will | B6: 1.25 | C6: Q3 demand growth was +235% (highest in industry) on 2 stores; 1.25x is conservative
A7: Q4 forecast demand (after ill will) | B7: =B4*B6*(1-B5) | C7: feed to Demand_Forecast
A8: Assumed production worker productivity | B8: 0.74 | C8: Graph-checked: industry runs 68-73%. Assume 74% WITH a pay raise. Never plan on 85%.
A9: Capacity factor (1 / productivity) | B9: =1/B8 | C9: CORRECTED: was 1+(1-p)=1.26, which understated the requirement. 1/0.74 = 1.35.
A10: Required OC per day | B10: =B7/(B8*65) | C10: units / (productivity x days) - schedule AT LEAST this
A11: Required OC per quarter | B11: =B10*65
A12: Fixed capacity per day | B12: 24 | C12: 3 printers
A13: Headroom (fixed - required) | B13: =B12-B10 | C13: if negative, order printers THIS quarter
A14: Suggested scheduled OC (safety on top) | B14: =ROUNDUP(B10*1.1,0) | C14: ~10% cushion vs excess-capacity cost
A18: Other Q4 levers | B18: Q3 value | C18: Direction | D18: Why
A19: Sales force productivity | B19: 0.7 | C19: RAISE PAY | D19: Fell from 85% projected — competitors out-paid us; Q4 shows industry averages
A20: Production worker productivity | B20: 0.72 | C20: RAISE PAY | D20: Same; also feeds capacity pad
A21: Common stock issued | B21: 500000 | C21: STOP if cash idle | D21: More shares lowers Financial Performance (per-share) and Asset Turnover
A22: Cash on hand | B22: 1010838 | C22: DEPLOY | D22: Idle cash is the #1 cause of Asset Mgmt 0.353 (last place)
A23: City #3 | C23: OPEN ONE | D23: Revenue growth is the cure for Asset Turnover and unit cost
A24: Speed share | B24: 0.0747 | C24: FIX OR REFOCUS | D24: Speed ad judgment 70 vs Mountain 80; segment is crowded by all 7 firms
A25: Gross margin | B25: 0.5382 | C25: RISES WITH VOLUME | D25: Lowest in industry because volume is lowest
A28: INDUSTRY BENCHMARKS FOR Q4 (from Strategic Graphs) | B28: WeBike Q3 | C28: Industry | D28: Q4 target
A29: Scheduled operating capacity [units/day] | B29: 8 | C29: 14 - 30 | D29: 15
A30: Fixed capacity [units/day] | B30: 24 | C30: 16 - 32 | D30: 24
A31: Overtime capacity [units/day] | B31: 1 | C31: 0 - 7 | D31: 0 - 2
A32: Average COGS per unit [$] | B32: 620 | C32: BB LLC lowest | D32: < 550
A33: Average labor cost per unit [$] | B33: 205 | D33: < 150
A34: Sales compensation [$] | B34: 24425 | C34: 7-firm mean 25,211 (range 22,060-27,630) | D34: 26564
A35: Production compensation [$] | B35: 20757 | C35: 7-firm mean 21,441 (range 19,609-23,293) | D35: 22240
A36: Demand per sales person | B36: 45 | C36: 60 typical / 72 best | D36: 60
A37: Store + web center spend [$] | B37: 121000 | C37: up to 360,000 | D37: raise — open city #3
A38: Organic SEM clicks | B38: 150 | C38: 440 best | D38: 300
A39: Number of stores | B39: 2 | C39: 2 (all but Bike Bros) | D39: 3
A42: UNIT-COST UPSIDE — why right-sizing OC pays twice
A43: Q3 COGS per unit | B43: 620
A44: Target COGS per unit at ~15/day scale | B44: 550
A45: Saving per unit | B45: =B43-B44
A46: DEMAND SCENARIOS -> REQUIRED OPERATING CAPACITY | B46: Demand | C46: Required OC/day | D46: Fits in 24/day?
A47: A. Do nothing (Q3 demand less 16.3% ill will) | B47: 525 | C47: =B48/(0.74*65) | D47: =IF(C48<=24,"yes","NO")
A48: B. Base forecast (planner B7) | B48: =B7 | C48: =B49/(0.74*65) | D48: =IF(C49<=24,"yes","NO")
A49: C. + fill Rio to the 7-person cap | B49: =B49+200 | C49: =B50/(0.74*65) | D49: =IF(C50<=24,"yes","NO")
A50: D. + full web rebuild (7 staff, 4 tactics) | B50: =B50+315 | C50: =B51/(0.74*65) | D50: =IF(C51<=24,"yes","NO")
A51: E. + New York store | B51: =B51+400 | C51: =B52/(0.74*65) | D51: =IF(C52<=24,"yes","NO")
A52: Max units at 24/day and 74% productivity | B52: =24*0.74*65
A53: Read | D53: Scenario C (Rio fill) fits comfortably at 17.8/day. Scenario D (Rio + full web rebuild) needs 24.3/day and EXCEEDS our 24/day fixed capacity by a hair. Scenario E (plus New York) needs 32.7/day. Capacity - not demand, not product - is now the binding constraint on growth.
A56: WEB & STAFFING TARGETS (from Q3_Web_Ops / Q3_Staffing) | B56: WeBike Q3 | C56: Industry | D56: Q4 target
A57: Web staff (cap is 7) | B57: 3 | C57: 7 (four firms) | D57: 7
A58: Web productivity tactics funded (of 4) | B58: 1 | C58: 4 | D58: 4
A59: Web productivity budget | B59: 6000 | C59: 24,000 - 33,000 | D59: 28000
A60: Web demand | B60: 120 | C60: 435 - 569 | D60: 435
A61: Rio store staff (cap is 7) | B61: 4 | C61: - | D61: 7
A62: Amsterdam store staff (cap is 7) | B62: 7 | C62: 7 | D62: 7 (AT CAP - no room)
A63: Untrained staff | B63: 2 | C63: 0 | D63: 0
A66: CAPACITY IS NOW THE BINDING CONSTRAINT — and idle cash is the cure | B66: Value | C66: Note
A67: Cash sitting idle | B67: 1010838 | C67: the direct cause of Asset Management 0.353 (LAST place)
A68: Fixed capacity today | B68: 24 | C68: 3 printers, $720,000 original cost -> ~$240,000 each
A69: Max units at 24/day and 74% productivity | B69: =24*0.74*65
A70: Demand if we fill Rio AND rebuild web | B70: 1171 | C70: exceeds the ceiling by ~17 units
A71: A 4th printer would give | B71: 32 | C71: units/day -> max ~1,539 units
A72: Approx capital cost | B72: 240000 | C72: 24% of idle cash
A73: Approx added depreciation | B73: 10000 | C73: per quarter
A74: Read | C74: Buying capacity solves TWO problems at once: it lifts the growth ceiling AND converts idle cash into revenue-producing assets, which is exactly what Asset Management 0.353 is punishing. Note that owning capacity is NOT what caused Q2's $148,652 excess-capacity charge - that came from SCHEDULING operating capacity we did not use. Depreciation is the only carrying cost of ownership.
A75: Decision framing | C75: If we want Rio + web + New York we need roughly 33/day, i.e. 2 more printers. If we want Rio + web only, 1 more printer gives comfortable slack. Doing nothing caps us at ~1,154 units.

Sheet Q3_Industry_Graphs
A1: Q3 Strategic Graphs — industry comparison (WeBike vs 6 rivals)
A2: Source: Strategic Graphs > Workspace, Quarter 4 view (shows Q0-Q3 actuals). Chart-read values are approximate; numeric report values live in Q3_BSC / Q3_Market / Q3_Financials.
A3: SUPERSEDED IN PART by Q3_Competitor_Profiles (exact report). Corrections: BB LLC fixed=24 OC=24 OT=6.90 · MILC OC=17 not 24 · LiteCycle OC=14 · Spoke'd Up OC=15 · sales prod ceiling 78 (BB LLC) · sales pay avg $25,211 / worker avg $21,441 — we are BELOW both.
A4: MANUFACTURING — capacity (units/day) | B4: Q2 | C4: Q3 | D4: Note
A5: WeBike fixed capacity | B5: 24 | C5: 24 | D5: 3 printers; tied 2nd highest in industry
A6: WeBike SCHEDULED operating capacity | B6: 20 | C6: 8 | D6: CONFIRMS the back-solve: we cut OC by 60%
A7: WeBike overtime capacity | B7: 0 | C7: 1 | D7: ran OT on top of a tiny base
A8: SpaceBikes operating capacity | B8: 20 | C8: 30 | D8: leader — expanded fixed capacity to 32
A9: MILC Bikes operating capacity | B9: 16 | C9: 24
A10: Bike Bros operating capacity | B10: 10 | C10: 15
A11: LiteCycle operating capacity | B11: 8 | C11: 15
A12: BB LLC operating capacity | B12: 6 | C12: 15 | D12: + ~7 overtime — highest OT in industry
A13: Spoke'd Up operating capacity | B13: 5 | C13: 14
A14: WeBike RANK on operating capacity | C14: LAST (7 of 7) | D14: Only firm that REDUCED operating capacity in Q3
A16: MANUFACTURING — WeBike unit costs | B16: Q2 | C16: Q3 | D16: Read
A17: Capacity utilization [%] | B17: 16 | C17: 73 | D17: Q2 = idle plant; Q3 = tight plant, but tiny plant
A18: Average labor cost per unit [$] | B18: 130 | C18: 205 | D18: ROSE 58% — small OC + overtime is expensive per unit
A19: Average cost of goods sold per unit [$] | B19: 520 | C19: 620 | D19: ROSE ~19% despite selling 4x the units
A20: Production cost [$] | B20: 100928 | C20: 272340
A21: Stock-outs [units] | B21: 0 | C21: 204 | D21: the whipsaw
A22: Excess capacity cost [$] | B22: 148652 | C22: 0 | D22: the whipsaw, other direction
A23: Lesson | D23: Under-scheduling cost us BOTH revenue AND margin. Volume normally lowers unit cost; we broke that by running a sub-scale OC with overtime.
A25: MARKET — segment size (units) | B25: Q2 | C25: Q3 | D25: Growth | E25: Note
A26: Speed | B26: 1500 | C26: 2878 | D26: =C25/B25-1 | E26: LARGEST and fastest growing; all 7 firms compete
A27: Recreation | B27: 1100 | C27: 2060 | D27: =C26/B26-1 | E27: we do not compete
A28: Mountain | B28: 1050 | C28: 1621 | D28: =C27/B27-1 | E28: SMALLEST and slowest; our primary; only 4 firms
A29: Total market | B29: 3700 | C29: 6559 | D29: =C28/B28-1 | E29: Strategic tension: our least-crowded segment is also the smallest and slowest-growing.
A31: MARKET — searches (web interest, Q3) | B31: Approx | C31: Note
A32: Recreation | B32: 1350 | C32: highest search volume — segment we ignore
A33: Mountain | B33: 1030
A34: Speed | B34: 900 | C34: large demand but lowest search volume
A36: MARKET — Q3 share by segment [%] | B36: Recreation | C36: Mountain | D36: Speed | E36: Overall | F36: Note
A37: BB LLC | B37: 4.8 | C37: 46.3 | D37: 22.8 | E37: 23 | F37: LEADER — all 3 segments, dominates Mountain
A38: SpaceBikes | B38: 34.5 | C38: 0 | D38: 20.4 | E38: 19.8 | F38: #2 — Rec + Speed only, no Mountain
A39: Spoke'd Up | B39: 23.9 | C39: 0 | D39: 12.6 | E39: 13
A40: LiteCycle | B40: 4.7 | C40: 21 | D40: 19 | E40: 15 | F40: our closest Mountain rival
A41: MILC Bikes | B41: 22.9 | C41: 0 | D41: 11.4 | E41: 12.2
A42: WeBike | B42: 2.6 | C42: 22.1 | D42: 7.5 | E42: 9.6 | F42: #2 Mountain, 6th Speed
A43: Bike Bros | B43: 6.7 | C43: 10.6 | D43: 6.3 | E43: 7.5 | F43: FALLING in every segment (Mtn 19->11)
A45: MARKET — demand productivity per head (Q3, approx) | B45: WeBike | C45: Industry best | D45: Industry typical | E45: Note
A46: Demand per sales person | B46: 45 | C46: 72 | D46: 60 | E46: LAST — every rival gets more demand per head
A47: Demand per store sales person | B47: 46 | C47: 88 | D47: 70 | E47: BB LLC ~88; our stores under-produce
A48: Demand per web sales center person | B48: 42 | C48: 95 | D48: 75 | E48: we CUT web staff in Q3 — wrong lever
A49: Total sales people | B49: 14 | C49: 21 | D49: 14 | E49: headcount is at parity; output per head is not
A51: MARKET — demand vs units sold (the leakage) | B51: Value | C51: Note
A52: WeBike share of total DEMAND [%] | B52: 9.6 | C52: what we created
A53: WeBike share of UNITS SOLD [%] | B53: 7.3 | C53: what we captured
A54: Leakage [pct points] | B54: =B48-B49 | C54: pure stock-out loss, visible in the graphs
A55: Q3 demand growth rate [%] | B55: 235 | C55: highest in industry — demand generation is NOT our problem
A57: MARKETING INPUTS (Q3, approx) | B57: WeBike | C57: Industry high | D57: Rank | E57: Note
A58: Advertising expenses [$] | B58: 119165 | C58: 145000 | D58: 3rd | E58: spend is competitive
A59: Total regional ads [count] | B59: 19 | C59: 24 | D59: 2nd | E59: ad VOLUME is a strength
A60: Organic SEM clicks | B60: 150 | C60: 440 | D60: 6th | E60: weak; BB LLC 440, SpaceBikes 400
A61: Organic SEM expenses [$] | B61: 2000 | C61: 5000 | D61: 3rd | E61: Bike Bros spends 5k for 200 clicks — poor ROI benchmark
A62: Average price [$] | B62: 1400 | C62: 1480 | D62: 3rd | E62: BB LLC prices HIGHER and still leads share
A63: Number of stores | B63: 2 | C63: 2 | D63: tied | E63: everyone but Bike Bros has 2 -> city #3 is a differentiator
A64: Number of web sales centers | B64: 1 | C64: 1 | D64: tied
A65: Store + web center expenses [$] | B65: 121000 | C65: 360000 | D65: lowest | E65: we UNDER-invest in channel
A67: HUMAN RESOURCES (Q3, approx) — CORRECTS earlier read | B67: WeBike | C67: Industry range | D67: Note
A68: Production worker compensation [$] | B68: 20757 | C68: 19,609 - 23,293 (7-firm) | D68: tied 5th/6th of 7; mix already right, salary low
A69: Sales force compensation [$] | B69: 24425 | C69: 22,060 - 27,630 (7-firm) | D69: 6th of 7; salary starved, Full coverage bloated
A70: Production worker productivity [%] | B70: 72 | C70: 68 - 73 | D70: MID-PACK, not behind
A71: Sales force productivity [%] | B71: 70 | C71: 70 - 75 | D71: MID-PACK; BB LLC ~75 best
A72: Comp satisfaction | B72: 68 | C72: 65 - 72
A73: CORRECTION | D73: The whole industry runs ~70%. Our 85% projection was never realistic. The error was PLANNING CAPACITY on 85%, not being badly underpaid. Pay raises buy a few points, not 15.
A75: BALANCED SCORECARD — Q3 by firm (approx from graph) | B75: Total Perf | C75: Financial | D75: Market | E75: Asset Mgmt | F75: Wealth
A76: BB LLC | B76: 22 | C76: 37.7 | D76: 0.345 | E76: 0.92 | F76: 0.87
A77: SpaceBikes | B77: 11 | C77: 34 | D77: 0.27 | E77: 0.67 | F77: 0.95
A78: MILC Bikes | B78: 2.8 | C78: 15 | D78: 0.175 | E78: 0.48 | F78: 0.79
A79: Bike Bros | B79: 2.5 | C79: 14 | D79: 0.085 | E79: 0.46 | F79: 0.82
A80: LiteCycle | B80: 2 | C80: 14.5 | D80: 0.155 | E80: 0.53 | F80: 0.8
A81: Spoke'd Up | B81: 1 | C81: 6 | D81: 0.15 | E81: 0.42 | F81: 0.79
A82: WeBike | B82: 0.411 | C82: 5.319 | D82: 0.098 | E82: 0.353 | F82: 0.668
A84: CUMULATIVE BSC (approx) | B84: Value | C84: Note
A85: SpaceBikes | B85: 6.3 | C85: cumulative leader
A86: BB LLC | B86: 6.2 | C86: closing fast — Q3 single-quarter leader
A87: Bike Bros | B87: 1.3
A88: MILC Bikes | B88: 1.3
A89: Spoke'd Up | B89: 0.7
A90: LiteCycle | B90: 0.6
A91: WeBike | B91: 0.033 | C91: Q2 Manufacturing Productivity of 0.20 still poisons the cumulative product
A93: RIVAL PROFILES — what to copy and what to avoid | B93: Read
A94: BB LLC (leader) | B94: All 3 segments. Highest price (~$1,480) AND highest share. Most regional ads (24). Asset Mgmt 0.920 — best capital efficiency. Runs heavy overtime (~7) on modest fixed capacity: buys flexibility instead of printers. 21 sales people, ~88 demand per store rep.
A95: SpaceBikes (cumulative leader) | B95: Skips Mountain entirely; owns Recreation (34.5%) + Speed (20.4%). Expanded fixed capacity to 32/day — the only firm that out-built us. Highest ad spend (~$145k). Wealth 0.95.
A96: LiteCycle | B96: Our Mountain rival at 21.0%, plus 19.0% of Speed. Organic SEM clicks COLLAPSED 400->180.
A97: Bike Bros (cautionary tale) | B97: 1 store, 0 web sales centers, 7 sales people. Share falling in all three segments (Mountain 19->11). Under-channeling is fatal — this is the risk of our 'cut web spend' instinct.
A98: MILC / Spoke'd Up | B98: Mid-pack. Spoke'd Up has the highest market growth but lowest Marketing Effectiveness (0.66).
A100: Q4 IMPLICATIONS FROM THE GRAPHS | B100: Action
A101: 1. Operating capacity | B101: We were LAST at 8/day while owning 24. Schedule to forecast (~15/day). This is confirmed by the Operating Capacity chart, not just inferred.
A102: 2. Unit cost | B102: Labor cost/unit rose $130->$205 and COGS/unit $520->$620 because OC was sub-scale. Right-sizing OC cuts unit cost AND ends stock-outs — one decision, two wins.
A103: 3. Do NOT cut channel | B103: Store+web spend is the LOWEST in industry and demand per head is LAST. Bike Bros shows where that path ends. Open city #3 and re-staff web.
A104: 4. Pay expectations | B104: Industry productivity is ~70% across the board. Raise pay to upper-quartile (sales ~$26-27k, production ~$22-23k) but PLAN on ~73-75%, not 85%.
A105: 5. Segment strategy | B105: Mountain is the smallest, slowest segment (1,621) and BB LLC holds 46%. Speed is 2,878 and growing. Recreation has the most searches (1,350) and we hold 2.6%.
... A107: 7. Advertising | B107: Ad count 2nd, spend 3rd, Marketing Effectiveness at par. Marketing is NOT the problem. Weakest marketing input is organic SEM clicks (150 vs 440).

Sheet Q3_Brand_Judgment
A1: Brand Judgment — World Market, Q3 actual (all 20 industry brands)
A2: Score = segment appeal of the brand DESIGN (1 = no appeal). Exact figures from the sim report. A score of 1 means the brand is irrelevant to that segment.
A4: Brand | B4: Company | C4: Recreation | D4: Mountain | E4: Speed | F4: Targets | G4: Best score | H4: Gap to segment best
A5: MACH I.I | B5: Bike Bros | C5: 12 | D5: 1 | E5: 77 | F5: Speed | G5: 77 | H5: 0
A6: TERRAMAX | B6: Bike Bros | C6: 56 | D6: 73 | E6: 1 | F6: Mountain | G6: 73 | H6: 0
A7: Mach 0.6 | B7: Bike Bros | C7: 9 | D7: 1 | E7: 61 | F7: Speed | G7: 61 | H7: 16
A8: TERRAMean | B8: Bike Bros | C8: 59 | D8: 72 | E8: 1 | F8: Mountain | G8: 72 | H8: 1
A9: MountainCruise1 | B9: Bike Bros | C9: 76 | D9: 1 | E9: 1 | F9: Recreation | G9: 76 | H9: 0
A10: LiteSpeed Pro+ | B10: LiteCycle | C10: 12 | D10: 1 | E10: 77 | F10: Speed | G10: 77 | H10: 0
A11: LiteSpeed+ | B11: LiteCycle | C11: 7 | D11: 1 | E11: 74 | F11: Speed | G11: 74 | H11: 3
A12: LiteTrail Pro | B12: LiteCycle | C12: 58 | D12: 70 | E12: 1 | F12: Mountain | G12: 70 | H12: 3
A13: Hike Bike | B13: WeBike | C13: 56 | D13: 73 | E13: 1 | F13: Mountain | G13: 73 | H13: 0
A14: Swift Bike | B14: WeBike | C14: 10 | D14: 1 | E14: 72 | F14: Speed | G14: 72 | H14: 5
A15: Blu Ruged Ballz | B15: BB LLC | C15: 56 | D15: 73 | E15: 1 | F15: Mountain | G15: 73 | H15: 0
A16: Blu Aero Ballz | B16: BB LLC | C16: 7 | D16: 1 | E16: 74 | F16: Speed | G16: 74 | H16: 3
... A24: Skim MILC MKII | B24: MILC Bikes | C24: 9 | D24: 1 | E24: 76 | F24: Speed | G24: 76 | H24: 1
A26: SEGMENT CEILINGS — what the best design achieves | B26: Best score | C26: Who holds it | D26: WeBike | E26: Gap
A27: Mountain | B27: 73 | C27: Hike Bike (WeBike), TERRAMAX (Bike Bros), Blu Ruged Ballz (BB LLC) | D27: 73 | E27: 0
A28: Speed | B28: 77 | C28: MACH I.I (Bike Bros), LiteSpeed Pro+ (LiteCycle) | D28: 72 | E28: 5
A29: Recreation | B29: 76 | C29: MountainCruise1 (Bike Bros) | D29: n/a (56 spillover) | E29: n/a
A32: HEADLINE — Hike Bike is tied for the BEST Mountain brand in the industry
A33: Hike Bike Mountain judgment | B33: 73
A34: BB LLC Blu Ruged Ballz Mountain judgment | B34: 73
A35: Our Mountain share [%] | B35: 22.1
A36: BB LLC Mountain share [%] | B36: 46.3
A37: Share ratio on an IDENTICAL brand score | B37: =B36/B35
A38: Conclusion | B38: BB LLC takes 2.1x our Mountain share with a brand design scored EXACTLY the same as ours. The gap is therefore NOT product. It is supply (we stocked out 33%), sales coverage (21 sales people vs our 14, ~88 demand/store rep vs our 46) and ad volume (24 vs 19). Do not redesign Hike Bike. Feed it.
A41: SPEED GAP — Swift Bike is the weakest real Speed brand | B41: Rec | C41: Mtn | D41: Speed | E41: Note
A42: MACH I.I (Bike Bros) | B42: 12 | C42: 1 | D42: 77 | E42: co-best Speed design
A43: LiteSpeed Pro+ (LiteCycle) | B43: 12 | C43: 1 | D43: 77 | E43: co-best Speed design
A44: Blu Tube Ballz (BB LLC) | B44: 9 | C44: 1 | D44: 76
A45: The Armstrong (SpaceBikes) | B45: 9 | C45: 1 | D45: 76
A46: Skim MILC MKII (MILC) | B46: 9 | C46: 1 | D46: 76
A47: Spoke'd Speed (Spoke'd Up) | B47: 10 | C47: 1 | D47: 75
A48: LiteSpeed+ (LiteCycle) | B48: 7 | C48: 1 | D48: 74
A49: Blu Aero Ballz (BB LLC) | B49: 7 | C49: 1 | D49: 74
A50: Swift Bike (WeBike) | B50: 10 | C50: 1 | D50: 72 | E50: 2nd WORST — 5 points off the ceiling
A51: Mach 0.6 (Bike Bros) | B51: 9 | C51: 1 | D51: 61 | E51: only brand worse than ours
A52: Read | E52: 8 of 9 rival Speed brands beat Swift Bike. The winning profile (12/1/77) is nearly identical to ours (10/1/72) - so a modest redesign should close most of the 5-point gap. Combined with our Speed AD judgment of 70, weak product + weak ad explains 7.5% share in a 2,878-unit segment.
A55: DESIGN CONVERGENCE — the market has found the optimal profiles | B55: Brands sharing it
A56: 56 / 73 / 1 (Mountain optimum) | B56: TERRAMAX (Bike Bros), Hike Bike (WeBike), Blu Ruged Ballz (BB LLC)
A57: 58 / 70 / 1 (Mountain, 2nd tier) | B57: LiteTrail Pro (LiteCycle), Blu Tail Ballz (BB LLC)
A58: 12 / 1 / 77 (Speed optimum) | B58: MACH I.I (Bike Bros), LiteSpeed Pro+ (LiteCycle)
A59: 9 / 1 / 76 (Speed, 2nd tier) | B59: Blu Tube Ballz (BB LLC), The Armstrong (SpaceBikes), Skim MILC MKII (MILC)
A60: 7 / 1 / 74 (Speed, 3rd tier) | B60: LiteSpeed+ (LiteCycle), Blu Aero Ballz (BB LLC)
A61: 73 / 1 / 1 (Recreation) | B61: Spoke'd Easy (Spoke'd Up), Mars Rover (SpaceBikes)
A62: Read | B62: Multiple firms have landed on byte-identical designs. Brand design is becoming COMMODITISED - no one can win on product alone. Nobody exceeds 73 in Mountain or 77 in Speed, so those look like hard ceilings. Differentiation must come from supply, channel, ads and price.
A65: PORTFOLIO BREADTH | B65: Brands | C65: Segments covered | D65: Overall share [%] | E65: Note
A66: Bike Bros | B66: 5 | C66: Rec + Mtn + Speed | D66: 7.5 | E66: MOST brands, LOWEST share - 1 store, 0 web centers
A67: BB LLC | B67: 4 | C67: Rec* + Mtn + Speed | D67: 23 | E67: leader; 2 Mtn + 2 Speed brands, Rec via spillover only
A68: LiteCycle | B68: 3 | C68: Mtn + Speed | D68: 15
A69: WeBike | B69: 2 | C69: Mtn + Speed | D69: 9.6 | E69: at parity on count
A70: Spoke'd Up | B70: 2 | C70: Rec + Speed | D70: 13
A71: SpaceBikes | B71: 2 | C71: Rec + Speed | D71: 19.8 | E71: cumulative LEADER on just 2 brands - skips Mountain
A72: MILC Bikes | B72: 2 | C72: Rec + Speed | D72: 12.2
A73: Read | E73: Brand COUNT does not drive share: Bike Bros has 5 brands and last place; SpaceBikes has 2 and leads cumulatively. A 3rd brand is NOT our priority - filling demand for the 2 we have is.
A76: RECREATION SPILLOVER — a free option we are not using | B76: Score
A77: Hike Bike appeal to Recreation buyers | B77: 56
A78: Best dedicated Recreation brand (MountainCruise1) | B78: 76
A79: Recreation segment size [units] | B79: 2060
A80: Recreation searches (highest of 3 segments) | B80: 1350
A81: Our Recreation share [%] | B81: 2.6
A82: Our Recreation demand [units, untargeted] | B82: 54
A83: Read | B83: Hike Bike already scores 56 with Recreation buyers and pulled 54 units we never asked for. That is real latent demand in the LARGEST-search segment. But 56 vs 76 means we cannot win Recreation on spillover - it would need a dedicated brand. Park this as a Q5 option, not a Q4 one.
A86: Q4 BRAND ACTIONS | B86: Decision
A87: Hike Bike (Mountain) | B87: DO NOT REDESIGN. Tied for best in industry at 73 - already at the ceiling. Every dollar should go to supplying and selling it, not improving it.
A88: Swift Bike (Speed) | B88: REDESIGN toward the 12/1/77 profile. We are 5 points off the ceiling and 8 of 9 rival Speed brands beat us. Also strengthen the Speed ad (judgment 70).
A89: Third brand | B89: NO. Bike Bros proves brand count does not buy share. Fix supply first.
A90: Recreation | B90: DEFER. Spillover of 56 is not competitive vs 76; revisit in Q5 with a dedicated design.
A91: Price | B91: HOLD. Our Mountain brand matches the best design and BB LLC charges ~$1,480 - we have room at $1,365, not a reason to discount.

Sheet Q3_Components
A1: Competitors' Brands — component teardown, Q3 actual (all 20 brands)
A2: 1 = included, blank = not included. 'Base components' and 'Standard carbon fiber' are in every brand and omitted.
A4: Company | C4: Bike Bros | D4: Bike Bros | E4: Bike Bros | F4: Bike Bros | G4: Bike Bros | H4: LiteCycle | I4: LiteCycle | J4: LiteCycle | K4: WeBike | L4: WeBike | M4: BB LLC | N4: BB LLC | O4: BB LLC | P4: BB LLC | Q4: Spoke'd Up | R4: Spoke'd Up | S4: SpaceBikes | T4: SpaceBikes | U4: MILC Bikes | V4: MILC Bikes
A5: Brand | C5: MACH I.I | D5: TERRAMAX | E5: Mach 0.6 | F5: TERRAMean | G5: MountainCruise1 | H5: LiteSpeed Pro+ | I5: LiteSpeed+ | J5: LiteTrail Pro | K5: Hike Bike | L5: Swift Bike | M5: Blu Ruged Ballz | N5: Blu Aero Ballz | O5: Blu Tail Ballz | P5: Blu Tube Ballz | Q5: Spoke'd Easy | R5: Spoke'd Speed | S5: The Armstrong | T5: Mars Rover | U5: Whole MILC MKII | V5: Skim MILC MKII
A6: Targets | C6: Speed | D6: Mountain | E6: Speed | F6: Mountain | G6: Recreation | H6: Speed | I6: Speed | J6: Mountain | K6: Mountain | L6: Speed | M6: Mountain | N6: Speed | O6: Mountain | P6: Speed | Q6: Recreation | R6: Speed | S6: Speed | T6: Recreation | U6: Recreation | V6: Speed
A7: Judgment in target segment | C7: 77 | D7: 73 | E7: 61 | F7: 72 | G7: 76 | H7: 77 | I7: 74 | J7: 70 | K7: 73 | L7: 72 | M7: 73 | N7: 74 | O7: 70 | P7: 76 | Q7: 73 | R7: 75 | S7: 76 | T7: 73 | U7: 74 | V7: 76
A8: Frame
B9: Comfort (relaxed) | G9: 1 | Q9: 1 | T9: 1 | U9: 1
B10: Rugged (rough terrain) | D10: 1 | F10: 1 | J10: 1 | K10: 1 | M10: 1 | O10: 1
B11: Aerodynamic (speed) | C11: 1 | E11: 1 | H11: 1 | I11: 1 | L11: 1 | N11: 1 | P11: 1 | R11: 1 | S11: 1 | V11: 1
A12: Tires
B13: Mountain - high grip | D13: 1 | F13: 1 | J13: 1 | K13: 1 | M13: 1 | O13: 1
B14: Hybrid - road/off-road | G14: 1 | Q14: 1 | T14: 1 | U14: 1
B15: Racing - fast | C15: 1 | E15: 1 | H15: 1 | I15: 1 | L15: 1 | N15: 1 | P15: 1 | R15: 1 | S15: 1 | V15: 1
A16: Brakes
B17: Standard | T17: 1
B18: Precision | C18: 1 | E18: 1 | H18: 1 | I18: 1 | L18: 1 | N18: 1 | P18: 1 | Q18: 1 | R18: 1 | S18: 1 | U18: 1 | V18: 1
B19: Standard disc | D19: 1 | F19: 1 | G19: 1 | J19: 1 | K19: 1 | M19: 1 | O19: 1
A20: Handlebars
B21: Basic straight | D21: 1 | F21: 1 | J21: 1 | K21: 1 | M21: 1 | O21: 1
B22: Comfort straight | G22: 1 | Q22: 1 | T22: 1 | U22: 1
B23: Basic drop down | C23: 1 | E23: 1 | H23: 1 | I23: 1 | L23: 1 | N23: 1 | P23: 1 | R23: 1 | S23: 1 | V23: 1
A24: Gears
B25: 7 speed (1x7) | E25: 1 | G25: 1 | Q25: 1 | T25: 1 | U25: 1
B26: 14 speed (2x7) | C26: 1 | H26: 1 | I26: 1 | N26: 1 | P26: 1 | R26: 1 | S26: 1 | V26: 1
B27: 24 speed (3x8) | D27: 1 | F27: 1 | J27: 1 | K27: 1 | L27: 1 | M27: 1 | O27: 1
A28: Seat
B29: Polymer gel all-purpose | D29: 1 | F29: 1 | K29: 1 | M29: 1
B30: Polymer gel comfort | G30: 1 | J30: 1 | O30: 1 | Q30: 1 | T30: 1 | U30: 1
B31: Polymer gel racing | C31: 1 | E31: 1 | H31: 1 | I31: 1 | L31: 1 | N31: 1 | P31: 1 | R31: 1 | S31: 1 | V31: 1
A32: Accessories
B33: Reflectors | C33: 1 | E33: 1 | F33: 1 | G33: 1 | H33: 1 | L33: 1 | N33: 1 | Q33: 1 | R33: 1 | T33: 1 | U33: 1
A34: Decals
B35: Colorful brushstrokes | C35: 1 | D35: 1 | E35: 1 | F35: 1 | G35: 1 | H35: 1 | J35: 1 | K35: 1 | M35: 1 | O35: 1 | P35: 1 | Q35: 1 | S35: 1 | V35: 1
A36: Lights
B37: Standard | C37: 1 | E37: 1 | G37: 1 | H37: 1 | I37: 1 | L37: 1 | P37: 1 | R37: 1 | S37: 1 | T37: 1 | U37: 1 | V37: 1
A38: Carriers
B39: Plastic basket | G39: 1 | Q39: 1 | T39: 1 | U39: 1
A40: Suspension
B41: Front shocks | D41: 1 | F41: 1 | G41: 1 | J41: 1 | K41: 1 | M41: 1 | O41: 1 | Q41: 1 | T41: 1 | U41: 1

Sheet Q3_Design_Model
A1: Reverse-engineered brand judgment model (fitted to all 20 brands)
A2: Every brand in each segment shares one base recipe; scores differ only by a few components. The point values below reproduce all 20 observed scores exactly.
A4: SPEED — base recipe (all 10 Speed brands share this) | B4: Component
A5: Frame | B5: Aerodynamic
A6: Tires | B6: Racing - fast
A7: Brakes | B7: Precision
A8: Handlebars | B8: Basic drop down
A9: Seat | B9: Polymer gel racing
A10: Carriers / Suspension | B10: none
A13: SPEED — what the variable components are worth | B13: Points | C13: Evidence
A14: Gears 14 speed (2x7) | B14: optimal | C14: all 8 top Speed brands use it
A15: Gears 24 speed (3x8) instead | B15: -3 | C15: Swift Bike is the ONLY Speed brand with it
A16: Gears 7 speed (1x7) instead | B16: -16 | C16: Mach 0.6 = 61 with an otherwise full kit
A17: Decals (colorful brushstrokes) | B17: 2 | C17: every 76-77 brand has them; every 72-75 brand lacks them
A18: Reflectors | B18: 1 | C18: MACH I.I 77 (with) vs Blu Tube 76 (without), else identical
A19: Lights | B19: 1 | C19: Blu Aero 74 lacks lights; otherwise matches 75-point kit
A20: MAXIMUM ACHIEVABLE (Speed) | B20: 77 | C20: MACH I.I and LiteSpeed Pro+ both hit it
A23: SWIFT BIKE — exact fix to reach the industry ceiling | B23: Now | C23: Change to | D23: Points
A24: Frame | B24: Aerodynamic | C24: keep | D24: 0
A25: Tires | B25: Racing | C25: keep | D25: 0
A26: Brakes | B26: Precision | C26: keep | D26: 0
A27: Handlebars | B27: Basic drop down | C27: keep | D27: 0
A28: Seat | B28: Polymer gel racing | C28: keep | D28: 0
A29: Reflectors | B29: included | C29: keep | D29: 0
A30: Lights | B30: included | C30: keep | D30: 0
A31: Gears | B31: 24 speed (3x8) | C31: 14 speed (2x7) | D31: 3
A32: Decals | B32: not included | C32: ADD colorful brushstrokes | D32: 2
A33: Current judgment | B33: 72
A34: Projected judgment after both changes | B34: =B33+SUM(D32:D33) | C34: =industry ceiling (tied best)
A37: Why the gears mistake happened | B37: Note
A38: Root cause | B38: Swift Bike inherited the 24-speed (3x8) mountain drivetrain from Hike Bike. 24-speed is OPTIMAL in Mountain (all 6 Mountain brands use it) and WRONG in Speed (all 8 leading Speed brands use 14-speed). We copied our Mountain spec into a Speed bike.
A39: Cost side effect | B39: 14 speed (2x7) is a simpler drivetrain than 24 speed (3x8), so this change should also LOWER unit cost. Verify against the component price list before locking.
A42: MOUNTAIN — base recipe (all 6 Mountain brands share this) | B42: Component
A43: Frame | B43: Rugged
A44: Tires | B44: Mountain - high grip
A45: Brakes | B45: Standard disc
A46: Handlebars | B46: Basic straight
A47: Gears | B47: 24 speed (3x8)
A48: Suspension | B48: Front shocks
A49: Decals | B49: Colorful brushstrokes
A50: Lights / Carriers | B50: none
A53: MOUNTAIN — what the variable components are worth | B53: Points | C53: Evidence
A54: Seat: Polymer gel ALL-PURPOSE | B54: optimal | C54: Hike Bike, TERRAMAX, Blu Ruged Ballz all = 73
A55: Seat: Polymer gel COMFORT instead | B55: -3 | C55: LiteTrail Pro and Blu Tail Ballz both = 70
A56: Reflectors added | B56: -1 | C56: TERRAMean = 72; identical to Hike Bike except reflectors
A57: MAXIMUM ACHIEVABLE (Mountain) | B57: 73 | C57: Hike Bike already there
A60: HIKE BIKE — verified optimal, do not touch | B60: Status
A61: Seat | B61: Polymer gel all-purpose = correct (comfort seat would cost 3 points)
A62: Reflectors | B62: correctly EXCLUDED (adding them costs 1 point - they are a Recreation cue)
A63: Lights | B63: correctly excluded
A64: Judgment | B64: 73 of a possible 73 - nothing left to gain from redesign
A65: Implication | B65: Any Q4 budget aimed at improving Hike Bike is wasted. Spend it on capacity, sales coverage and ads instead.
A68: RECREATION — blueprint if we ever enter (Q5 option) | B68: Component
A69: Frame | B69: Comfort (relaxed)
A70: Tires | B70: Hybrid - road/off-road
A71: Brakes | B71: Standard disc <-- NOT precision (costs 2) and NOT standard (costs 1)
A72: Handlebars | B72: Comfort straight
A73: Gears | B73: 7 speed (1x7)
... A85: Seat | B85: The single biggest lever in Mountain: comfort seat = -3 vs all-purpose.

Sheet Q3_City_Demand
A1: Detailed Brand Demand — World Market by city, Q3 actual
A2: Reconciles exactly to 6,559 total / 627 WeBike / 412 Hike Bike / 215 Swift Bike.
A4: Brand | B4: Company | C4: City | D4: Recreation | E4: Mountain | F4: Speed | G4: Total
A5: LiteSpeed Pro+ | B5: LiteCycle | C5: New York City | D5: 0 | E5: 0 | F5: 39 | G5: 39
A6: LiteSpeed+ | B6: LiteCycle | C6: New York City | D6: 0 | E6: 0 | F6: 29 | G6: 29
A7: LiteTrail Pro | B7: LiteCycle | C7: New York City | D7: 13 | E7: 62 | F7: 0 | G7: 75
A8: Hike Bike | B8: WeBike | C8: New York City | D8: 3 | E8: 23 | F8: 0 | G8: 26
A9: Swift Bike | B9: WeBike | C9: New York City | D9: 0 | E9: 0 | F9: 12 | G9: 12
A10: Blu Ruged Ballz | B10: BB LLC | C10: New York City | D10: 19 | E10: 265 | F10: 0 | G10: 284
A11: Blu Aero Ballz | B11: BB LLC | C11: New York City | D11: 0 | E11: 0 | F11: 135 | G11: 135
A12: Blu Tail Ballz | B12: BB LLC | C12: New York City | D12: 22 | E12: 145 | F12: 0 | G12: 167
A13: Blu Tube Ballz | B13: BB LLC | C13: New York City | D13: 0 | E13: 0 | F13: 166 | G13: 166
A14: Spoke'd Easy | B14: Spoke'd Up | C14: New York City | D14: 237 | E14: 0 | F14: 0 | G14: 237
A15: Spoke'd Speed | B15: Spoke'd Up | C15: New York City | D15: 0 | E15: 0 | F15: 175 | G15: 175
A16: The Armstrong | B16: SpaceBikes | C16: New York City | D16: 0 | E16: 0 | F16: 272 | G16: 272
... A69: Skim MILC MKII | B69: MILC Bikes | C69: Bangalore | D69: 0 | E69: 0 | F69: 42 | G69: 42

Sheet Q3_City_Strategy
A1: City-level competitive map and the City #3 decision
A2: Amsterdam + New York are 77% of the entire market. We hold 9.9% of Amsterdam and 1.9% of New York, but 34.9% of Rio - the one city where we are the only firm with a store.
A4: CITY SIZE & OUR POSITION | B4: Recreation | C4: Mountain | D4: Speed | E4: Total demand | F4: % of market | G4: WeBike units | H4: WeBike share
A5: Amsterdam | B5: 992 | C5: 650 | D5: 1343 | E5: 2985 | F5: 0.45509986 | G5: 295 | H5: 0.098827471
A6: New York City | B6: 664 | C6: 495 | D6: 880 | E6: 2039 | F6: 0.31087056 | G6: 38 | H6: 0.018636587
A7: Rio de Janeiro | B7: 219 | C7: 286 | D7: 269 | E7: 774 | F7: 0.11800579 | G7: 270 | H7: 0.34883721
A8: Bangalore | B8: 185 | C8: 190 | D8: 386 | E8: 761 | F8: 0.11602378 | G8: 24 | H8: 0.031537451
A9: TOTAL | B9: 2060 | C9: 1621 | D9: 2878 | E9: 6559 | F9: 1 | G9: 627 | H9: 0.095593841
A12: SHARE BY CITY [%] — who owns what | B12: Amsterdam | C12: New York City | D12: Rio de Janeiro | E12: Bangalore
A13: BB LLC | B13: 0.16515913 | C13: 0.36880824 | D13: 0.17958656 | E13: 0.16162943
A14: SpaceBikes | B14: 0.1641541 | C14: 0.28151054 | D14: 0.15503876 | E14: 0.14980289
A15: LiteCycle | B15: 0.12227806 | C15: 0.070132418 | D15: 0.1369509 | E15: 0.48620237
A16: Spoke'd Up | B16: 0.12730318 | C16: 0.20205983 | D16: 0.041343669 | E16: 0.039421813
A17: MILC Bikes | B17: 0.15812395 | C17: 0.058852379 | D17: 0.13824289 | E17: 0.13140604
A18: WeBike | B18: 0.098827471 | C18: 0.018636587 | D18: 0.34883721 | E18: 0.031537451
A19: Bike Bros | B19: 0.1641541 | C19: 0 | D19: 0 | E19: 0
A22: INFERRED STORE LOCATIONS (from demand concentration) | B22: Firms with a store | C22: City demand | D22: Read
A23: Amsterdam | B23: ALL SEVEN | C23: 2985 | D23: Most contested city AND the largest. Nobody exceeds 16.5%.
A24: New York City | B24: BB LLC, SpaceBikes, Spoke'd Up | C24: 2039 | D24: 2nd largest. We have NO store -> only 1.9% share.
A25: Rio de Janeiro | B25: WeBike ONLY | C25: 774 | D25: Uncontested by any rival store -> we take 34.9%.
A26: Bangalore | B26: LiteCycle ONLY | C26: 761 | D26: Uncontested by others -> LiteCycle takes 48.6%.
A27: Bike Bros | B27: Amsterdam only (1 store, 0 web) | D27: Appears in NO other city. Confirms the 1-store read.
A28: CAUTION | D28: Store locations are INFERRED from demand patterns, not reported directly. MILC Bikes is Amsterdam-concentrated but its 2nd store is not identifiable.
A31: THE STORE EFFECT — what a local store is worth | B31: Share with store | C31: Share without store
A32: WeBike in Rio (only store in city) | B32: 0.349
A33: LiteCycle in Bangalore (only store in city) | B33: 0.486
A34: WeBike in Amsterdam (store, 6 rivals) | B34: 0.099
A35: WeBike in New York City (no store) | C35: 0.019
A36: WeBike in Bangalore (no store) | C36: 0.032
A37: Read | B37: A store is worth roughly 10x the share of web-only coverage (2-3% without, 10-35% with). An UNCONTESTED store is worth 35-49%. This is the highest-leverage decision we have.
A40: OUR PRIMARY SEGMENT (Mountain) BY CITY | B40: Segment size | C40: WeBike units | D40: WeBike share | E40: Leader | F40: Leader units | G40: Leader share
A41: Amsterdam | B41: 650 | C41: 156 | D41: 0.24 | E41: WeBike | F41: 156 | G41: 0.24
A42: New York City | B42: 495 | C42: 23 | D42: 0.046464646 | E42: BB LLC (both brands) | F42: 410 | G42: 0.82828283
A43: Rio de Janeiro | B43: 286 | C43: 166 | D43: 0.58041958 | E43: WeBike | F43: 166 | G43: 0.58041958
A44: Bangalore | B44: 190 | C44: 13 | D44: 0.068421053 | E44: LiteCycle | F44: 122 | G44: 0.64210526
A47: CITY #3 DECISION — New York City vs Bangalore | B47: New York City | C47: Bangalore
A48: Total city demand (Q3) | B48: 2039 | C48: 761
A49: Share of total market | B49: =B48/6559 | C49: =C48/6559
A50: Rival stores already there | B50: 3 | C50: 1
A51: Our current share (web only) | B51: 0.019 | C51: 0.032
A52: Mountain segment size | B52: 495 | C52: 190
A53: Mountain leader hold | B53: BB LLC 82.8% | C53: LiteCycle 64.2%
A54: Speed segment size | B54: 880 | C54: 386
A55: Recreation segment size (untapped) | B55: 664 | C55: 185
A56: Units at a conservative 10% share | B56: =B48*0.10 | C56: =C48*0.10
A57: Units at a Rio-like 25% share | B57: =B48*0.25 | C57: =C48*0.25
A58: VERDICT | B58: LARGER PRIZE — 2.7x the demand. Even at a weak 10% it beats Bangalore at 25%. Fits our locked 'largest geos even if expensive' strategy. | C58: SAFER but SMALLER — only LiteCycle to fight, yet the whole city is worth less than NYC's Speed segment alone.
A61: CAPACITY CHECK — can we even serve a 3rd city? | B61: Units
A62: Fixed capacity per day | B62: 24
A63: Days per quarter | B63: 65
A64: Theoretical max units | B64: =B62*B63
A65: At 74% worker productivity | B65: =B64*0.74
A66: Q4 forecast demand (existing cities, after ill will) | B66: 656
A67: Headroom for a new city | B67: =B65-B66
A68: Read | B68: We can absorb roughly 500 more units without buying a printer. A New York store at 10% (~204 units) fits comfortably. DO NOT repeat Q3 - schedule the operating capacity to match.
A71: RISKS & PROTECTIONS | B71: Note
A72: Rio is our crown jewel | B72: 58.0% of Rio Mountain and 34.9% of the city. Hike Bike's single best market (166 Mountain units, more than Amsterdam's 156). The Q3 stock-out damaged our strongest position - ill will bites hardest exactly where we lead.
A73: Amsterdam is the biggest miss | B73: 2,985 units = 45.5% of the market and we hold only 9.9%. Adding sales coverage here may be cheaper per unit than a new city, and no rival exceeds 16.5% - it is genuinely open.
A74: New York is BB LLC's fortress | B74: They take 36.9% of the city and 82.8% of its Mountain. Attack via SPEED (880 units, no single firm dominant) and Recreation, not head-on in Mountain.
A75: Bangalore is LiteCycle's fortress | B75: 48.6% city share, 64.2% of its Mountain - the most concentrated position any firm holds in any city.
A76: Do not spread too thin | B76: Bike Bros ran 5 brands from 1 store and finished last. Our constraint is supply and coverage depth, not map coverage.

Sheet Q3_Channel
A1: Demand Distribution by Channel — Q3 actual
A2: We cut web staff and spend in Q3. This is the bill: 120 web units, the lowest of any firm that operates a web centre, and 19.1% web mix against an industry average of 34.9%.
A4: Company | B4: Store demand | C4: Store % | D4: Web demand | E4: Web % | F4: Total demand | G4: Stores | H4: Demand / store | I4: Web centres | J4: Demand / web centre
A5: BB LLC | B5: 938 | C5: 0.62242867 | D5: 569 | E5: 0.37757133 | F5: 1507 | G5: 2 | H5: 469 | I5: 1 | J5: 569
A6: SpaceBikes | B6: 807 | C6: 0.62172573 | D6: 491 | E6: 0.37827427 | F6: 1298 | G6: 2 | H6: 403.5 | I6: 1 | J6: 491
A7: LiteCycle | B7: 549 | C7: 0.55792683 | D7: 435 | E7: 0.44207317 | F7: 984 | G7: 2 | H7: 274.5 | I7: 1 | J7: 435
A8: Spoke'd Up | B8: 716 | C8: 0.83840749 | D8: 138 | E8: 0.16159251 | F8: 854 | G8: 2 | H8: 358 | I8: 1 | J8: 138
A9: MILC Bikes | B9: 364 | C9: 0.45556946 | D9: 435 | E9: 0.54443054 | F9: 799 | G9: 1 | H9: 364 | I9: 1 | J9: 435
A10: WeBike | B10: 507 | C10: 0.80861244 | D10: 120 | E10: 0.19138756 | F10: 627 | G10: 2 | H10: 253.5 | I10: 1 | J10: 120
A11: Bike Bros | B11: 490 | C11: 1 | D11: 0 | E11: 0 | F11: 490 | G11: 1 | H11: 490 | I11: 0 | J11: 0
A14: OUR CHANNEL MIX vs INDUSTRY | B14: Value | C14: Note
A15: WeBike web mix [%] | B15: 0.191 | C15: we CUT web staff and spend in Q3
A16: Industry average web mix [%] (firms with a web centre) | B16: 0.34922156 | C16: MILC 54.4% - LiteCycle 44.2% - BB LLC 37.8% - SpaceBikes 37.8%
A17: Gap [pct points] | B17: =C16-C15
A18: WeBike web demand [units] | B18: 120 | C18: LOWEST of any firm operating a web centre
A19: Industry web demand range | B19: 138 - 569 | C19: Spoke'd Up 138 is the only firm near us
A20: Rank on web demand | B20: 6 of 7 | C20: only Bike Bros is lower, and it has NO web centre
A23: WHY WEB MATTERS MORE THAN WE THOUGHT | B23: Units | C23: Note
A24: Our demand from New York City (no store) | B24: 38 | C24: web only
A25: Our demand from Bangalore (no store) | B25: 24 | C25: web only
A26: Subtotal from cities where we have NO store | B26: =B24+B25
A27: Total web demand | B27: 120
A28: Share of web demand coming from non-store cities | B28: =B26/B27
A29: Store demand (Amsterdam + Rio) | B29: 507
A30: Amsterdam + Rio total demand | B30: 565 | C30: so 58 units of web demand also came from store cities
A31: CHECK | B31: =B30-B29 | C31: 58 = web demand inside store cities; 58 + 62 = 120 web total
A32: Read | C32: The web centre is HALF our reach into cities where we have no store. It is the only way to touch New York and Bangalore today, and we shrank it.
A35: THE WEB REBUILD CASE | B35: Value | C35: Note
A36: Current store demand [units] | B36: 507 | C36: hold constant
A37: Current web demand [units] | B37: 120
A38: Current total | B38: =B36+B37
A39: If web mix matched industry average (34.9%)
A40: implied total demand | B40: =B36/(1-0.3492) | C40: store demand becomes 65.1% of total
A41: implied web demand | B41: =B41-B36
A42: ADDITIONAL demand vs today | B42: =B42-B37
A43: Contribution per unit (Q3 actual, avg) | B43: 750 | C43: Hike Bike $747 / Swift Bike $756
A44: Gross margin opportunity | B44: =B43*B44
A45: Cost of ~4 additional web staff per quarter | B45: 24425 | C45: $24,425/yr each = ~$6,106/qtr x 4
A46: Net quarterly gain | B46: =B45-B46
A47: Read | C47: Web headcount is the cheapest demand in the game: no lease, no store setup, and it reaches all four cities. This is a far better first dollar than a third store.
A50: STORE PRODUCTIVITY — we under-staff what we own | B50: Demand / store | C50: Note
A51: Bike Bros | B51: 490 | C51: ONE store, highest per-store demand in the industry
A52: BB LLC | B52: 469 | C52: leader
A53: SpaceBikes | B53: 404
A54: Spoke'd Up | B54: 358
A55: LiteCycle | B55: 275
A56: WeBike | B56: 254 | C56: LOWEST of the two-store firms
A57: MILC Bikes | B57: 364 | C57: web-first model; Amsterdam store base
A58: Read | C58: BB LLC pulls 1.8x our demand from the same number of stores. Depth inside Amsterdam and Rio is unfinished business before we add a third location.
A61: CHANNEL MODELS IN THIS INDUSTRY | B61: Profile | C61: Result
A62: Web-first | B62: MILC Bikes - 54.4% web, lowest store demand (364) | C62: 12.2% share on 1 store base
A63: Balanced | B63: LiteCycle 44.2% - BB LLC 37.8% - SpaceBikes 37.8% | C63: the three strongest firms sit here
A64: Store-heavy | B64: Spoke'd Up 83.8% - WeBike 80.9% | C64: 13.0% and 9.6% share
A65: Store-only | B65: Bike Bros 100% store, no web centre | C65: 7.5% share, LAST, falling everywhere
A66: Read | C66: The top three firms all run 38-44% web. Store-only is last. We are 80.9% store-heavy and drifting toward the Bike Bros failure mode.
A69: Q4 CHANNEL ACTIONS | B69: Decision
A70: 1. Reverse the Q3 web cut | B70: Rehire web sales + support toward 6 people. Cheapest demand available: no lease, no setup, reaches all 4 cities.
A71: 2. Restart page upgrades | B71: We stopped this tactic in Q3. Toll-free stayed on. Both were cheap (~$3k and ~$6k/qtr) relative to ~$750 contribution per unit.
A72: 3. Deepen Amsterdam + Rio | B72: 254 demand/store vs BB LLC's 469. Add store sales staff before adding a third city - same money, faster payback.
A73: 4. Re-evaluate city #3 order | B73: Web already reaches New York (38 units). A store there is still the biggest prize, but web staff + store depth may be the better FIRST dollar this quarter.
A74: 5. Never cut channel again | B74: Bike Bros is the control group: 100% store, no web, last place, share falling in all three segments.

Sheet Q3_Presence
A1: Competitors in City — CONFIRMED footprints, Q3
A2: This report confirms every store location previously INFERRED from demand patterns. One correction: MILC Bikes has only ONE store (Amsterdam), not two.
A4: Location | B4: Bike Bros | C4: LiteCycle | D4: WeBike | E4: BB LLC | F4: Spoke'd Up | G4: SpaceBikes | H4: MILC Bikes | I4: Store firms present
A5: Amsterdam | B5: YES | C5: YES | D5: YES | E5: YES | F5: YES | G5: YES | H5: YES | I5: 7
A6: New York City | B6: - | C6: - | D6: - | E6: YES | F6: YES | G6: YES | H6: - | I6: 3
A7: Rio de Janeiro | B7: - | C7: - | D7: YES | E7: - | F7: - | G7: - | H7: - | I7: 1
A8: Bangalore | B8: - | C8: YES | D8: - | E8: - | F8: - | G8: - | H8: - | I8: 1
A9: Web Sales Centre | B9: - | C9: YES | D9: YES | E9: YES | F9: YES | G9: YES | H9: YES | I9: 6
A12: CONFIRMED FOOTPRINT | B12: Stores | C12: Cities | D12: Web centre | E12: Total demand
A13: BB LLC | B13: 2 | C13: Amsterdam, New York City | D13: yes | E13: 1507
A14: SpaceBikes | B14: 2 | C14: Amsterdam, New York City | D14: yes | E14: 1298
A15: LiteCycle | B15: 2 | C15: Amsterdam, Bangalore | D15: yes | E15: 984
A16: Spoke'd Up | B16: 2 | C16: Amsterdam, New York City | D16: yes | E16: 854
A17: MILC Bikes | B17: 1 | C17: Amsterdam | D17: yes | E17: 799
A18: WeBike | B18: 2 | C18: Amsterdam, Rio de Janeiro | D18: yes | E18: 627
A19: Bike Bros | B19: 1 | C19: Amsterdam | D19: NO | E19: 490
A22: MARKET STRUCTURE — a store never captures the whole city | B22: Store firms | C22: Store-firm demand | D22: Store capture % | E22: Web-only demand | F22: Web-only % | G22: Avg per store firm
A23: Amsterdam | B23: 7 | C23: 2985 | D23: 1 | E23: 0 | F23: 0 | G23: 426.42857
A24: New York City | B24: 3 | C24: 1738 | D24: 0.85237862 | E24: 301 | F24: 0.14762138 | G24: 579.33333
A25: Rio de Janeiro | B25: 1 | C25: 270 | D25: 0.34883721 | E25: 504 | F25: 0.65116279 | G25: 270
A26: Bangalore | B26: 1 | C26: 370 | D26: 0.48620237 | E26: 391 | F26: 0.51379763 | G26: 370
A29: CORRECTION — Amsterdam is the MOST contested city, not an open one | B29: Note
A30: Earlier read | B30: 'No rival exceeds 16.5%, so Amsterdam is genuinely open.'
A31: What the presence report shows | B31: ALL SEVEN firms hold an Amsterdam store. Nobody exceeds 16.5% precisely BECAUSE all seven are there.
A32: Avg demand per store firm - Amsterdam | B32: 426
A33: Avg demand per store firm - New York City | B33: 579
A34: Implication | B34: A store in New York is worth MORE than deeper investment in Amsterdam. Amsterdam is 2,985 units split 7 ways; New York is 2,039 units split 3 ways. Gaining share in Amsterdam means taking it from six store-equipped rivals.
A37: RIO — we under-exploit our monopoly | B37: WeBike in Rio | C37: LiteCycle in Bangalore
A38: Only firm with a store in the city | B38: yes | C38: yes
A39: City demand | B39: 774 | C39: 761
A40: Our / their units | B40: 270 | C40: 370
A41: Share as sole store holder | B41: 0.349 | C41: 0.486
A42: Gap | B42: =C41-B41 | C42: 13.7 pts of share we leave on the table
A43: Web-only rivals take | B43: 504 | C43: 391
A44: Web-only rivals' capture % | B44: =B43/B39 | C44: =C43/C39
A45: Read | C45: Same structural position, nearly identical city size - LiteCycle extracts 13.7 more points than we do. Rio opened only in Q3 and we stocked out, so some of this is timing. But 65% of OUR exclusive city still goes to rivals who have no store there at all.
A48: WHY THE WEB CASE IS NOW STRONGER | B48: Note
A49: Evidence | B49: BB LLC pulls 139 units out of Rio with NO store there - 51% of what we get WITH a store. SpaceBikes 120, MILC 107, LiteCycle 106. Web-only rivals took 504 of Rio's 774 units.
A50: Our mirror position | B50: We pull only 38 from New York and 24 from Bangalore by web. Rivals do 3-5x better at the same trick.
A51: Conclusion | B51: Web reach is not a consolation prize for cities we skip - it is how the strong firms raid cities they never entered. Our 19.1% web mix is costing us in all four cities, including the two where we have stores.
A54: CITY #3 — updated read | B54: New York City | C54: Bangalore
A55: City demand | B55: 2039 | C55: 761
A56: Store firms already present | B56: 3 | C56: 1
A57: Avg demand per store firm today | B57: 579 | C57: 370
A58: Weakest incumbent store firm | B58: Spoke'd Up 412 | C58: n/a
A59: Our current web-only demand there | B59: 38 | C59: 24
A60: Plausible units with a store | B60: 412 - 574 (match Spoke'd Up or SpaceBikes) | C60: ~250 (split LiteCycle's monopoly)
A61: Verdict | B61: STILL THE BEST STORE TARGET. 2.7x the demand, and only 3 rivals hold stores vs Amsterdam's 7. Enter via SPEED (880 units, no dominant firm) - BB LLC holds 82.8% of NYC Mountain. | C61: Smallest prize. LiteCycle's 48.6% monopoly is the industry's most concentrated position.
A64: Q4 SEQUENCING — reconciling depth vs breadth | B64: Decision
A65: 1st dollar: web rebuild | B65: Cheapest demand, reaches all 4 cities, pays back in-quarter (~+$89,600). Rivals prove web raids cities you never enter.
A66: 2nd dollar: Rio depth | B66: We are the ONLY store in Rio and extract just 34.9% vs LiteCycle's 48.6% in the same position. Closing that gap is ~106 units with no new lease.
A67: 3rd dollar: New York store | B67: Biggest single prize (2,039 units, only 3 store rivals). Enter through Speed once Swift Bike is fixed to 77.
A68: NOT a priority | B68: Deepening Amsterdam against 6 store-equipped rivals; opening Bangalore against LiteCycle's entrenched 48.6%.

Sheet Q3_Staffing
A1: Sales and Service People — World Market, Q3 actual
A2: Two hard findings: 7 people per city is the cap (nobody exceeds it, and Amsterdam has us AT it), and we are the only firm besides Bike Bros carrying UNTRAINED staff.
A4: City | B4: Company | C4: Total | D4: Service | E4: Recreation | F4: Mountain | G4: Speed | H4: Assigned | I4: UNTRAINED | J4: At 7-cap?
A5: New York City | B5: BB LLC | C5: 7 | D5: 1 | E5: 0 | F5: 3 | G5: 3 | H5: 7 | I5: 0 | J5: YES
A6: New York City | B6: Spoke'd Up | C6: 5 | D6: 1 | E6: 2 | F6: 0 | G6: 2 | H6: 5 | I6: 0
A7: New York City | B7: SpaceBikes | C7: 7 | D7: 2 | E7: 2 | F7: 0 | G7: 3 | H7: 7 | I7: 0 | J7: YES
A8: Rio de Janeiro | B8: WeBike | C8: 4 | D8: 1 | E8: 0 | F8: 1 | G8: 1 | H8: 3 | I8: 1
A9: Amsterdam | B9: Bike Bros | C9: 7 | D9: 2 | E9: 0 | F9: 2 | G9: 2 | H9: 6 | I9: 1 | J9: YES
A10: Amsterdam | B10: LiteCycle | C10: 5 | D10: 1 | E10: 0 | F10: 1 | G10: 3 | H10: 5 | I10: 0
A11: Amsterdam | B11: WeBike | C11: 7 | D11: 1 | E11: 0 | F11: 3 | G11: 2 | H11: 6 | I11: 1 | J11: YES
A12: Amsterdam | B12: BB LLC | C12: 7 | D12: 1 | E12: 0 | F12: 3 | G12: 3 | H12: 7 | I12: 0 | J12: YES
A13: Amsterdam | B13: Spoke'd Up | C13: 6 | D13: 1 | E13: 2 | F13: 0 | G13: 3 | H13: 6 | I13: 0
A14: Amsterdam | B14: SpaceBikes | C14: 7 | D14: 2 | E14: 2 | F14: 0 | G14: 3 | H14: 7 | I14: 0 | J14: YES
A15: Amsterdam | B15: MILC Bikes | C15: 7 | D15: 1 | E15: 3 | F15: 0 | G15: 3 | H15: 7 | I15: 0 | J15: YES
A16: Bangalore | B16: LiteCycle | C16: 5 | D16: 1 | E16: 0 | F16: 1 | G16: 3 | H16: 5 | I16: 0
A19: FIRM ROLLUP | B19: Store people | C19: Service | D19: Recreation | E19: Mountain | F19: Speed | G19: Untrained | H19: Store demand | I19: Demand / store person
A20: Bike Bros | B20: 7 | C20: 2 | D20: 0 | E20: 2 | F20: 2 | G20: 1 | H20: 490 | I20: 70
A21: BB LLC | B21: 14 | C21: 2 | D21: 0 | E21: 6 | F21: 6 | G21: 0 | H21: 938 | I21: 67
A22: Spoke'd Up | B22: 11 | C22: 2 | D22: 4 | E22: 0 | F22: 5 | G22: 0 | H22: 716 | I22: 65.090909
A23: SpaceBikes | B23: 14 | C23: 4 | D23: 4 | E23: 0 | F23: 6 | G23: 0 | H23: 807 | I23: 57.642857
A24: LiteCycle | B24: 10 | C24: 2 | D24: 0 | E24: 2 | F24: 6 | G24: 0 | H24: 549 | I24: 54.9
A25: MILC Bikes | B25: 7 | C25: 1 | D25: 3 | E25: 0 | F25: 3 | G25: 0 | H25: 364 | I25: 52
A26: WeBike | B26: 11 | C26: 2 | D26: 0 | E26: 4 | F26: 3 | G26: 2 | H26: 507 | I26: 46.090909
A29: PRODUCTIVITY GAP | B29: Value | C29: Note
A30: WeBike demand per store person | B30: 46.090909 | C30: LOWEST in the industry
A31: Industry average (excl. us) | B31: 61.105628 | C31: Bike Bros 70.0 is best; BB LLC 67.0
A32: Shortfall per person | B32: =C31-C30
A33: Our store people | B33: 11
A34: Store demand if we matched the average | B34: =C31*C33
A35: Additional units available at current headcount | B35: =C34-507 | C35: no new hires needed
A38: THE 7-PERSON CITY CAP — this settles depth vs breadth | B38: Value | C38: Note
A39: Maximum staff observed in any city (all 12 rows) | B39: 7 | C39: BB LLC, SpaceBikes, Bike Bros, MILC and our own Amsterdam all sit at 7
A40: WeBike Amsterdam headcount | B40: 7 | C40: AT THE CAP - we cannot add a single person there
A41: WeBike Rio headcount | B41: 4 | C41: 3 SLOTS OPEN - the only store depth available to us
A42: Read | C42: 'Deepen Amsterdam' is not a legal move. Amsterdam is maxed at 7. The only ways to add store selling capacity are (a) fill Rio's 3 open slots, or (b) open a new city, which unlocks 7 more.
A45: RIO vs AMSTERDAM — where a body is worth more | B45: Rio | C45: Amsterdam
A46: Store people | B46: 4 | C46: 7
A47: City demand (all channels) | B47: 270 | C47: 295
A48: Demand per person | B48: =C47/C46 | C48: =D47/D46
A49: Rival stores in city | B49: 0 | C49: 6
A50: Open slots to the 7-cap | B50: 3 | C50: 0
A51: Read | B51: A Rio head is worth ~60% more than an Amsterdam head because Rio has no rival store. Filling the 3 open Rio slots is the highest-return staffing move on the board.
A52: CAVEAT | B52: City demand includes web orders, so per-person figures are directional rather than pure store productivity. The ranking is robust; the exact multiple is not.
A55: UNTRAINED STAFF — a free win we skipped | B55: Value | C55: Note
A56: WeBike untrained people | B56: 2 | C56: 1 in Rio, 1 in Amsterdam
A57: Firms with any untrained staff | B57: WeBike (2), Bike Bros (1) | C57: the other five are 100% trained
A58: Mountain training cost | B58: 400 | C58: per quarter
A59: Speed training cost | B59: 400 | C59: per quarter
A60: Cost to train both | B60: 800 | C60: trivial against ~$750 contribution PER UNIT
A61: Read | C61: We are paying two full salaries ($24,425/yr each) for untrained sellers while every serious competitor trains everyone. Fix this first - it costs $800.
A64: SPECIALISATION vs SEGMENT RESULT | B64: Specialists | C64: Segment demand | D64: Demand per specialist
A65: MOUNTAIN
A66: LiteCycle | B66: 2 | C66: 340 | D66: =C66/B66
A67: BB LLC | B67: 6 | C67: 751 | D67: =C67/B67
A68: WeBike | B68: 4 | C68: 358 | D68: =C68/B68
A69: Bike Bros | B69: 2 | C69: 172 | D69: =C69/B69
A70: SPEED
A71: BB LLC | B71: 6 | C71: 657 | D71: =C71/B71
A72: MILC Bikes | B72: 3 | C72: 328 | D72: =C72/B72
A73: SpaceBikes | B73: 6 | C73: 588 | D73: =C73/B73
A74: LiteCycle | B74: 6 | C74: 548 | D74: =C74/B74
A75: Spoke'd Up | B75: 5 | C75: 362 | D75: =C75/B75
A76: WeBike | B76: 3 | C76: 215 | D76: =C76/B76
A77: RECREATION
A78: SpaceBikes | B78: 4 | C78: 710 | D78: =C78/B78
A79: MILC Bikes | B79: 3 | C79: 471 | D79: =C79/B79
A80: Spoke'd Up | B80: 4 | C80: 492 | D80: =C80/B80
A81: WeBike | B81: 0 | C81: 54 | D81: spillover only - no Rec specialists
A84: Q4 STAFFING PLAN | B84: Action | C84: Cost | D84: Expected units
A85: 1. Train the 2 untrained | B85: 1 Mountain (Rio) + 1 Speed (Amsterdam) | C85: 800 | D85: free productivity
A86: 2. Fill Rio to the 7-cap | B86: +3 people: 1 Mountain, 1 Speed, 1 Service | C86: ~$18,300/qtr salary + hire + train | D86: ~+200 at Rio's ~67/head
A87: 3. Rebuild web staff | B87: 3 -> 6 web sales/support | C87: ~$18,300/qtr | D87: ~+152 (see Q3_Channel)
A88: 4. Add Speed specialists | B88: we have 3 vs BB LLC/LiteCycle/SpaceBikes 6 | C88: included above | D88: Speed is our weakest segment AND the largest
A89: 5. New York store (if funded) | B89: unlocks 7 fresh slots; staff Speed-heavy | C89: setup + lease + salaries | D89: ~400-570 at incumbent rates
A90: NOT possible | B90: Adding anyone in Amsterdam - we are at the 7-person cap

Sheet Q3_Web_Ops
A1: Web Sales & Service + Web Productivity Budgets — Q3 actual
A2: Two findings: web staff is ALSO capped at 7 and we sit at 3, and there are FOUR web productivity tactics of which we fund ONE. Every firm running all four gets 435-569 web units; the two running fewer get 120-138.
A4: WEB STAFF | B4: Sales | C4: Service | D4: Total | E4: Web demand | F4: Demand / web head | G4: Slots open to 7
A5: BB LLC | B5: 5 | C5: 2 | D5: 7 | E5: 569 | F5: 81.285714 | G5: 0
A6: SpaceBikes | B6: 5 | C6: 2 | D6: 7 | E6: 491 | F6: 70.142857 | G6: 0
A7: LiteCycle | B7: 5 | C7: 2 | D7: 7 | E7: 435 | F7: 62.142857 | G7: 0
A8: MILC Bikes | B8: 6 | C8: 1 | D8: 7 | E8: 435 | F8: 62.142857 | G8: 0
A9: Spoke'd Up | B9: 2 | C9: 1 | D9: 3 | E9: 138 | F9: 46 | G9: 4
A10: WeBike | B10: 2 | C10: 1 | D10: 3 | E10: 120 | F10: 40 | G10: 4
A11: Bike Bros | B11: 0 | C11: 0 | D11: 0 | E11: 0 | F11: 0 | G11: no web centre
A14: THE WEB STAFF CAP | B14: Value | C14: Note
A15: Max web staff observed | B15: 7 | C15: LiteCycle, BB LLC, SpaceBikes and MILC all sit exactly at 7
A16: WeBike web staff | B16: 3 | C16: 2 sales + 1 service - we CUT to this in Q3
A17: Slots open | B17: 4 | C17: same 7-person ceiling as the city stores
A18: Our demand per web head | B18: 40 | C18: LOWEST of all six firms with a web centre
A19: Leader demand per web head | B19: 81.3 | C19: BB LLC
A20: Read | C20: The web centre has the same 7-person ceiling as a store, but unlike Amsterdam we are nowhere near it. Four open slots and the worst output per head is the largest single pool of unclaimed demand we have found.
A23: WEB PRODUCTIVITY BUDGETS | B23: LiteCycle | C23: WeBike | D23: BB LLC | E23: Spoke'd Up | F23: SpaceBikes | G23: MILC Bikes | H23: Average
A24: Toll-free phone advising / service calls | B24: 7000 | C24: 6000 | D24: 9000 | E24: 3000 | F24: 6000 | G24: 3000 | H24: 5667
A25: Advanced shopping cart & checkout | B25: 7000 | C25: 0 | D25: 7000 | E25: 0 | F25: 7000 | G25: 7000 | H25: 7000
A26: Continuous page upgrades (content, appeal, navigation) | B26: 7000 | C26: 0 | D26: 9000 | E26: 6000 | F26: 12000 | G26: 6000 | H26: 6667
A27: Order tracking software | B27: 8000 | C27: 0 | D27: 8000 | E27: 0 | F27: 8000 | G27: 8000 | H27: 8000
A28: TOTAL | B28: 29000 | C28: 6000 | D28: 33000 | E28: 9000 | F28: 33000 | G28: 24000 | H28: 27334
A29: Tactics funded (of 4) | B29: 4 | C29: 1 | D29: 4 | E29: 2 | F29: 4 | G29: 4
A30: Web demand | B30: 435 | C30: 120 | D30: 569 | E30: 138 | F30: 491 | G30: 435
A33: THE PATTERN IS ALMOST PERFECT | B33: Tactics funded | C33: Total budget | D33: Web demand
A34: BB LLC | B34: 4 | C34: 33000 | D34: 569
A35: SpaceBikes | B35: 4 | C35: 33000 | D35: 491
A36: LiteCycle | B36: 4 | C36: 29000 | D36: 435
A37: MILC Bikes | B37: 4 | C37: 24000 | D37: 435
A38: Spoke'd Up | B38: 2 | C38: 9000 | D38: 138
A39: WeBike | B39: 1 | C39: 6000 | D39: 120
A40: Read | D40: Every firm funding all four tactics ($24k-33k) lands at 435-569 web units. Both firms funding fewer land at 120-138. Headcount moves with budget (7 vs 3) so the two effects cannot be fully separated - but we are at the bottom of BOTH.
A43: WHAT WE NEVER STARTED | B43: Our budget | C43: Industry average | D43: Note
A44: Toll-free phone | B44: 6000 | C44: 5667 | D44: ABOVE average - our one good web decision (raised from $3k)
A45: Advanced shopping cart & checkout | B45: 0 | C45: 7000 | D45: NEVER STARTED - 4 of 6 firms fund it at $7,000
A46: Continuous page upgrades | B46: 0 | C46: 6667 | D46: WE STOPPED THIS IN Q3 - SpaceBikes funds it at $12,000
A47: Order tracking software | B47: 0 | C47: 8000 | D47: NEVER STARTED - 4 of 6 firms fund it at $8,000
A48: Our total | B48: 6000 | C48: 27500 | D48: average of the four full-tactic firms
A51: THE FULL WEB REBUILD CASE | B51: Value | C51: Note
A52: Current web demand | B52: 120 | C52: 3 staff, 1 tactic, $6,000
A53: Full-tactic cohort web demand range | B53: 435 - 569 | C53: 7 staff, 4 tactics, $24k-33k
A54: Conservative target (cohort floor) | B54: 435 | C54: LiteCycle / MILC level
A55: Additional demand | B55: =C54-C52
A56: Contribution per unit | B56: 750
A57: Gross margin opportunity | B57: =C55*C56
A58: Cost: +4 web staff per quarter | B58: 24425 | C58: 4 x $24,425/yr = ~$6,106/qtr each
A59: Cost: raise web budget $6,000 -> $28,000 | B59: 22000 | C59: add 3 tactics, top up toll-free
A60: Total incremental cost | B60: =C58+C59
A61: NET QUARTERLY GAIN | B61: =C57-C60
A62: Note | C62: This supersedes the earlier +$89,600 estimate, which only modelled matching the average web MIX. Matching the leaders' web OPERATION is worth far more.
A65: CAPACITY WARNING | B65: Units | C65: Note
A66: Store demand today | B66: 507
A67: Rio +3 staff at ~67/head | B67: 200 | C67: see Q3_Staffing
A68: Web at cohort floor | B68: 435
A69: Indicative total demand | B69: =C66+C67+C68 | C69: before ill will
A70: Max units at 24/day, 65 days, 74% productivity | B70: =24*65*0.74
A71: Required scheduled OC per day | B71: =C69/(0.74*65) | C71: units / (productivity x days)
A72: Fixed capacity per day | B72: 24
A73: Headroom | B73: =C72-C71
A74: Read | C74: Doing all of this at once pushes demand toward ~1,140 and required OC to roughly 21/day - inside our 24/day fixed capacity, but with little slack. Schedule OC to the FORECAST and re-run the production simulation before committing.

Sheet Q3_Price_Judgment
A1: Price Judgment — World Market, Q3 actual
A2: 100 = no price resistance. Lower = buyers find the price high. Because the score depends only on price vs segment willingness-to-pay, identical triplets imply identical prices - which lets us rank every rival's price without seeing the price list.
A4: Brand | B4: Company | C4: Recreation | D4: Mountain | E4: Speed | F4: Targets | G4: Price judgment in target | H4: Resistance?
A5: MACH I.I | B5: Bike Bros | C5: 63 | D5: 78 | E5: 90 | F5: Speed | G5: 90 | H5: -10
A6: TERRAMAX | B6: Bike Bros | C6: 73 | D6: 91 | E6: 100 | F6: Mountain | G6: 91 | H6: -9
A7: Mach 0.6 | B7: Bike Bros | C7: 70 | D7: 86 | E7: 100 | F7: Speed | G7: 100 | H7: none
A8: TERRAMean | B8: Bike Bros | C8: 82 | D8: 100 | E8: 100 | F8: Mountain | G8: 100 | H8: none
A9: MountainCruise1 | B9: Bike Bros | C9: 92 | D9: 100 | E9: 100 | F9: Recreation | G9: 92 | H9: -8
A10: LiteSpeed Pro+ | B10: LiteCycle | C10: 73 | D10: 90 | E10: 100 | F10: Speed | G10: 100 | H10: none
A11: LiteSpeed+ | B11: LiteCycle | C11: 83 | D11: 100 | E11: 100 | F11: Speed | G11: 100 | H11: none
A12: LiteTrail Pro | B12: LiteCycle | C12: 85 | D12: 100 | E12: 100 | F12: Mountain | G12: 100 | H12: none
A13: Hike Bike | B13: WeBike | C13: 81 | D13: 100 | E13: 100 | F13: Mountain | G13: 100 | H13: none
A14: Swift Bike | B14: WeBike | C14: 76 | D14: 94 | E14: 100 | F14: Speed | G14: 100 | H14: none
A15: Blu Ruged Ballz | B15: BB LLC | C15: 81 | D15: 100 | E15: 100 | F15: Mountain | G15: 100 | H15: none
A16: Blu Aero Ballz | B16: BB LLC | C16: 70 | D16: 86 | E16: 100 | F16: Speed | G16: 100 | H16: none
... A24: Skim MILC MKII | B24: MILC Bikes | C24: 76 | D24: 94 | E24: 100 | F24: Speed | G24: 100 | H24: none
A27: INFERRED PRICE TIERS (cheapest first) | B27: Rec | C27: Mountain | D27: Speed | E27: Brands at this price
A28: tier 100 | B28: 100 | C28: 100 | D28: 100 | E28: Spoke'd Easy (Spoke'd Up), Mars Rover (SpaceBikes), Whole MILC MKII (MILC Bikes)
A29: tier 92 | B29: 92 | C29: 100 | D29: 100 | E29: MountainCruise1 (Bike Bros)
A30: tier 85 | B30: 85 | C30: 100 | D30: 100 | E30: LiteTrail Pro (LiteCycle)
A31: tier 83 | B31: 83 | C31: 100 | D31: 100 | E31: LiteSpeed+ (LiteCycle)
A32: tier 82 | B32: 82 | C32: 100 | D32: 100 | E32: TERRAMean (Bike Bros)
A33: tier 81 | B33: 81 | C33: 100 | D33: 100 | E33: Hike Bike (WeBike), Blu Ruged Ballz (BB LLC), Blu Tail Ballz (BB LLC)
A34: tier 76 | B34: 76 | C34: 94 | D34: 100 | E34: Swift Bike (WeBike), Skim MILC MKII (MILC Bikes)
A35: tier 73 | B35: 73 | C35: 91 | D35: 100 | E35: TERRAMAX (Bike Bros), Spoke'd Speed (Spoke'd Up)
A36: tier 73 | B36: 73 | C36: 90 | D36: 100 | E36: LiteSpeed Pro+ (LiteCycle)
A37: tier 70 | B37: 70 | C37: 86 | D37: 100 | E37: Mach 0.6 (Bike Bros), Blu Aero Ballz (BB LLC), Blu Tube Ballz (BB LLC), The Armstrong (SpaceBikes)
A38: tier 63 | B38: 63 | C38: 78 | D38: 90 | E38: MACH I.I (Bike Bros)
A41: SEGMENT PRICE SENSITIVITY — resistance sets in at different tiers | B41: Mountain | C41: Speed | D41: Recreation
A42: tier 100 (cheapest) | B42: 100 | C42: 100 | D42: 100
A43: tier 92 | B43: 100 | C43: 100 | D43: 92
A44: tier 85 | B44: 100 | C44: 100 | D44: 85
A45: tier 83 | B45: 100 | C45: 100 | D45: 83
A46: tier 82 | B46: 100 | C46: 100 | D46: 82
A47: tier 81 <- Hike Bike | B47: 100 | C47: 100 | D47: 81
A48: tier 76 <- Swift Bike | B48: 94 | C48: 100 | D48: 76
A49: tier 73 | B49: 91 | C49: 100 | D49: 73
A50: tier 70 | B50: 86 | C50: 100 | D50: 70
A51: tier 63 (most expensive) | B51: 78 | C51: 90 | D51: 63
A52: Read | D52: SPEED is the least price-sensitive segment in the game - it tolerates every price up to tier 70 with zero resistance. MOUNTAIN starts resisting immediately below tier 81. RECREATION resists almost everything.
A55: HIKE BIKE — price is already optimal, hold it | B55: Value | C55: Note
A56: Price | B56: 1365
A57: Mountain price judgment | B57: 100 | C57: ZERO price resistance
A58: Price tier | B58: 81 | C58: the HIGHEST-priced tier that still scores 100 in Mountain
A59: Next tier up (73) | B59: 91 | C59: TERRAMAX sits there and takes a 9-point hit
A60: Verdict | C60: We are extracting the maximum price Mountain will bear without penalty. Raising it drops us into the resistance band. HOLD $1,365.
A63: SWIFT BIKE — we are UNDER-priced in Speed | B63: Value | C63: Note
A64: Price | B64: 1450
A65: Speed price judgment | B65: 100 | C65: zero resistance
A66: Our price tier | B66: 76
A67: Tier 70 brands (Armstrong, Blu Tube, Blu Aero, Mach 0.6) | B67: 100 | C67: priced ABOVE us and STILL score 100 in Speed
A68: First tier with Speed resistance | B68: 63 | C68: only MACH I.I, at 90
A69: Headroom | C69: roughly 1-2 price tiers before Speed resistance appears
A70: Estimated tier-70 price | B70: 1595 | C70: INFERRED - see the estimate note below
A71: Potential price increase | B71: =C70-C64
A72: On Q3 volume (215 units) | B72: =C71*215 | C72: pure margin - no cost change
A73: On a rebuilt Speed volume (say 400 units) | B73: =C71*400
A74: CAVEAT | C74: The $1,595 figure is inferred from BB LLC's ~$1,480 average price across 4 brands, two of which appear to sit at our $1,365 tier. VERIFY against the actual price list before locking. The DIRECTION (we have room to raise) is solid; the exact number is not.
A77: THE BB LLC COMPARISON IS NOW AIRTIGHT | B77: Hike Bike (WeBike) | C77: Blu Ruged Ballz (BB LLC)
A78: Brand judgment - Mountain | B78: 73 | C78: 73
A79: Component recipe | B79: 56/73/1 | C79: 56/73/1 (identical)
A80: Price judgment | B80: 81 / 100 / 100 | C80: 81 / 100 / 100 (identical)
A81: Implied price | B81: $1,365 | C81: $1,365 (same tier)
A82: Mountain share | B82: 0.221 | C82: 0.463
A83: Conclusion | C83: Same product, same price, same price perception - and they take 2.1x our share. There is now no product or pricing explanation left. The entire gap is SUPPLY (we stocked out 33%), COVERAGE (14 store staff vs 14 but 7 web vs our 3) and ADS (24 regional vs our 19).
A86: ANOTHER REASON TO SKIP RECREATION | B86: Value | C86: Note
A87: Hike Bike Recreation price judgment | B87: 81 | C87: Rec buyers resist our $1,365
A88: All three Recreation brands | B88: 100 | C88: Spoke'd Easy, Mars Rover, Whole MILC - all at tier 100
A89: Read | C89: Recreation is the most price-sensitive segment AND the winning brands are the cheapest in the game. Entering would mean a low-price, low-margin product - the opposite of our 'profit margin leader' strategy. Combined with the 56-vs-76 brand judgment gap, Recreation stays parked.
A92: Q4 PRICING ACTIONS | B92: Decision
A93: Hike Bike | B93: HOLD $1,365. Mountain judgment 100 and we sit at the top tier that achieves it.
A94: Swift Bike | B94: RAISE. Speed tolerates 1-2 tiers above us with zero resistance. Verify the exact price list, then move toward the Armstrong / Blu Tube tier.
A95: Sequencing note | B95: Raise the Swift Bike price in the SAME quarter we fix its design to 77 - better product plus a price the segment does not resist is the cleanest margin gain available.
A96: Capacity note | B96: A price rise also RELIEVES the capacity squeeze: more margin per unit on the same 24/day. If we cannot build 1,171 units, we should at least earn more on the ones we do build.

Sheet Q3_Prices
A1: Competitors' Prices — World Market, Q3 actual
A2: Actual price list. It confirms the price tiers inferred from price judgment: every tier maps to a distinct price, monotonically, across all 11 tiers.
A4: Brand | B4: Company | C4: Price | D4: Rebate | E4: Net price | F4: Priority | G4: Segment | H4: Brand judgment | I4: Price judgment | J4: Price tier
A5: MACH I.I | B5: Bike Bros | C5: 1749 | D5: 0 | E5: 1749 | F5: 1 | G5: Speed | H5: 77 | I5: 90 | J5: 63
A6: Blu Aero Ballz | B6: BB LLC | C6: 1580 | D6: 0 | E6: 1580 | F6: 2 | G6: Speed | H6: 74 | I6: 100 | J6: 70
A7: Blu Tube Ballz | B7: BB LLC | C7: 1580 | D7: 0 | E7: 1580 | F7: 3 | G7: Speed | H7: 76 | I7: 100 | J7: 70
A8: The Armstrong | B8: SpaceBikes | C8: 1580 | D8: 0 | E8: 1580 | F8: 1 | G8: Speed | H8: 76 | I8: 100 | J8: 70
A9: Mach 0.6 | B9: Bike Bros | C9: 1579 | D9: 0 | E9: 1579 | F9: 3 | G9: Speed | H9: 61 | I9: 100 | J9: 70
A10: LiteSpeed Pro+ | B10: LiteCycle | C10: 1515 | D10: 0 | E10: 1515 | F10: 1 | G10: Speed | H10: 77 | I10: 100 | J10: 73
A11: TERRAMAX | B11: Bike Bros | C11: 1499 | D11: 0 | E11: 1499 | F11: 2 | G11: Mountain | H11: 73 | I11: 91 | J11: 73
A12: Spoke'd Speed | B12: Spoke'd Up | C12: 1499 | D12: 0 | E12: 1499 | F12: 2 | G12: Speed | H12: 75 | I12: 100 | J12: 73
A13: Swift Bike | B13: WeBike | C13: 1450 | D13: 0 | E13: 1450 | F13: 2 | G13: Speed | H13: 72 | I13: 100 | J13: 76
A14: Skim MILC MKII | B14: MILC Bikes | C14: 1450 | D14: 0 | E14: 1450 | F14: 2 | G14: Speed | H14: 76 | I14: 100 | J14: 76
A15: Hike Bike | B15: WeBike | C15: 1365 | D15: 0 | E15: 1365 | F15: 1 | G15: Mountain | H15: 73 | I15: 100 | J15: 81
A16: Blu Ruged Ballz | B16: BB LLC | C16: 1365 | D16: 0 | E16: 1365 | F16: 1 | G16: Mountain | H16: 73 | I16: 100 | J16: 81
... A24: Whole MILC MKII | B24: MILC Bikes | C24: 1050 | D24: 100 | E24: 950 | F24: 1 | G24: Recreation | H24: 74 | I24: 100 | J24: 100
A27: TIER VALIDATION — inferred tier vs actual net price | B27: Net price range | C27: Spread | D27: Brands
A28: tier 100 | B28: 950 - 1,050 | C28: 100 | D28: Spoke'd Easy, Mars Rover, Whole MILC MKII
A29: tier 92 | B29: 1,199 - 1,199 | C29: 0 | D29: MountainCruise1
A30: tier 85 | B30: 1,300 - 1,300 | C30: 0 | D30: LiteTrail Pro
A31: tier 83 | B31: 1,325 - 1,325 | C31: 0 | D31: LiteSpeed+
A32: tier 82 | B32: 1,349 - 1,349 | C32: 0 | D32: TERRAMean
A33: tier 81 | B33: 1,365 - 1,365 | C33: 0 | D33: Hike Bike, Blu Ruged Ballz, Blu Tail Ballz
A34: tier 76 | B34: 1,450 - 1,450 | C34: 0 | D34: Swift Bike, Skim MILC MKII
A35: tier 73 | B35: 1,499 - 1,515 | C35: 16 | D35: TERRAMAX, LiteSpeed Pro+, Spoke'd Speed
A36: tier 70 | B36: 1,579 - 1,580 | C36: 1 | D36: Mach 0.6, Blu Aero Ballz, Blu Tube Ballz, The Armstrong
A37: tier 63 | B37: 1,749 - 1,749 | C37: 0 | D37: MACH I.I
A38: Result | D38: Perfectly monotonic. Identical price judgment DID mean identical price in every case. Our earlier $1,595 estimate for tier 70 came in at $1,580 - off by $15 (0.9%).
A41: SPEED PRICE LADDER — we are nearly the cheapest | B41: Price | C41: Brand judgment | D41: Price judgment | E41: Note
A42: MACH I.I | B42: 1749 | C42: 77 | D42: 90 | E42: only Speed brand with price resistance
A43: Blu Aero Ballz | B43: 1580 | C43: 74 | D43: 100 | E43: highest price with ZERO resistance
A44: Blu Tube Ballz | B44: 1580 | C44: 76 | D44: 100 | E44: highest price with ZERO resistance
A45: The Armstrong | B45: 1580 | C45: 76 | D45: 100 | E45: highest price with ZERO resistance
A46: Mach 0.6 | B46: 1579 | C46: 61 | D46: 100
A47: LiteSpeed Pro+ | B47: 1515 | C47: 77 | D47: 100
A48: Spoke'd Speed | B48: 1499 | C48: 75 | D48: 100
A49: Swift Bike | B49: 1450 | C49: 72 | D49: 100 | E49: OURS - 2nd cheapest, 2nd worst product
A50: Skim MILC MKII | B50: 1450 | C50: 76 | D50: 100
A51: LiteSpeed+ | B51: 1325 | C51: 74 | D51: 100
A54: SWIFT BIKE PRICE MOVE — now precise | B54: Value | C54: Note
A55: Current price | B55: 1450 | C55: 2nd cheapest of 10 Speed brands
A56: Speed median price | B56: 1547 | C56: we sit $97 below the median
A57: Highest price with ZERO Speed resistance | B57: 1580 | C57: Mach 0.6, Blu Aero, Blu Tube, The Armstrong
A58: First price WITH resistance | B58: 1749 | C58: MACH I.I, judgment 90
A59: Safe increase | B59: =C57-C55 | C59: proven safe by four rival brands
A60: On Q3 volume (215 units) | B60: =C59*215 | C60: pure margin, no cost change
A61: On a rebuilt Speed volume (400 units) | B61: =C59*400
A62: Untested zone | B62: 1,581 - 1,748 | C62: nobody prices here, so resistance onset is unknown. $1,580 is the evidence-backed target.
A65: HIKE BIKE — confirmed at the Mountain ceiling | B65: Price | C65: Mountain price judgment
A66: LiteTrail Pro | B66: 1300 | C66: 100
A67: LiteSpeed+ (Speed brand) | B67: 1325 | C67: 100
A68: TERRAMean | B68: 1349 | C68: 100
A69: Hike Bike / Blu Ruged Ballz / Blu Tail Ballz | B69: 1365 | C69: 100
A70: Swift Bike / Skim MILC (tier above) | B70: 1450 | C70: 94
A71: TERRAMAX | B71: 1499 | C71: 91
A72: Read | C72: Mountain resistance begins somewhere between $1,365 and $1,450. We sit at the top of the clean band. HOLD $1,365 - the $85 of untested space is not worth risking a judgment drop.
A75: CONTRIBUTION PER UNIT — matters now that capacity binds | B75: Price | C75: Q3 unit cost | D75: Contribution
A76: Hike Bike | B76: 1365 | C76: 618 | D76: =B76-C76
A77: Swift Bike (today) | B77: 1450 | C77: 694 | D77: =B77-C77
A78: Swift Bike at $1,580 | B78: 1580 | C78: 694 | D78: =B78-C78
A79: Swift Bike at $1,580 with 14-speed gears | B79: 1580 | C79: lower | D79: higher still
A80: Read | D80: At $1,580 Swift Bike becomes our MOST profitable unit ($886 vs Hike Bike's $747). Switching it to 14-speed (the design fix) should cut its cost too, widening the gap further.
A83: PRIORITY FIELD — a lever we have not thought about | B83: Value | C83: Note
A84: Our priority order | B84: 1 Hike Bike, 2 Swift Bike
A85: Q3 stock-out by brand | B85: Hike Bike 134/412 = 32.5% | C85: Swift Bike 70/215 = 32.6%
A86: Observation | C86: Both brands lost almost exactly the same percentage, so priority 1 did NOT shield Hike Bike in Q3. Treat the mechanism as unverified.
A87: Why it matters in Q4 | C87: Capacity is now binding (see Q4_Planner). If we cannot build all demand, the priority order decides the mix. After the price rise, Swift Bike earns $886/unit vs Hike Bike's $747 - so a pure margin view argues for promoting Swift Bike.
A88: Counter-argument | C88: Mountain is our PRIMARY segment for the Balanced Scorecard's Market Performance, and we hold 22.1% there vs 7.5% in Speed. Starving Hike Bike would hurt the scorecard even if it helps the income statement. Decide deliberately - do not leave it on default.
A89: Rebates | B89: we use 0 | C89: Only the two Recreation leaders rebate: Mars Rover $50, Whole MILC $100. Rebates appear to be a Recreation/price-sensitive tool - no reason for us to start.
A92: HOW RIVALS PRICE BY SEGMENT — the pattern to copy | B92: Mountain | C92: Speed | D92: Recreation
A93: BB LLC | B93: $1,365 | C93: $1,580 | D93: n/a
A94: SpaceBikes | B94: n/a | C94: $1,580 | D94: $1,050 net
A95: MILC Bikes | B95: n/a | C95: $1,450 | D95: $950 net
A96: LiteCycle | B96: $1,300 | C96: $1,325 - $1,515 | D96: n/a
A97: Bike Bros | B97: $1,349 - $1,499 | C97: $1,579 - $1,749 | D97: $1,199
A98: Spoke'd Up | B98: n/a | C98: $1,499 | D98: $999
A99: WeBike | B99: $1,365 | C99: $1,450 | D99: n/a
A100: Read | D100: The strong firms price Speed $200+ above Mountain and Recreation far below. BB LLC is the cleanest example: identical Mountain price to ours, Speed $215 higher. We copied their Mountain price correctly and missed their Speed price entirely.

Sheet Q3_City_Profiles
A1: Competitors' Profiles by city — Q3 actual (measured store vs web)
A2: Source: Detailed report for city, all four cities. Totals reconcile to 6,559. WeBike 627 / 507 store / 120 web. Firm store+web vs Q3_Channel is ±1 rounding; city figures are the ground truth. Bike Bros is N/A outside Amsterdam.
A4: Company | B4: City | C4: Total | D4: Store | E4: Web | F4: Brands | G4: Avg price | H4: Inserts | I4: Store people | J4: Demand / store person | K4: Web people | L4: Demand / web person
A5: LiteCycle | B5: New York City | C5: 143 | D5: 0 | E5: 143 | F5: 3 | G5: 1380 | H5: 12 | K5: 7 | L5: 20
A6: WeBike | B6: New York City | C6: 38 | D6: 0 | E6: 38 | F6: 2 | G6: 1408 | H6: 19 | K6: 3 | L6: 13
A7: BB LLC | B7: New York City | C7: 752 | D7: 567 | E7: 185 | F7: 4 | G7: 1473 | H7: 24 | I7: 7 | J7: 81 | K7: 7 | L7: 26
A8: Spoke'd Up | B8: New York City | C8: 412 | D8: 371 | E8: 41 | F8: 2 | G8: 1249 | H8: 12 | I8: 5 | J8: 74 | K8: 3 | L8: 14
A9: SpaceBikes | B9: New York City | C9: 574 | D9: 435 | E9: 139 | F9: 2 | G9: 1340 | H9: 17 | I9: 7 | J9: 62 | K9: 7 | L9: 20
A10: MILC Bikes | B10: New York City | C10: 120 | D10: 0 | E10: 120 | F10: 2 | G10: 1250 | H10: 12 | K10: 7 | L10: 17
A11: LiteCycle | B11: Rio de Janeiro | C11: 106 | D11: 0 | E11: 106 | F11: 3 | G11: 1380 | H11: 12 | K11: 7 | L11: 15
A12: WeBike | B12: Rio de Janeiro | C12: 270 | D12: 240 | E12: 30 | F12: 2 | G12: 1408 | H12: 19 | I12: 4 | J12: 60 | K12: 3 | L12: 10
A13: BB LLC | B13: Rio de Janeiro | C13: 139 | D13: 0 | E13: 139 | F13: 4 | G13: 1473 | H13: 24 | K13: 7 | L13: 20
A14: Spoke'd Up | B14: Rio de Janeiro | C14: 32 | D14: 0 | E14: 32 | F14: 2 | G14: 1249 | H14: 12 | K14: 3 | L14: 11
A15: SpaceBikes | B15: Rio de Janeiro | C15: 120 | D15: 0 | E15: 120 | F15: 2 | G15: 1340 | H15: 17 | K15: 7 | L15: 17
A16: MILC Bikes | B16: Rio de Janeiro | C16: 107 | D16: 0 | E16: 107 | F16: 2 | G16: 1250 | H16: 12 | K16: 7 | L16: 15
A17: Bike Bros | B17: Amsterdam | C17: 490 | D17: 490 | E17: 0 | F17: 5 | G17: 1475 | H17: 10 | I17: 7 | J17: 70
A18: LiteCycle | B18: Amsterdam | C18: 365 | D18: 272 | E18: 93 | F18: 3 | G18: 1380 | H18: 12 | I18: 5 | J18: 54 | K18: 7 | L18: 13
A19: WeBike | B19: Amsterdam | C19: 295 | D19: 267 | E19: 28 | F19: 2 | G19: 1408 | H19: 19 | I19: 7 | J19: 38 | K19: 3 | L19: 9
A20: BB LLC | B20: Amsterdam | C20: 493 | D20: 372 | E20: 121 | F20: 4 | G20: 1473 | H20: 24 | I20: 7 | J20: 53 | K20: 7 | L20: 17
A21: Spoke'd Up | B21: Amsterdam | C21: 380 | D21: 344 | E21: 36 | F21: 2 | G21: 1249 | H21: 12 | I21: 6 | J21: 57 | K21: 3 | L21: 12
A22: SpaceBikes | B22: Amsterdam | C22: 490 | D22: 371 | E22: 119 | F22: 2 | G22: 1340 | H22: 17 | I22: 7 | J22: 53 | K22: 7 | L22: 17
A23: MILC Bikes | B23: Amsterdam | C23: 472 | D23: 365 | E23: 107 | F23: 2 | G23: 1250 | H23: 12 | I23: 7 | J23: 52 | K23: 7 | L23: 15
A24: LiteCycle | B24: Bangalore | C24: 370 | D24: 277 | E24: 93 | F24: 3 | G24: 1380 | H24: 12 | I24: 5 | J24: 55 | K24: 7 | L24: 13
A25: WeBike | B25: Bangalore | C25: 24 | D25: 0 | E25: 24 | F25: 2 | G25: 1408 | H25: 19 | K25: 3 | L25: 8
A26: BB LLC | B26: Bangalore | C26: 123 | D26: 0 | E26: 123 | F26: 4 | G26: 1473 | H26: 24 | K26: 7 | L26: 18
A27: Spoke'd Up | B27: Bangalore | C27: 30 | D27: 0 | E27: 30 | F27: 2 | G27: 1249 | H27: 12 | K27: 3 | L27: 10
A28: SpaceBikes | B28: Bangalore | C28: 114 | D28: 0 | E28: 114 | F28: 2 | G28: 1340 | H28: 17 | K28: 7 | L28: 16
A29: MILC Bikes | B29: Bangalore | C29: 100 | D29: 0 | E29: 100 | F29: 2 | G29: 1250 | H29: 12 | K29: 7 | L29: 14
A32: CITY CHANNEL MIX (measured) | B32: Total | C32: Store units | D32: Store % | E32: Web units | F32: Web % | G32: Store firms | H32: Store people in city
A33: Amsterdam | B33: 2985 | C33: 2481 | D33: 0.83115578 | E33: 504 | F33: 0.16884422 | G33: 7 | H33: 46
A34: New York City | B34: 2039 | C34: 1373 | D34: 0.6733693 | E34: 666 | F34: 0.3266307 | G34: 3 | H34: 19
A35: Rio de Janeiro | B35: 774 | C35: 240 | D35: 0.31007752 | E35: 534 | F35: 0.68992248 | G35: 1 | H35: 4
A36: Bangalore | B36: 761 | C36: 277 | D36: 0.36399474 | E36: 484 | F36: 0.63600526 | G36: 1 | H36: 5
A39: STORE PRODUCTIVITY (pure store units / store person) | B39: City | C39: Store units | D39: People | E39: Per person | F39: Note
A40: BB LLC | B40: New York City | C40: 567 | D40: 7 | E40: 81 | F40: NYC ceiling analog (Mountain + Speed, 7 people)
A41: Spoke'd Up | B41: New York City | C41: 371 | D41: 5 | E41: 74 | F41: 5 people, NO Mountain brand — NYC floor analog
A42: Bike Bros | B42: Amsterdam | C42: 490 | D42: 7 | E42: 70
A43: SpaceBikes | B43: New York City | C43: 435 | D43: 7 | E43: 62
A44: WeBike | B44: Rio de Janeiro | C44: 240 | D44: 4 | E44: 60 | F44: Already 1.6x our Amsterdam rate; 3 slots open
A45: Spoke'd Up | B45: Amsterdam | C45: 344 | D45: 6 | E45: 57
A46: LiteCycle | B46: Bangalore | C46: 277 | D46: 5 | E46: 55
A47: LiteCycle | B47: Amsterdam | C47: 272 | D47: 5 | E47: 54
A48: BB LLC | B48: Amsterdam | C48: 372 | D48: 7 | E48: 53
A49: SpaceBikes | B49: Amsterdam | C49: 371 | D49: 7 | E49: 53
A50: MILC Bikes | B50: Amsterdam | C50: 365 | D50: 7 | E50: 52
A51: WeBike | B51: Amsterdam | C51: 267 | D51: 7 | E51: 38 | F51: LAST in our home city
A54: NYC STORE PRIZE — retire the 10% = 204 estimate | B54: People | C54: Store units | D54: Web units | E54: Total | F54: Per store person | G54: Read
A55: BB LLC (has store) | B55: 7 | C55: 567 | D55: 185 | E55: 752 | F55: 81 | G55: Mountain + Speed, 4 brands, 24 inserts
A56: SpaceBikes (has store) | B56: 7 | C56: 435 | D56: 139 | E56: 574 | F56: 62 | G56: Recreation + Speed, worst NYC store rate
A57: Spoke'd Up (has store) | B57: 5 | C57: 371 | D57: 41 | E57: 412 | F57: 74 | G57: Rec + Speed, NO Mountain, only 5 people
A58: LiteCycle (web only) | C58: 0 | D58: 143 | E58: 143 | G58: Full web op, no store — web-only ceiling
A59: MILC Bikes (web only) | C59: 0 | D59: 120 | E59: 120 | G59: Web-first firm
A60: WeBike (web only) | C60: 0 | D60: 38 | E60: 38 | G60: Last among web-only firms
A61: NYC physical store total | B61: 19 | C61: 1373 | D61: 365 | E61: 1738 | F61: 72 | G61: 67.3% of city is store; 85.2% is store-firm (store+their web)
A62: If we open as 4th store, floor | B62: 7 | C62: 371 | F62: 53 | G62: Match Spoke'd Up's STORE units (they have 5 people and no Mountain).
A63: If we staff 7 at SpaceBikes rate | B63: 7 | C63: 434 | F63: 62 | G63: Worst incumbent NYC rate × our likely 7-cap staff.
A64: If 4th store splits today's 1,373 | B64: 7 | C64: 343 | F64: 49 | G64: Conservative: store pool unchanged, split 4 ways instead of 3.
A65: VERDICT | G65: The 10% = 204 figure is retired. A NYC store is a 340–570 unit prize, not a 204 unit prize. Enter via Speed (Spoke'd Up's Speed ad is <70). Stacked on Rio-fill + web rebuild this needs printers — see Q4_Planner scenario E.
A68: AMSTERDAM — we are last in our own city | B68: Store units | C68: People | D68: Per person | E68: Web units | F68: Total
A69: Bike Bros | B69: 490 | C69: 7 | D69: 70 | E69: 0 | F69: 490
A70: Spoke'd Up | B70: 344 | C70: 6 | D70: 57 | E70: 36 | F70: 380
A71: LiteCycle | B71: 272 | C71: 5 | D71: 54 | E71: 93 | F71: 365
A72: BB LLC | B72: 372 | C72: 7 | D72: 53 | E72: 121 | F72: 493
A73: SpaceBikes | B73: 371 | C73: 7 | D73: 53 | E73: 119 | F73: 490
A74: MILC Bikes | B74: 365 | C74: 7 | D74: 52 | E74: 107 | F74: 472
A75: WeBike | B75: 267 | C75: 7 | D75: 38 | E75: 28 | F75: 295
A76: Industry excl. us | B76: 2214 | C76: 39 | D76: 57 | E76: 476 | F76: 2690
A77: Read | F77: Same 7 people, same city: Bike Bros 70 vs WeBike 38. We cannot add a head (at cap). Closing the gap is training, filling stock-outs, and the Swift Bike fix — not hiring. Matching industry 57/head would be ~399 store units (+132) with the people we already have.
A80: SOLE-STORE CITIES — store vs web split | B80: WeBike in Rio | C80: LiteCycle in Bangalore
A81: City demand | B81: 774 | C81: 761
A82: Physical store units | B82: 240 | C82: 277
A83: Store people | B83: 4 | C83: 5
A84: Store units per person | B84: 60 | C84: 55
A85: Own web in the city | B85: 30 | C85: 93
A86: Total as sole store holder | B86: 270 | C86: 370
A87: Share of city | B87: 0.349 | C87: 0.486
A88: Rivals' web (no store) | B88: 504 | C88: 391
A89: Open store slots | B89: 3 | C89: 2
A90: Fill to 7 at current store rate | B90: 420 | C90: 385
A91: Read | B91: Filling 3 Rio slots at 60/head = +180 store units, no new lease. Our 30 web in our own city is 1/3 of LiteCycle's 93 in theirs — another web-rebuild tell. BB LLC takes 139 Rio units with no store. | C91: LiteCycle extracts more with 5 people than we do with 4, and still has 2 slots open. Their city web (93) is 3x ours in Rio (30).
A94: WEB RAID BY CITY (web units, one shared web centre) | B94: Amsterdam | C94: New York City | D94: Rio de Janeiro | E94: Bangalore | F94: Total | G94: Web people | H94: Per head
A95: BB LLC | B95: 121 | C95: 185 | D95: 139 | E95: 123 | F95: 568 | G95: 7 | H95: 81.1
A96: SpaceBikes | B96: 119 | C96: 139 | D96: 120 | E96: 114 | F96: 492 | G96: 7 | H96: 70.3
A97: LiteCycle | B97: 93 | C97: 143 | D97: 106 | E97: 93 | F97: 435 | G97: 7 | H97: 62.1
A98: MILC Bikes | B98: 107 | C98: 120 | D98: 107 | E98: 100 | F98: 434 | G98: 7 | H98: 62
A99: Spoke'd Up | B99: 36 | C99: 41 | D99: 32 | E99: 30 | F99: 139 | G99: 3 | H99: 46.3
A100: WeBike | B100: 28 | C100: 38 | D100: 30 | E100: 24 | F100: 120 | G100: 3 | H100: 40
A103: WHAT THE WEB RAID SHOWS | B103: Note
A104: BB LLC is even across all 4 cities | B104: Amsterdam 121 · NYC 185 · Rio 139 · Bangalore 123. They raid cities they never entered at the same scale they sell online in cities they own.
A105: We are even and tiny | B105: Amsterdam 28 · NYC 38 · Rio 30 · Bangalore 24. Same shape, ~1/5 the scale.
A106: Even in Amsterdam, where we have a store | B106: BB LLC 121 web vs our 28. Store presence does not automatically produce web demand — the web operation does.
A107: LiteCycle with no NYC store beats our NYC web 3.8x | B107: 143 vs 38. That is the web-only NYC benchmark once we staff 7 and fund all 4 tactics.
A108: Spoke'd Up is our twin | B108: Web staff 3, web total 139 vs our 120. Same failure mode. They still out-produce us in NYC store (371 with 5 people) because they showed up.
A111: COMPANY BRAND / AD SCORES (repeated identically in every city report) | B111: Rec brand | C111: Mtn brand | D111: Speed brand | E111: Rec ad | F111: Mtn ad | G111: Speed ad | H111: Inserts
A112: Bike Bros | B112: 76 MountainCruise1 | C112: 73 TERRAMAX | D112: 77 MACH I.I | E112: 75 Easy Rider | F112: 78 TerraTech | G112: 78 AndStill | H112: 10
A113: LiteCycle | B113: — | C113: 70 LiteTrail Pro | D113: 77 LiteSpeed Pro+ | E113: — | F113: 79 Trail Blazing 1 | G113: 77 Speed of Lite 1 | H113: 12
A114: WeBike | B114: — | C114: 73 Hike Bike | D114: 72 Swift Bike | E114: — | F114: 80 HikeBike 1 | G114: 70 Swift Bike | H114: 19
A115: BB LLC | B115: — | C115: 73 Blu Ruged Ballz | D115: 76 Blu Tube Ballz | E115: — | F115: 81 BB Big Momma | G115: 76 Unleash lil pap | H115: 24
A116: Spoke'd Up | B116: 73 Spoke'd Easy | C116: — | D116: 75 Spoke'd Speed | E116: — | F116: — | G116: — | H116: 12
A117: SpaceBikes | B117: 73 Mars Rover | C117: — | D117: 76 The Armstrong | E117: 79 Mars Rover 1 | F117: — | G117: 77 The Armstrong 1 | H117: 17
...

Sheet Q3_Organic_SEM
A1: Organic SEM Results — Q3 actual
A2: WeBike 144 clicks vs BB LLC 437. HikeBike 1 is #2 in Mountain (115 clicks, ad 80). Swift Bike is #5 in Speed (29 clicks, ad 70) with Rec/price copy. Organic is NOT why web sales are last: LiteCycle has 153 clicks and 435 web units; we have 144 and 120.
A4: Segment | B4: Searches | C4: Listings | D4: Total clicks | E4: Clicks / searches
A5: Recreation | B5: 1333 | C5: 4 | D5: 596 | E5: 0.44711178
A6: Mountain | B6: 1027 | C6: 5 | D6: 500 | E6: 0.48685492
A7: Speed | B7: 894 | C7: 9 | D7: 521 | E7: 0.58277405
A10: Segment | B10: Pos | C10: Company | D10: Ad | E10: Brand | F10: SERP 1 | G10: SERP 2 | H10: SERP 3 | I10: Clicks | J10: CTR | K10: Ad judgment | L10: Page $
A11: Recreation | B11: 1 | C11: SpaceBikes | D11: Mars Rover 1 | E11: Mars Rover | F11: Highest rated Recreation bike | G11: Lots of fun to ride | H11: Picture of riders on a greenway | I11: 303 | J11: 0.2273 | K11: 79 | L11: 1000
A12: Recreation | B12: 2 | C12: MILC Bikes | D12: Whole MILC MKII | E12: Whole MILC MKII | F12: Easy riding on a comfort seat | G12: Keep your head high - comfort straight handlebar | H12: Enjoy your ride - carbon fiber light | I12: 144 | J12: 0.108 | K12: 77 | L12: 1000
A13: Recreation | B13: 3 | C13: Bike Bros | D13: Easy Rider | E13: MountainCruise1 | F13: Easy riding on a comfort seat | G13: Keep your head high - comfort straight handlebar | H13: Picture of riders on a greenway | I13: 88 | J13: 0.066 | K13: 75 | L13: 1000
A14: Recreation | B14: 4 | C14: Spoke'd Up | D14: Spoke'd Easy | E14: Spoke'd Easy | F14: Easy riding on a comfort seat | G14: Lots of fun to ride | H14: Keep your head high - comfort straight handlebar | I14: 61 | J14: 0.0458 | K14: 59 | L14: 1000
A15: Mountain | B15: 1 | C15: BB LLC | D15: BB Big Momma | E15: Blu Ruged Ballz | F15: Tackle steep climbs with more gears | G15: Grab the path with high tread tires | H15: Highest rated Mountain bike | I15: 237 | J15: 0.2308 | K15: 81 | L15: 1000
A16: Mountain | B16: 2 | C16: WeBike | D16: HikeBike 1 | E16: Hike Bike | F16: Picture of a rider on a steep trail | G16: Tackle steep climbs with more gears | H16: Grab the path with high tread tires | I16: 115 | J16: 0.112 | K16: 80 | L16: 1000
A17: Mountain | B17: 3 | C17: LiteCycle | D17: Trail Blazing 1 | E17: LiteTrail Pro | F17: Picture of a rider on a steep trail | G17: Mountains are no longer difficult | H17: Have an adventure on a carbon bike! | I17: 69 | J17: 0.0672 | K17: 79 | L17: 1000
A18: Mountain | B18: 4 | C18: Bike Bros | D18: TerraTech | E18: TERRAMAX | F18: Picture of a rider on a steep trail | G18: Go anywhere on a tough carbon bike | H18: Local sales & service | I18: 46 | J18: 0.0448 | K18: 78 | L18: 1000
A19: Mountain | B19: 5 | C19: Bike Bros | D19: Mountainability | E19: TERRAMAX | F19: Picture of a rider on a steep trail | G19: Have an adventure on a carbon bike! | H19: Tackle steep climbs with more gears | I19: 33 | J19: 0.0321 | K19: 77 | L19: 1000
A20: Speed | B20: 1 | C20: BB LLC | D20: Unleash lil pap | E20: Blu Tube Ballz | F20: Ride a wind-cheater | G20: Roll fast with racing tires | H20: Elite look - a ride of distinction | I20: 200 | J20: 0.2237 | K20: 76 | L20: 1000
A21: Speed | B21: 2 | C21: SpaceBikes | D21: The Armstrong 1 | E21: The Armstrong | F21: Highest rated Speed bike | G21: Picture of road race | H21: Fast and furious | I21: 98 | J21: 0.1096 | K21: 77 | L21: 1000
A22: Speed | B22: 3 | C22: LiteCycle | D22: Speed of Lite 1 | E22: LiteSpeed Pro+ | F22: Picture of road race | G22: Ride a wind-cheater | H22: Elite look - a ride of distinction | I22: 61 | J22: 0.0682 | K22: 77 | L22: 1000
... A28: Speed | B28: 9 | C28: Spoke'd Up | D28: Spoke'd Speed | E28: Spoke'd Speed | F28: Fast and furious | G28: Ride a wind-cheater | H28: Roll fast with racing tires | I28: 21 | J28: 0.0235 | K28: 57 | L28: 1000
A31: COMPANY TOTALS | B31: Organic clicks | C31: Web demand | D31: Web units per click | E31: Note
A32: BB LLC | B32: 437 | C32: 569 | D32: 1.3020595 | E32: best; #1 Mountain + #1 Speed, no Rec page
A33: SpaceBikes | B33: 401 | C33: 491 | D33: 1.2244389
A34: Bike Bros | B34: 213 | C34: 0 | D34: 0 | E34: 213 clicks, 0 web centre -> organic without ops captures nothing online
A35: MILC Bikes | B35: 187 | C35: 435 | D35: 2.3262032
A36: LiteCycle | B36: 153 | C36: 435 | D36: 2.8431373 | E36: almost our traffic, 3.6x our web sales
A37: WeBike | B37: 144 | C37: 120 | D37: 0.83333333 | E37: 6th of 7; 115 Mountain + 29 Speed + 0 Rec
A38: Spoke'd Up | B38: 82 | C38: 138 | D38: 1.6829268
A41: CTR BY POSITION (clicks / searches) — almost identical across segments | B41: Recreation | C41: Mountain | D41: Speed
A42: Position 1 | B42: 0.2273 | C42: 0.2308 | D42: 0.2237
A43: Position 2 | B43: 0.108 | C43: 0.112 | D43: 0.1096
A44: Position 3 | B44: 0.066 | C44: 0.0672 | D44: 0.0682
A45: Position 4 | B45: 0.0458 | C45: 0.0448 | D45: 0.0481
A46: Position 5 | C46: 0.0321 | D46: 0.0324
A47: Position 6 | D47: 0.0257
A48: Position 7 | D48: 0.0257
A49: Position 8 | D49: 0.0257
A50: Position 9 | D50: 0.0235
A51: Read | D51: Position 1 always takes ~22-23% of searches, position 2 ~11%, position 3 ~6.7%. CTR is a function of RANK, not ad judgment. Ad judgment sets rank in Rec and Mountain (monotonic) but NOT in Speed (AndStill 78 sits at #7).
A54: SERP MECHANICS | B54: Finding
A55: Web page investment | B55: Every listing is $1,000. No one spent more. Page $ is not a Q3 lever.
A56: Brand name on SERP | B56: HikeBike 1 locked rank 1 = Mention brand name, but the snippet is picture / gears / tires (locked ranks 2-4). Brand fills the Ad/Brand columns; it does NOT consume a content slot. SERP shows the next three benefits.
A57: Picture-first underperforms | B57: Rec #1 and Mountain #1 lead with a CLAIM (Highest rated / gears). Our Mountain page leads with a picture and sits #2. Speed positions 3-8 almost all lead with the road-race picture; positions 1-2 do not.
A58: Two pages in one segment cannibalize | B58: Bike Bros 2 Mountain ads = 79 clicks vs our one page at 115. Their 2 Speed ads both stall at 23 clicks. Do not add a second page.
A61: COPY vs WINNERS | B61: SERP 1 | C61: SERP 2 | D61: SERP 3 | E61: Ad j | F61: Pos | G61: Clicks
A62: BB LLC Mountain (best) | B62: Tackle steep climbs with more gears | C62: Grab the path with high tread tires | D62: Highest rated Mountain bike | E62: 81 | F62: 1 | G62: 237
A63: WeBike HikeBike 1 | B63: Picture of a rider on a steep trail | C63: Tackle steep climbs with more gears | D63: Grab the path with high tread tires | E63: 80 | F63: 2 | G63: 115
A64: BB LLC Speed (best) | B64: Ride a wind-cheater | C64: Roll fast with racing tires | D64: Elite look - a ride of distinction | E64: 76 | F64: 1 | G64: 200
A65: WeBike Swift Bike | B65: Picture of road race | C65: Enjoy your ride - carbon fiber light | D65: Carbon fiber quality at a great price | E65: 70 | F65: 5 | G65: 29
A66: Read | G66: HikeBike 1 is one point and one picture away from the #1 recipe; Hike Bike IS tied for highest-rated Mountain so we can claim it. Swift Bike SERP is Rec-coded (enjoy your ride) plus HikeBike 1's price claim. Speed is the least price-sensitive segment. This CONFIRMS the Q3_Ad_Judgment clone hypothesis with the actual copy.
A69: Q4 SEM ACTIONS (not locked) | B69: Decision
A70: Organic is not the web problem | B70: 144 vs LiteCycle 153 clicks, 120 vs 435 web units. Rebuild web staff 3->7 and fund all 4 tactics. That is the +315 unit / +$189,800 case.
A71: Swift Bike ad | B71: REDESIGN SERP around Speed cues. Target top 3 after brand: wind-cheater / racing tires / elite look (or Highest rated Speed bike once design hits 77). Drop 'great price' and 'enjoy your ride'. Already required for Marketing Effectiveness 0.7675.
A72: HikeBike 1 | B72: KEEP as the default. 80 vs 81, position 2 of 5. Optional cheap tweak if we are already in Ad Design: rank gears / tires / Highest rated Mountain bike so the snippet matches BB LLC. Do not pay a full redesign fee for one point.
A73: Recreation page | B73: Do not add. No Rec brand; Rec winners all lead with comfort-seat copy we cannot truthfully run on Hike Bike.
A74: Second page in a segment | B74: Do not. Bike Bros split themselves and finished last.
A75: Page investment | B75: Leave at $1,000 until a rival demonstrates that spending more moves rank.

Sheet Q3_Competitor_Profiles
A1: Competitors' Profiles — Q3 actual (EXACT from Workspace report)
A2: Source: Competitors' Profiles, results of previous quarter (Quarter 3). These numbers SUPERSEDE chart-read approximations in Q3_Industry_Graphs. Biggest correction: BB LLC fixed capacity is 24, not 16; they schedule all 24 plus 6.90 overtime. WeBike / BB LLC / MILC are tied at 24 printers; SpaceBikes owns 32.
A4: Metric | B4: Bike Bros | C4: LiteCycle | D4: WeBike | E4: BB LLC | F4: Spoke'd Up | G4: SpaceBikes | H4: MILC Bikes
A5: BSC (Q3 quarterly, rounded) | B5: 1 | C5: 3 | D5: 0 | E5: 22 | F5: 2 | G5: 11 | H5: 3
A6: Total demand | B6: 490 | C6: 984 | D6: 627 | E6: 1507 | F6: 854 | G6: 1298 | H6: 799
A7: Number of brands | B7: 5 | C7: 3 | D7: 2 | E7: 4 | F7: 2 | G7: 2 | H7: 2
A8: Average price | B8: 1475 | C8: 1380 | D8: 1408 | E8: 1473 | F8: 1249 | G8: 1340 | H8: 1250
A9: Best Rec brand (>=70) | B9: 76 MountainCruise1 | C9: N/A | D9: N/A | E9: N/A | F9: 73 Spoke'd Easy | G9: 73 Mars Rover | H9: 74 Whole MILC MKII
A10: Best Mountain brand (>=70) | B10: 73 TERRAMAX | C10: 70 LiteTrail Pro | D10: 73 Hike Bike | E10: 73 Blu Ruged Ballz | F10: N/A | G10: N/A | H10: N/A
A11: Best Speed brand (>=70) | B11: 77 MACH I.I | C11: 77 LiteSpeed Pro+ | D11: 72 Swift Bike | E11: 76 Blu Tube Ballz | F11: 75 Spoke'd Speed | G11: 76 The Armstrong | H11: 76 Skim MILC MKII
A12: Regional inserts | B12: 10 | C12: 12 | D12: 19 | E12: 24 | F12: 12 | G12: 17 | H12: 12
A13: Web pages | B13: 5 | C13: 3 | D13: 2 | E13: 2 | F13: 2 | G13: 2 | H13: 2
A14: Organic SEM clicks | B14: 213 | C14: 153 | D14: 144 | E14: 437 | F14: 82 | G14: 401 | H14: 187
A15: Organic SEM expenses | B15: 5000 | C15: 3000 | D15: 2000 | E15: 2000 | F15: 2000 | G15: 2000 | H15: 2000
A16: Best Rec ad (>=70) | B16: 75 Easy Rider | C16: N/A | D16: N/A | E16: N/A | F16: N/A | G16: 79 Mars Rover 1 | H16: 77 Whole MILC MKII
A17: Best Mountain ad (>=70) | B17: 78 TerraTech | C17: 79 Trail Blazing 1 | D17: 80 HikeBike 1 | E17: 81 BB Big Momma | F17: N/A | G17: N/A | H17: N/A
A18: Best Speed ad (>=70) | B18: 78 AndStill | C18: 77 Speed of Lite 1 | D18: 70 Swift Bike | E18: 76 Unleash lil pap | F18: N/A | G18: 77 The Armstrong 1 | H18: 75 Skim MILC MKII
A19: Stores | B19: 1 | C19: 2 | D19: 2 | E19: 2 | F19: 2 | G19: 2 | H19: 1
A20: Store sales force | B20: 7 | C20: 10 | D20: 11 | E20: 14 | F20: 11 | G20: 14 | H20: 7
A21: Web sales centers | B21: 0 | C21: 1 | D21: 1 | E21: 1 | F21: 1 | G21: 1 | H21: 1
A22: Web sales force | B22: 0 | C22: 7 | D22: 3 | E22: 7 | F22: 3 | G22: 7 | H22: 7
A23: Web productivity features | B23: 0 | C23: 4 | D23: 1 | E23: 4 | F23: 2 | G23: 4 | H23: 4
A24: Sales compensation | B24: 22060 | C24: 25736 | D24: 24425 | E24: 27402 | F24: 24511 | G24: 24711 | H24: 27630
A25: Sales productivity [%] | B25: 68 | C25: 73 | D25: 70 | E25: 78 | F25: 71 | G25: 74 | H25: 70
A26: Fixed capacity / day | B26: 16 | C26: 16 | D26: 24 | E26: 24 | F26: 16 | G26: 32 | H26: 24
A27: Operating capacity / day | B27: 15 | C27: 14 | D27: 8 | E27: 24 | F27: 15 | G27: 30 | H27: 17
A28: Overtime capacity / day | B28: 0 | C28: 1.75 | D28: 1 | E28: 6.9 | F28: 1.88 | G28: 0 | H28: 0
A29: Worker compensation | B29: 19609 | C29: 21622 | D29: 20757 | E29: 23042 | F29: 20757 | G29: 21004 | H29: 23293
A30: Worker productivity [%] | B30: 70 | C30: 74 | D30: 72 | E30: 75 | F30: 72 | G30: 73 | H30: 73
A33: CAPACITY — derived (exact) | B33: Fixed / day | C33: Scheduled OC / day | D33: OT / day | E33: Effective (OC+OT) | F33: OC / fixed | G33: Demand
A34: BB LLC | B34: 24 | C34: 24 | D34: 6.9 | E34: 30.9 | F34: 1 | G34: 1507
A35: SpaceBikes | B35: 32 | C35: 30 | D35: 0 | E35: 30 | F35: 0.9375 | G35: 1298
A36: MILC Bikes | B36: 24 | C36: 17 | D36: 0 | E36: 17 | F36: 0.70833333 | G36: 799
A37: Spoke'd Up | B37: 16 | C37: 15 | D37: 1.88 | E37: 16.88 | F37: 0.9375 | G37: 854
A38: LiteCycle | B38: 16 | C38: 14 | D38: 1.75 | E38: 15.75 | F38: 0.875 | G38: 984
A39: Bike Bros | B39: 16 | C39: 15 | D39: 0 | E39: 15 | F39: 0.9375 | G39: 490
A40: WeBike | B40: 24 | C40: 8 | D40: 1 | E40: 9 | F40: 0.33333333 | G40: 627
A43: CHART-READ CORRECTIONS (Strategic Graphs were off) | B43: Chart-read | C43: Exact | D43: What changes
A44: BB LLC fixed capacity | B44: 16 | C44: 24 | D44: They bought the SAME 3 printers we did. 'Buys flexibility not printers' is FALSE.
A45: BB LLC scheduled OC | B45: 15 | C45: 24 | D45: They schedule 100% of owned capacity, then add 6.90 OT on top.
A46: MILC scheduled OC | B46: 24 | C46: 17 | D46: MILC owns 24 but schedules only 17 (70.8% of owned). Still well above us.
A47: LiteCycle scheduled OC | B47: 15 | C47: 14 | D47: Off by 1; rank unchanged.
A48: Spoke'd Up scheduled OC | B48: 14 | C48: 15 | D48: Off by 1; rank unchanged.
A49: WeBike OC / OT / fixed | B49: 8 / 1 / 24 | C49: 8 / 1.00 / 24 | D49: Confirmed. Last on OC. Only firm that reduced OC in Q3 (from graphs).
A50: Fixed-capacity ranking | B50: SpaceBikes 32, WeBike/MILC 24, rest 16 | C50: SpaceBikes 32; WeBike = BB LLC = MILC 24; rest 16 | D50: Three firms own 24, not two. We are tied for 2nd, and we used the least.
A53: BB LLC IS THE CAPACITY GOLD STANDARD | B53: Value | C53: Note
A54: BB LLC effective capacity (OC+OT) | B54: 30.9 | C54: Highest in the industry, slightly above SpaceBikes' 30
A55: Implied output at 75% x 65 days | B55: 1506.4 | C55: Matches their 1,507 demand almost exactly — they scheduled TO demand
A56: WeBike implied output at 72% x 65 days | B56: 421.2 | C56: Matches the 423 units we actually produced; 204 demand went unfilled
A57: SpaceBikes model | B57: 32 owned, 30 scheduled, 0 OT | C57: Own more printers, no overtime. Served 1,298 with slack.
A58: BB LLC model | B58: 24 owned, 24 scheduled, 6.90 OT | C58: Same printers as us, sweat them with OT + 75% worker productivity.
A59: WeBike model | B59: 24 owned, 8 scheduled, 1.00 OT | C59: Same printers as the leader, used one-third of them.
A60: Q4 read | C60: Matching BB LLC's 1,507 units on 24 printers is possible (full OC + ~7 OT + 75% productivity). Rio+web (scenario D, 1,171) fits inside 24 with a little OT. New York (scenario E, 1,571) still needs a 4th printer.
A63: COMPENSATION vs PRODUCTIVITY (exact) | B63: Sales pay | C63: Sales prod % | D63: vs sales avg | E63: Worker pay | F63: Worker prod % | G63: vs worker avg
A64: BB LLC | B64: 27402 | C64: 78 | D64: 2191.2857 | E64: 23042 | F64: 75 | G64: 1601.4286
A65: SpaceBikes | B65: 24711 | C65: 74 | D65: -499.71429 | E65: 21004 | F65: 73 | G65: -436.57143
A66: LiteCycle | B66: 25736 | C66: 73 | D66: 525.28571 | E66: 21622 | F66: 74 | G66: 181.42857
A67: Spoke'd Up | B67: 24511 | C67: 71 | D67: -699.71429 | E67: 20757 | F67: 72 | G67: -683.57143
A68: WeBike | B68: 24425 | C68: 70 | D68: -785.71429 | E68: 20757 | F68: 72 | G68: -683.57143
A69: MILC Bikes | B69: 27630 | C69: 70 | D69: 2419.2857 | E69: 23293 | F69: 73 | G69: 1852.4286
A70: Bike Bros | B70: 22060 | C70: 68 | D70: -3150.7143 | E70: 19609 | F70: 70 | G70: -1831.5714
A73: PAY FINDINGS | B73: Value | C73: Note
A74: Industry sales-pay average | B74: 25211 | C74: WeBike $24,425 is BELOW average — team goal 'pay > average' is currently failing
A75: Industry worker-pay average | B75: 21441 | C75: WeBike $20,757 is BELOW average (tied with Spoke'd Up; only Bike Bros lower)
A76: Sales productivity range | B76: 68 – 78 | C76: Ceiling is 78 (BB LLC), not ~75. Still nowhere near the 85% we planned on.
A77: Worker productivity range | B77: 70 – 75 | C77: Ceiling is 75 (BB LLC). Industry is tight; 85% remains unreachable.
A78: Highest sales pay | B78: MILC $27,630 at 70% prod | C78: Highest pay does NOT equal highest productivity. BB LLC $27,402 → 78%.
A79: Highest worker pay | B79: MILC $23,293 at 73% prod | C79: BB LLC $23,042 → 75% (best productivity). LiteCycle $21,622 → 74%.
A80: Q4 target to meet team goal | B80: Sales > $25,211 · Worker > $21,441 | C80: Upper quartile is sales ~$27.4k (BB LLC/MILC) and worker ~$23.0k. Plan capacity on 73–75% workers, mid-70s sales — never 85%.
A83: CHANNEL (exact) | B83: Stores | C83: Store SF | D83: Web centres | E83: Web SF | F83: Web features / 4 | G83: Total SF | H83: Demand | I83: Demand / SF
A84: BB LLC | B84: 2 | C84: 14 | D84: 1 | E84: 7 | F84: 4 | G84: 21 | H84: 1507 | I84: 71.8
A85: SpaceBikes | B85: 2 | C85: 14 | D85: 1 | E85: 7 | F85: 4 | G85: 21 | H85: 1298 | I85: 61.8
A86: LiteCycle | B86: 2 | C86: 10 | D86: 1 | E86: 7 | F86: 4 | G86: 17 | H86: 984 | I86: 57.9
A87: Spoke'd Up | B87: 2 | C87: 11 | D87: 1 | E87: 3 | F87: 2 | G87: 14 | H87: 854 | I87: 61
A88: MILC Bikes | B88: 1 | C88: 7 | D88: 1 | E88: 7 | F88: 4 | G88: 14 | H88: 799 | I88: 57.1
A89: WeBike | B89: 2 | C89: 11 | D89: 1 | E89: 3 | F89: 1 | G89: 14 | H89: 627 | I89: 44.8
A90: Bike Bros | B90: 1 | C90: 7 | D90: 0 | E90: 0 | F90: 0 | G90: 7 | H90: 490 | I90: 70
A93: CHANNEL FINDINGS | B93: Value | C93: Note
A94: Store counts | B94: 5 firms have 2; Bike Bros AND MILC have 1 | C94: City #3 is still unclaimed. MILC is web-first (confirmed 1 store + 7 web staff + 4 features).
A95: Web feature pattern | B95: 4 tactics → 7 web staff; 1–2 tactics → 3 web staff | C95: Confirmed. WeBike 1 feature / 3 staff; Spoke'd Up 2 / 3; leaders 4 / 7.
A96: Demand per sales person | B96: WeBike 44.8 = LAST | C96: BB LLC 71.8 · Bike Bros 70.0 (one store!) · SpaceBikes 61.8 · Spoke'd Up 61.0
A97: Headcount is NOT at parity | B97: Leaders have 21 (BB LLC, SpaceBikes) | C97: WeBike / Spoke'd Up / MILC = 14. LiteCycle 17. The 'parity at 14' line was wrong — leaders run 50% more people.
A100: MARKETING (exact) | B100: Inserts | C100: SEM clicks | D100: SEM $ | E100: Clicks / $1k | F100: Web pages | G100: Best Mtn ad | H100: Best Speed ad
A101: BB LLC | B101: 24 | C101: 437 | D101: 2000 | E101: 218.5 | F101: 2 | G101: 81 BB Big Momma | H101: 76 Unleash lil pap
A102: SpaceBikes | B102: 17 | C102: 401 | D102: 2000 | E102: 200.5 | F102: 2 | G102: N/A | H102: 77 The Armstrong 1
A103: Bike Bros | B103: 10 | C103: 213 | D103: 5000 | E103: 42.6 | F103: 5 | G103: 78 TerraTech | H103: 78 AndStill
A104: MILC Bikes | B104: 12 | C104: 187 | D104: 2000 | E104: 93.5 | F104: 2 | G104: N/A | H104: 75 Skim MILC MKII
A105: LiteCycle | B105: 12 | C105: 153 | D105: 3000 | E105: 51 | F105: 3 | G105: 79 Trail Blazing 1 | H105: 77 Speed of Lite 1
A106: WeBike | B106: 19 | C106: 144 | D106: 2000 | E106: 72 | F106: 2 | G106: 80 HikeBike 1 | H106: 70 Swift Bike
A107: Spoke'd Up | B107: 12 | C107: 82 | D107: 2000 | E107: 41 | F107: 2 | G107: N/A | H107: N/A
A110: MARKETING FINDINGS | B110: Value | C110: Note
A111: SEM is a quality game, not a budget game | B111: 5 of 7 firms spend $2,000 | C111: BB LLC 437 clicks and SpaceBikes 401 clicks on the SAME $2,000 we spent for 144. Bike Bros spent $5,000 for 213 clicks — worse ROI. Pages don't explain it (BB LLC has 2 pages, we have 2).
A112: Mountain ad | B112: HikeBike 1 = 80, 2nd of 4 | C112: BB Big Momma 81. One point off the top. Do not redesign.
A113: Speed ad | B113: Swift Bike = 70, last of scored ads | C113: Spoke'd Up Speed ad is below 70 (N/A). We are last among anyone who cleared the bar. Redesign.
A114: Average price | B114: WeBike $1,408 = 3rd | C114: Bike Bros $1,475 edges BB LLC $1,473. 'BB LLC highest price' was a $2 rounding error. Rec specialists (Spoke'd Up $1,249, MILC $1,250) sit ~$160 below us.
A115: Brand count ≠ share | B115: Bike Bros 5 brands, 490 demand, BSC 1 | C115: SpaceBikes 2 brands, 1,298 demand, BSC 11. BB LLC 4 brands (2 Mtn + 2 Speed, no Rec >=70). A 3rd brand is still not a Q4 priority.
A116: BB LLC Rec = N/A | B116: No Rec brand or ad >= 70 | C116: 'All 3 segments' is spillover (99 Rec units), not a Rec franchise. They win Mountain + Speed only.
A119: Q3 QUARTERLY BSC (this report, integer) | B119: Score | C119: Demand | D119: Read
A120: BB LLC | B120: 22 | C120: 1507 | D120: Q3 single-quarter leader by a mile
A121: SpaceBikes | B121: 11 | C121: 1298 | D121: Strong Q3 too — cumulative lead plus a double-digit quarter
...

Sheet Q3_Media
A1: Major Media Inserts — World Market, Q3 actual (all 106 industry inserts)
A2: World Market rows sum exactly to the company insert totals, so this IS the whole Major Media Inserts report (not a subset). BB LLC put all 24 inserts in Biking Magazines ($4,500, highest Mountain AND Speed preference) and spent LESS than we did. We cut HikeBike 1 Biking from 12 (Q2) to 6 (Q3) to 'diversify' — that was the mistake.
A4: Company | B4: Inserts | C4: Rank | D4: Insert spend [$] | E4: $ / insert | F4: Biking inserts | G4: Biking % of own buy | H4: Other inserts
A5: BB LLC | B5: 24 | C5: 1 | D5: 108000 | E5: 4500 | F5: 24 | G5: 1 | H5: 0
A6: WeBike | B6: 19 | C6: 2 | D6: 116000 | E6: 6105 | F6: 10 | G6: 0.52631579 | H6: 9
A7: SpaceBikes | B7: 17 | C7: 3 | D7: 132000 | E7: 7765 | F7: 2 | G7: 0.11764706 | H7: 15
A8: LiteCycle | B8: 12 | C8: 4 | D8: 75000 | E8: 6250 | F8: 6 | G8: 0.5 | H8: 6
A9: Spoke'd Up | B9: 12 | C9: 5 | D9: 96000 | E9: 8000 | F9: 2 | G9: 0.16666667 | H9: 10
A10: MILC Bikes | B10: 12 | C10: 6 | D10: 68500 | E10: 5708 | F10: 5 | G10: 0.41666667 | H10: 7
A11: Bike Bros | B11: 10 | C11: 7 | D11: 76000 | E11: 7600 | F11: 2 | G11: 0.2 | H11: 8
A14: THE EFFICIENCY FINDING | B14: Value | C14: Note
A15: BB LLC inserts | B15: 24 | C15: industry high — 100% Biking Magazines
A16: WeBike inserts | B16: 19 | C16: 2nd — but spread across 5 media
A17: BB LLC insert spend [$] | B17: 108000 | C17: 24 x $4,500
A18: WeBike insert spend [$] | B18: 116000 | C18: Health+Biking+Sport+Business+NV+News
A19: WeBike reported ad expense [$] | B19: 119165 | C19: inserts $116k + ~$3,165 web/design
A20: WeBike $ / insert | B20: 6105 | C20: we pay 36% more per insert than BB LLC
A21: BB LLC $ / insert | B21: 4500 | C21: the Biking rate — cheapest medium, best Mtn+Speed pref
A22: Inserts we could have bought at $4,500 with our $116k | B22: 25 | C22: 25 Biking inserts vs the 10 we actually bought
A25: Inserts by medium (industry) | B25: Bike Bros | C25: LiteCycle | D25: WeBike | E25: BB LLC | F25: Spoke'd Up | G25: SpaceBikes | H25: MILC Bikes | I25: Industry
A26: Leisure & Entertainment | B26: 1 | C26: 0 | D26: 0 | E26: 0 | F26: 3 | G26: 2 | H26: 0 | I26: 6
A27: Health & Fitness Magazines | B27: 2 | C27: 0 | D27: 1 | E27: 0 | F27: 2 | G27: 3 | H27: 5 | I27: 13
A28: Biking Magazines | B28: 2 | C28: 6 | D28: 10 | E28: 24 | F28: 2 | G28: 2 | H28: 5 | I28: 51
A29: Sport Magazines | B29: 2 | C29: 1 | D29: 3 | E29: 0 | F29: 2 | G29: 2 | H29: 0 | I29: 10
A30: Business Magazines | B30: 1 | C30: 2 | D30: 1 | E30: 0 | F30: 1 | G30: 2 | H30: 0 | I30: 7
A31: New Venture Magazines | B31: 1 | C31: 2 | D31: 3 | E31: 0 | F31: 1 | G31: 2 | H31: 2 | I31: 11
A32: General News Magazines | B32: 1 | C32: 1 | D32: 1 | E32: 0 | F32: 1 | G32: 4 | H32: 0 | I32: 8
A33: TOTAL | B33: 10 | C33: 12 | D33: 19 | E33: 24 | F33: 12 | G33: 17 | H33: 12 | I33: 106
A36: WEBIKE MIX — Q2 HikeBike1 lock vs Q3 actual | B36: Q2 HikeBike1 | C36: Q3 HikeBike 1 | D36: Q3 Swift Bike | E36: Q3 total | F36: Q2→Q3 Hike change
A37: Leisure & Entertainment | B37: 0 | C37: 0 | D37: 0 | E37: 0 | F37: 0
A38: Health & Fitness Magazines | B38: 1 | C38: 1 | D38: 0 | E38: 1 | F38: 0
A39: Biking Magazines | B39: 12 | C39: 6 | D39: 4 | E39: 10 | F39: -6
A40: Sport Magazines | B40: 2 | C40: 2 | D40: 1 | E40: 3 | F40: 0
A41: Business Magazines | B41: 0 | C41: 0 | D41: 1 | E41: 1 | F41: 0
A42: New Venture Magazines | B42: 0 | C42: 1 | D42: 2 | E42: 3 | F42: 1
A43: General News Magazines | B43: 1 | C43: 1 | D43: 0 | E43: 1 | F43: 0
A44: Inserts | B44: 16 | C44: 11 | D44: 8 | E44: 19 | F44: -5
A45: Spend [$] | B45: 89000 | C45: 67500 | D45: 48500 | E45: 116000 | F45: -21500
A48: IDENTICAL MOUNTAIN PRODUCT — Biking Magazines only | B48: Inserts | C48: Spend [$] | D48: Mountain share | E48: Note
A49: BB LLC BB Big Momma → Blu Ruged Ballz (56/73/1, $1,365) | B49: 12 | C49: 54000 | D49: 0.463 | E49: same design, same price as Hike Bike
A50: WeBike HikeBike 1 → Hike Bike (56/73/1, $1,365) | B50: 6 | C50: 27000 | D50: 0.221 | E50: we ran this at 12 in Q2 and cut it in half
A51: Gap | B51: 6 | C51: 27000 | D51: 0.242 | E51: half the Biking weight, half-ish the share — plus stock-outs
A54: SPEED — Biking Magazines | B54: Inserts | C54: Spend [$] | D54: Speed share | E54: Note
A55: BB LLC Unleash lil pap → Blu Tube Ballz (judgment 76, $1,580) | B55: 12 | C55: 54000 | E55: their advertised Speed brand
